{
  "version": 1,
  "createdAt": "2025-12-09T19:22:12.317Z",
  "blocks": [
    {
      "id": "estrategia_es_QA_50_enriquecido__001",
      "title": "¿Cuál es la visión central de la Estrategia de Desarrollo para la Educación Superior 2026–2038?",
      "source": "Estrategia ES.pdf",
      "text": "Q: ¿Cuál es la visión central de la Estrategia de Desarrollo para la Educación Superior 2026–2038?\n\nA: La visión propone un sistema de educación superior sostenible, dinámico y orientado estratégicamente, que integra docencia, investigación, innovación y vinculación con el medio. Mediante sinergias entre instituciones y subsistemas, el sistema debe producir capacidades efectivas para responder a desafíos sociales y tecnológicos, consolidarse como referente internacional y contribuir al desarrollo sostenible, la cohesión social y la equidad territorial.\n\nVariantes:\n- ¿Qué declara la visión del sistema de educación superior para 2026–2038?\n- ¿Cómo se describe el estado futuro deseado de la educación superior en la Estrategia?\n- Resume la visión proyectada para el sistema de educación superior en Chile\n- ¿Qué metas integrales plantea la visión de la Estrategia?\n\n\nMeta:\n- País: Chile\n- Periodo: 2026–2038\n- Sección: Visión (p.15)\n- Audiencia: policymakers,IES,docentes\n- Documento: Estrategia ES.pdf\n- Tags: visión, sostenibilidad, sinergias",
      "tags": [
        "visión",
        "sostenibilidad",
        "sinergias"
      ],
      "meta": {
        "country": "Chile",
        "timeframe": "2026–2038",
        "section": "Visión (p.15)",
        "audience": "policymakers,IES,docentes",
        "base": "estrategia_es_QA_50_enriquecido"
      }
    },
    {
      "id": "estrategia_es_QA_50_enriquecido__002",
      "title": "¿Cómo se estructura la Estrategia en términos de elementos clave (visión, principios, nudos, desafíos, objetivos y líneas de acción)?",
      "source": "Estrategia ES.pdf",
      "text": "Q: ¿Cómo se estructura la Estrategia en términos de elementos clave (visión, principios, nudos, desafíos, objetivos y líneas de acción)?\n\nA: La Estrategia se organiza jerárquicamente: una visión orientadora, principios transversales, nudos críticos que diagnostican problemas clave, desafíos estratégicos que fijan prioridades de transformación, objetivos estratégicos que prescriben la dirección del cambio y líneas de acción específicas, acotadas en el tiempo y con asignación institucional clara para operacionalizar esos objetivos.\n\nVariantes:\n- ¿Cuáles son los componentes que organizan la Estrategia?\n- Describe la organización jerárquica de la Estrategia de Educación Superior\n- ¿Qué papel cumplen visión, principios y nudos críticos en la Estrategia?\n- ¿Cómo se conectan desafíos, objetivos y líneas de acción?\n\n\nMeta:\n- País: Chile\n- Periodo: 2026–2038\n- Sección: Organización (p.12–14)\n- Audiencia: policymakers,IES\n- Documento: Estrategia ES.pdf\n- Tags: organización, principios, nudos-críticos",
      "tags": [
        "organización",
        "principios",
        "nudos-críticos"
      ],
      "meta": {
        "country": "Chile",
        "timeframe": "2026–2038",
        "section": "Organización (p.12–14)",
        "audience": "policymakers,IES",
        "base": "estrategia_es_QA_50_enriquecido"
      }
    },
    {
      "id": "estrategia_es_QA_50_enriquecido__003",
      "title": "¿Qué caracteriza el Desafío Estratégico 1 sobre trayectorias formativas flexibles y articuladas?",
      "source": "Estrategia ES.pdf",
      "text": "Q: ¿Qué caracteriza el Desafío Estratégico 1 sobre trayectorias formativas flexibles y articuladas?\n\nA: El Desafío 1 propone transitar hacia trayectorias flexibles y articuladas que reconozcan diversidad de necesidades y promuevan desarrollo integral. Persigue pertinencia frente a desafíos sociales, culturales y productivos, y sitúa el aprendizaje a lo largo de la vida como marco para conectar subsistemas, modalidades y programas.\n\nVariantes:\n- ¿En qué consiste el Desafío 1 de la Estrategia?\n- Explica el foco del desafío sobre trayectorias flexibles\n- ¿Qué busca el sistema respecto de itinerarios formativos?\n- ¿Qué relación tiene con aprendizaje a lo largo de la vida?\n\n\nMeta:\n- País: Chile\n- Periodo: 2026–2038\n- Sección: Desafío 1 (p.16)\n- Audiencia: IES,docentes,estudiantes\n- Documento: Estrategia ES.pdf\n- Tags: trayectorias, flexibilidad, lifelong-learning",
      "tags": [
        "trayectorias",
        "flexibilidad",
        "lifelong-learning"
      ],
      "meta": {
        "country": "Chile",
        "timeframe": "2026–2038",
        "section": "Desafío 1 (p.16)",
        "audience": "IES,docentes,estudiantes",
        "base": "estrategia_es_QA_50_enriquecido"
      }
    },
    {
      "id": "estrategia_es_QA_50_enriquecido__004",
      "title": "¿Qué cambios institucionales y formativos plantea el Objetivo 1.1 para habilitar trayectorias articuladas y diversas?",
      "source": "Estrategia ES.pdf",
      "text": "Q: ¿Qué cambios institucionales y formativos plantea el Objetivo 1.1 para habilitar trayectorias articuladas y diversas?\n\nA: El Objetivo 1.1 promueve cambios institucionales y formativos para articular, diversificar y flexibilizar las trayectorias, fortaleciendo eficiencia y conexión con contextos de aprendizaje permanente. Se materializa en adecuar títulos y grados, reconocer aprendizajes previos y consolidar un sistema nacional de cualificaciones.\n\nVariantes:\n- ¿Cómo potenciar trayectorias articuladas según el Objetivo 1.1?\n- ¿Qué ajustes institucionales propone el Objetivo 1.1?\n- Resume las orientaciones del Objetivo 1.1\n- ¿Qué resultados persigue el Objetivo 1.1?\n\n\nMeta:\n- País: Chile\n- Periodo: 2026–2038\n- Sección: Objetivo 1.1 y líneas 1.1.1–1.1.3 (p.17)\n- Audiencia: IES,policymakers\n- Documento: Estrategia ES.pdf\n- Tags: objetivo-1.1, cualificaciones, RAP",
      "tags": [
        "objetivo-1.1",
        "cualificaciones",
        "RAP"
      ],
      "meta": {
        "country": "Chile",
        "timeframe": "2026–2038",
        "section": "Objetivo 1.1 y líneas 1.1.1–1.1.3 (p.17)",
        "audience": "IES,policymakers",
        "base": "estrategia_es_QA_50_enriquecido"
      }
    },
    {
      "id": "estrategia_es_QA_50_enriquecido__005",
      "title": "¿Qué busca la línea de acción 1.1.1 al adecuar la estructura de títulos y grados?",
      "source": "Estrategia ES.pdf",
      "text": "Q: ¿Qué busca la línea de acción 1.1.1 al adecuar la estructura de títulos y grados?\n\nA: La 1.1.1 persigue desarrollar trayectorias más conectadas con el aprendizaje permanente, aumentando flexibilidad, innovación y eficiencia formativa, y mejorando la articulación entre subsistemas, modalidades y programas mediante una revisión y adecuación de títulos y grados.\n\nVariantes:\n- ¿Para qué se adecúa la estructura de títulos y grados (1.1.1)?\n- ¿Qué impacto tiene actualizar títulos y grados en trayectorias?\n- Explica el propósito de la línea 1.1.1\n- ¿Cómo contribuye la 1.1.1 a la flexibilidad e innovación?\n\n\nMeta:\n- País: Chile\n- Periodo: 2026–2038\n- Sección: Línea 1.1.1 (p.17)\n- Audiencia: IES\n- Documento: Estrategia ES.pdf\n- Tags: línea-1.1.1, títulos-y-grados, flexibilidad",
      "tags": [
        "línea-1.1.1",
        "títulos-y-grados",
        "flexibilidad"
      ],
      "meta": {
        "country": "Chile",
        "timeframe": "2026–2038",
        "section": "Línea 1.1.1 (p.17)",
        "audience": "IES",
        "base": "estrategia_es_QA_50_enriquecido"
      }
    },
    {
      "id": "estrategia_es_QA_50_enriquecido__006",
      "title": "¿Cómo se consolida el reconocimiento de aprendizajes previos según la línea 1.1.2?",
      "source": "Estrategia ES.pdf",
      "text": "Q: ¿Cómo se consolida el reconocimiento de aprendizajes previos según la línea 1.1.2?\n\nA: La 1.1.2 busca consolidar mecanismos de reconocimiento y validación de aprendizajes previos, formales y no formales, valorizándolos en los procesos formativos mediante credenciales y microcredenciales para facilitar acceso, progresión y articulación.\n\nVariantes:\n- ¿Qué mecanismos propone la 1.1.2 para reconocer aprendizajes previos?\n- ¿Cómo se incorporan credenciales y microcredenciales?\n- ¿Qué aporta el RAP a trayectorias flexibles?\n- Explica la finalidad de la 1.1.2\n\n\nMeta:\n- País: Chile\n- Periodo: 2026–2038\n- Sección: Línea 1.1.2 (p.17)\n- Audiencia: IES,estudiantes\n- Documento: Estrategia ES.pdf\n- Tags: línea-1.1.2, RAP, microcredenciales",
      "tags": [
        "línea-1.1.2",
        "RAP",
        "microcredenciales"
      ],
      "meta": {
        "country": "Chile",
        "timeframe": "2026–2038",
        "section": "Línea 1.1.2 (p.17)",
        "audience": "IES,estudiantes",
        "base": "estrategia_es_QA_50_enriquecido"
      }
    },
    {
      "id": "estrategia_es_QA_50_enriquecido__007",
      "title": "¿Qué rol cumple el sistema nacional de cualificaciones descrito en la línea 1.1.3?",
      "source": "Estrategia ES.pdf",
      "text": "Q: ¿Qué rol cumple el sistema nacional de cualificaciones descrito en la línea 1.1.3?\n\nA: La 1.1.3 apunta a integrar el Marco de Cualificaciones Técnico‑Profesional con el subsistema universitario y el sector laboral, mejorando pertinencia de competencias, legibilidad de credenciales y su articulación en el sistema, habilitando movilidad formativa y laboral.\n\nVariantes:\n- ¿Cómo integra el sistema de cualificaciones al subsistema universitario y laboral?\n- ¿Qué mejora en legibilidad y pertinencia de credenciales propone la 1.1.3?\n- Explica la articulación del MCTP con el sistema universitario\n- ¿Qué beneficios trae para movilidad formativa y laboral?\n\n\nMeta:\n- País: Chile\n- Periodo: 2026–2038\n- Sección: Línea 1.1.3 (p.17)\n- Audiencia: policymakers,IES\n- Documento: Estrategia ES.pdf\n- Tags: línea-1.1.3, cualificaciones, pertinencia",
      "tags": [
        "línea-1.1.3",
        "cualificaciones",
        "pertinencia"
      ],
      "meta": {
        "country": "Chile",
        "timeframe": "2026–2038",
        "section": "Línea 1.1.3 (p.17)",
        "audience": "policymakers,IES",
        "base": "estrategia_es_QA_50_enriquecido"
      }
    },
    {
      "id": "estrategia_es_QA_50_enriquecido__008",
      "title": "¿Qué propone el Objetivo 1.2 para fortalecer transiciones entre educación media, superior y trabajo?",
      "source": "Estrategia ES.pdf",
      "text": "Q: ¿Qué propone el Objetivo 1.2 para fortalecer transiciones entre educación media, superior y trabajo?\n\nA: El Objetivo 1.2 busca robustecer mecanismos de apoyo a la transición hacia la educación superior y al mundo del trabajo, fomentando vínculos interinstitucionales, habilidades para colaborar con educación secundaria y formación profesional, e impulsando programas de formación docente inicial y desarrollo profesional.\n\nVariantes:\n- ¿Cómo apoya el Objetivo 1.2 la articulación de subsistemas?\n- ¿Qué vínculos y habilidades institucionales impulsa el 1.2?\n- Resume las medidas del Objetivo 1.2\n- ¿Qué resultados busca respecto de equidad en transiciones?\n\n\nMeta:\n- País: Chile\n- Periodo: 2026–2038\n- Sección: Objetivo 1.2 y líneas 1.2.1–1.2.3 (p.17)\n- Audiencia: IES,policymakers,docentes\n- Documento: Estrategia ES.pdf\n- Tags: objetivo-1.2, transiciones, vinculación",
      "tags": [
        "objetivo-1.2",
        "transiciones",
        "vinculación"
      ],
      "meta": {
        "country": "Chile",
        "timeframe": "2026–2038",
        "section": "Objetivo 1.2 y líneas 1.2.1–1.2.3 (p.17)",
        "audience": "IES,policymakers,docentes",
        "base": "estrategia_es_QA_50_enriquecido"
      }
    },
    {
      "id": "estrategia_es_QA_50_enriquecido__009",
      "title": "¿Cómo potencia el Objetivo 1.3 la calidad y pertinencia de la docencia universitaria?",
      "source": "Estrategia ES.pdf",
      "text": "Q: ¿Cómo potencia el Objetivo 1.3 la calidad y pertinencia de la docencia universitaria?\n\nA: El Objetivo 1.3 impulsa calidad y pertinencia mediante una certificación nacional voluntaria de docentes, estándares y condiciones para quienes ejercen docencia fuera de planta regular, y el fortalecimiento de la innovación e investigación en docencia para anticipar cambios en aprendizaje ante diversidad y tecnologización.\n\nVariantes:\n- ¿Qué instrumentos se proponen para fortalecer docencia (1.3)?\n- ¿Qué lugar ocupa la innovación e investigación en enseñanza?\n- Resume las acciones del Objetivo 1.3\n- ¿Cómo responde a diversidad y tecnologización del aula?\n\n\nMeta:\n- País: Chile\n- Periodo: 2026–2038\n- Sección: Objetivo 1.3 y líneas 1.3.1–1.3.3 (p.18)\n- Audiencia: docentes,IES\n- Documento: Estrategia ES.pdf\n- Tags: objetivo-1.3, certificación-docente, innovación-docente",
      "tags": [
        "objetivo-1.3",
        "certificación-docente",
        "innovación-docente"
      ],
      "meta": {
        "country": "Chile",
        "timeframe": "2026–2038",
        "section": "Objetivo 1.3 y líneas 1.3.1–1.3.3 (p.18)",
        "audience": "docentes,IES",
        "base": "estrategia_es_QA_50_enriquecido"
      }
    },
    {
      "id": "estrategia_es_QA_50_enriquecido__010",
      "title": "¿Qué instrumentos de política pública contempla el Objetivo 1.4 para gestionar diversidad y asegurar resultados?",
      "source": "Estrategia ES.pdf",
      "text": "Q: ¿Qué instrumentos de política pública contempla el Objetivo 1.4 para gestionar diversidad y asegurar resultados?\n\nA: El 1.4 propone expandir y coordinar programas de acceso y permanencia; desarrollar información e indicadores para caracterizar diversidad (edad, género, origen cultural y socioeconómico); fortalecer mediciones de calidad que representen diversidad y resultados; y ofrecer modelos de formación general para habilidades inter e intrapersonales y ciudadanas.\n\nVariantes:\n- ¿Qué sistemas de información y medición propone el 1.4?\n- ¿Cómo se expanden programas de acceso y permanencia?\n- ¿Qué es la formación general complementaria según el 1.4?\n- ¿Cómo se monitorean empleabilidad y proyectos de vida?\n\n\nMeta:\n- País: Chile\n- Periodo: 2026–2038\n- Sección: Objetivo 1.4 y líneas 1.4.1–1.4.4 (p.18)\n- Audiencia: IES,policymakers\n- Documento: Estrategia ES.pdf\n- Tags: objetivo-1.4, equidad, sistemas-de-información",
      "tags": [
        "objetivo-1.4",
        "equidad",
        "sistemas-de-información"
      ],
      "meta": {
        "country": "Chile",
        "timeframe": "2026–2038",
        "section": "Objetivo 1.4 y líneas 1.4.1–1.4.4 (p.18)",
        "audience": "IES,policymakers",
        "base": "estrategia_es_QA_50_enriquecido"
      }
    },
    {
      "id": "estrategia_es_QA_50_enriquecido__011",
      "title": "¿Qué políticas y mecanismos de bienestar estudiantil impulsa el Objetivo 1.5?",
      "source": "Estrategia ES.pdf",
      "text": "Q: ¿Qué políticas y mecanismos de bienestar estudiantil impulsa el Objetivo 1.5?\n\nA: El 1.5 promueve políticas de bienestar y cuidado integral en IES, articulación de redes con actores del entorno, expansión y enriquecimiento de la experiencia estudiantil como componente central de la formación y sistemas de monitoreo y balance para equilibrar carga académica considerando factores de riesgo.\n\nVariantes:\n- ¿Cómo se articulan redes de bienestar según el 1.5?\n- ¿Qué sistemas de monitoreo de carga académica se proponen?\n- ¿Qué significa situar la experiencia estudiantil como componente central?\n- ¿Qué objetivos persigue el cuidado integral en IES?\n\n\nMeta:\n- País: Chile\n- Periodo: 2026–2038\n- Sección: Objetivo 1.5 y líneas 1.5.1–1.5.4 (p.19)\n- Audiencia: IES,estudiantes\n- Documento: Estrategia ES.pdf\n- Tags: objetivo-1.5, bienestar, experiencia-estudiantil",
      "tags": [
        "objetivo-1.5",
        "bienestar",
        "experiencia-estudiantil"
      ],
      "meta": {
        "country": "Chile",
        "timeframe": "2026–2038",
        "section": "Objetivo 1.5 y líneas 1.5.1–1.5.4 (p.19)",
        "audience": "IES,estudiantes",
        "base": "estrategia_es_QA_50_enriquecido"
      }
    },
    {
      "id": "estrategia_es_QA_50_enriquecido__012",
      "title": "¿Qué define el Desafío Estratégico 2 respecto de generación de conocimiento e innovación como valor público?",
      "source": "Estrategia ES.pdf",
      "text": "Q: ¿Qué define el Desafío Estratégico 2 respecto de generación de conocimiento e innovación como valor público?\n\nA: El Desafío 2 busca fortalecer procesos de generación de conocimiento, investigación e innovación en educación superior, constituyéndolos como valor público que produce capacidades para abordar desafíos de la sociedad del conocimiento y el desarrollo sostenible nacional.\n\nVariantes:\n- ¿Cuál es el foco del Desafío 2?\n- Explica el énfasis en investigación e innovación como valor público\n- ¿Qué capacidades se buscan para la sociedad del conocimiento?\n- ¿Cómo se relaciona con desarrollo sostenible del país?\n\n\nMeta:\n- País: Chile\n- Periodo: 2026–2038\n- Sección: Desafío 2 (p.20)\n- Audiencia: IES,policymakers\n- Documento: Estrategia ES.pdf\n- Tags: desafío-2, I+D+i, valor-público",
      "tags": [
        "desafío-2",
        "I+D+i",
        "valor-público"
      ],
      "meta": {
        "country": "Chile",
        "timeframe": "2026–2038",
        "section": "Desafío 2 (p.20)",
        "audience": "IES,policymakers",
        "base": "estrategia_es_QA_50_enriquecido"
      }
    },
    {
      "id": "estrategia_es_QA_50_enriquecido__013",
      "title": "¿Cómo se consolida una institucionalidad robusta para generación de conocimiento e innovación (Objetivo 2.1)?",
      "source": "Estrategia ES.pdf",
      "text": "Q: ¿Cómo se consolida una institucionalidad robusta para generación de conocimiento e innovación (Objetivo 2.1)?\n\nA: El 2.1 propone coordinar agencias rectoras de educación y CTCI, fortalecer incentivos a investigación asociativa con impacto público y desarrollar instrumentos para innovación e investigación aplicada en el subsistema técnico‑profesional, articulando políticas y subsistemas.\n\nVariantes:\n- ¿Qué coordinación interagencial propone el 2.1?\n- ¿Cómo incentivar investigación asociativa e impacto público?\n- ¿Qué instrumentos para innovación en el técnico‑profesional?\n- Resume el Objetivo 2.1\n\n\nMeta:\n- País: Chile\n- Periodo: 2026–2038\n- Sección: Objetivo 2.1 y líneas 2.1.1–2.1.3 (p.21)\n- Audiencia: policymakers,IES\n- Documento: Estrategia ES.pdf\n- Tags: objetivo-2.1, institucionalidad, investigación-asociativa",
      "tags": [
        "objetivo-2.1",
        "institucionalidad",
        "investigación-asociativa"
      ],
      "meta": {
        "country": "Chile",
        "timeframe": "2026–2038",
        "section": "Objetivo 2.1 y líneas 2.1.1–2.1.3 (p.21)",
        "audience": "policymakers,IES",
        "base": "estrategia_es_QA_50_enriquecido"
      }
    },
    {
      "id": "estrategia_es_QA_50_enriquecido__014",
      "title": "¿Qué ecosistema de postgrado se impulsa en el Objetivo 2.2 y cuáles son sus líneas clave?",
      "source": "Estrategia ES.pdf",
      "text": "Q: ¿Qué ecosistema de postgrado se impulsa en el Objetivo 2.2 y cuáles son sus líneas clave?\n\nA: El 2.2 impulsa un ecosistema de postgrado robusto: articular doctorados con CTCI para proyección regional e internacional; crear líneas de financiamiento con modelos de consorcio para atraer talento y generar conocimiento de frontera; promover doctorados co‑definidos con el sector socio‑productivo; y diversificar magíster hacia fines aplicados, profesionales, industriales y tecnológicos, con enfoques inter/multi/transdisciplinarios.\n\nVariantes:\n- ¿Cómo se articulan doctorados con CTCI y proyección internacional?\n- ¿Qué financiamiento y modelos de consorcio se proponen?\n- ¿Qué diversificación de propósitos formativos en magíster se promueve?\n- Resume las líneas 2.2.1–2.2.4\n\n\nMeta:\n- País: Chile\n- Periodo: 2026–2038\n- Sección: Objetivo 2.2 y líneas 2.2.1–2.2.4 (p.21)\n- Audiencia: IES,posgrados\n- Documento: Estrategia ES.pdf\n- Tags: objetivo-2.2, postgrado, internacionalización",
      "tags": [
        "objetivo-2.2",
        "postgrado",
        "internacionalización"
      ],
      "meta": {
        "country": "Chile",
        "timeframe": "2026–2038",
        "section": "Objetivo 2.2 y líneas 2.2.1–2.2.4 (p.21)",
        "audience": "IES,posgrados",
        "base": "estrategia_es_QA_50_enriquecido"
      }
    },
    {
      "id": "estrategia_es_QA_50_enriquecido__015",
      "title": "¿Qué impulsa el Objetivo 2.3 en creación de valor productivo desde las IES (EBCT e innovación abierta)?",
      "source": "Estrategia ES.pdf",
      "text": "Q: ¿Qué impulsa el Objetivo 2.3 en creación de valor productivo desde las IES (EBCT e innovación abierta)?\n\nA: El 2.3 promueve EBCT mediante diversificación de incentivos, colaboración con centros regionales de I+D y formación de equipos emprendedores científicos; impulsa ecosistemas de innovación abierta entre IES, empresas y organismos públicos mediante consorcios y hubs; y fortalece mecanismos para aumentar inversión privada en I+D, incluyendo adecuaciones legislativas y fondos para pruebas de concepto tempranas.\n\nVariantes:\n- ¿Cómo fomentar EBCT y su escalamiento desde IES?\n- ¿Qué rol cumplen consorcios, hubs y plataformas colaborativas?\n- ¿Qué incentivos se proponen para inversión privada en I+D?\n- Explica el enfoque de innovación aplicada en el técnico‑profesional\n\n\nMeta:\n- País: Chile\n- Periodo: 2026–2038\n- Sección: Objetivo 2.3 y líneas 2.3.1–2.3.3 (p.22)\n- Audiencia: IES,empresas,policymakers\n- Documento: Estrategia ES.pdf\n- Tags: objetivo-2.3, EBCT, innovación-abierta",
      "tags": [
        "objetivo-2.3",
        "EBCT",
        "innovación-abierta"
      ],
      "meta": {
        "country": "Chile",
        "timeframe": "2026–2038",
        "section": "Objetivo 2.3 y líneas 2.3.1–2.3.3 (p.22)",
        "audience": "IES,empresas,policymakers",
        "base": "estrategia_es_QA_50_enriquecido"
      }
    },
    {
      "id": "estrategia_es_QA_50_enriquecido__016",
      "title": "¿Qué aborda el Desafío Estratégico 3 sobre capacidades para anticipar y adaptarse a desafíos de futuro?",
      "source": "Estrategia ES.pdf",
      "text": "Q: ¿Qué aborda el Desafío Estratégico 3 sobre capacidades para anticipar y adaptarse a desafíos de futuro?\n\nA: El Desafío 3 fortalece capacidades para adaptarse, anticipar y protagonizar desafíos de futuro en formación, investigación, innovación, creación, vinculación y gestión, mediante articulación intersectorial, agendas de prospección laboral y cultura de formación continua.\n\nVariantes:\n- ¿Cuál es el propósito del Desafío 3?\n- Explica la orientación a anticipación y protagonismo de futuro\n- ¿Qué ámbitos del quehacer institucional cubre el Desafío 3?\n- ¿Cómo se relaciona con formación continua y prospección?\n\n\nMeta:\n- País: Chile\n- Periodo: 2026–2038\n- Sección: Desafío 3 (p.23–24)\n- Audiencia: IES,policymakers\n- Documento: Estrategia ES.pdf\n- Tags: desafío-3, anticipación, formación-continua",
      "tags": [
        "desafío-3",
        "anticipación",
        "formación-continua"
      ],
      "meta": {
        "country": "Chile",
        "timeframe": "2026–2038",
        "section": "Desafío 3 (p.23–24)",
        "audience": "IES,policymakers",
        "base": "estrategia_es_QA_50_enriquecido"
      }
    },
    {
      "id": "estrategia_es_QA_50_enriquecido__017",
      "title": "¿Cómo mejora la pertinencia formativa y las transiciones al trabajo el Objetivo 3.1?",
      "source": "Estrategia ES.pdf",
      "text": "Q: ¿Cómo mejora la pertinencia formativa y las transiciones al trabajo el Objetivo 3.1?\n\nA: El 3.1 impulsa articulación permanente entre IES, organismos públicos y sectores social‑productivos para pertinencia de planes formativos y transiciones. Fortalece institucionalidad de prospección laboral con métricas comparables de resultados y satisfacción post‑egreso, y promueve cultura de formación continua mediante incentivos y regulaciones.\n\nVariantes:\n- ¿Qué mecanismos permanentes de articulación propone el 3.1?\n- ¿Cómo se fortalecen sistemas de prospección laboral?\n- ¿Qué significa promover cultura de formación continua?\n- Resume las líneas 3.1.1–3.1.3\n\n\nMeta:\n- País: Chile\n- Periodo: 2026–2038\n- Sección: Objetivo 3.1 y líneas 3.1.1–3.1.3 (p.24)\n- Audiencia: IES,empresas,policymakers\n- Documento: Estrategia ES.pdf\n- Tags: objetivo-3.1, prospección-laboral, empleabilidad",
      "tags": [
        "objetivo-3.1",
        "prospección-laboral",
        "empleabilidad"
      ],
      "meta": {
        "country": "Chile",
        "timeframe": "2026–2038",
        "section": "Objetivo 3.1 y líneas 3.1.1–3.1.3 (p.24)",
        "audience": "IES,empresas,policymakers",
        "base": "estrategia_es_QA_50_enriquecido"
      }
    },
    {
      "id": "estrategia_es_QA_50_enriquecido__018",
      "title": "¿Qué promueve el Objetivo 3.2 respecto de agendas y programas CTCI con valor público?",
      "source": "Estrategia ES.pdf",
      "text": "Q: ¿Qué promueve el Objetivo 3.2 respecto de agendas y programas CTCI con valor público?\n\nA: El 3.2 promueve agendas y programas CTCI articulados prospectivamente a desafíos de futuro, mediante coordinación interministerial. Fortalece financiamiento para I+D+i colaborativa y bidireccional entre IES y agentes públicos, privados y de la sociedad civil, orientada a identificar y abordar desafíos locales, nacionales y globales.\n\nVariantes:\n- ¿Cómo se articulan programas CTCI con desafíos regionales, nacionales y globales?\n- ¿Qué instrumentos de financiamiento colaborativo se fortalecen?\n- ¿Por qué se enfatiza la bidireccionalidad entre IES y agentes externos?\n- Resume las líneas 3.2.1–3.2.2\n\n\nMeta:\n- País: Chile\n- Periodo: 2026–2038\n- Sección: Objetivo 3.2 y líneas 3.2.1–3.2.2 (p.24)\n- Audiencia: policymakers,IES\n- Documento: Estrategia ES.pdf\n- Tags: objetivo-3.2, CTCI, financiamiento",
      "tags": [
        "objetivo-3.2",
        "CTCI",
        "financiamiento"
      ],
      "meta": {
        "country": "Chile",
        "timeframe": "2026–2038",
        "section": "Objetivo 3.2 y líneas 3.2.1–3.2.2 (p.24)",
        "audience": "policymakers,IES",
        "base": "estrategia_es_QA_50_enriquecido"
      }
    },
    {
      "id": "estrategia_es_QA_50_enriquecido__019",
      "title": "¿Cómo vincula el Objetivo 3.3 la educación superior con el entorno para equidad territorial y desarrollo sostenible?",
      "source": "Estrategia ES.pdf",
      "text": "Q: ¿Cómo vincula el Objetivo 3.3 la educación superior con el entorno para equidad territorial y desarrollo sostenible?\n\nA: El 3.3 fomenta vinculación bidireccional, intersectorial y multinivel con el entorno: mejorar integración con educación secundaria en territorios; incentivar participación en redes y espacios de gobernanza para políticas y estrategias de desarrollo sostenible; fortalecer extensión y rol social en humanidades, artes y culturas; y ampliar el SIES con datos interoperables sobre contribución territorial y nacional.\n\nVariantes:\n- ¿Qué acciones intersectoriales y multinivel se impulsan en el 3.3?\n- ¿Cómo se orientan capacidades hacia educación secundaria en los territorios?\n- ¿Qué rol social y de extensión se proyecta en humanidades, artes y culturas?\n- ¿Qué mejoras se proponen para el SIES mediante interoperabilidad de datos?\n\n\nMeta:\n- País: Chile\n- Periodo: 2026–2038\n- Sección: Objetivo 3.3 y líneas 3.3.1–3.3.4 (p.25)\n- Audiencia: IES,policymakers,territorios\n- Documento: Estrategia ES.pdf\n- Tags: objetivo-3.3, equidad-territorial, SIES",
      "tags": [
        "objetivo-3.3",
        "equidad-territorial",
        "SIES"
      ],
      "meta": {
        "country": "Chile",
        "timeframe": "2026–2038",
        "section": "Objetivo 3.3 y líneas 3.3.1–3.3.4 (p.25)",
        "audience": "IES,policymakers,territorios",
        "base": "estrategia_es_QA_50_enriquecido"
      }
    },
    {
      "id": "estrategia_es_QA_50_enriquecido__020",
      "title": "¿Qué plantea el Desafío Estratégico 4 sobre gobernanza sistémica, regulación, calidad y financiamiento?",
      "source": "Estrategia ES.pdf",
      "text": "Q: ¿Qué plantea el Desafío Estratégico 4 sobre gobernanza sistémica, regulación, calidad y financiamiento?\n\nA: El Desafío 4 propone consolidar una gobernanza sistémica orientada estratégicamente mediante actualización de regulación, aseguramiento de calidad y financiamiento, para fortalecer sostenibilidad y capacidades de creación de valor y aporte al desarrollo del país.\n\nVariantes:\n- ¿Cuál es el objetivo general del Desafío 4?\n- Explica la orientación a sostenibilidad y creación de valor en gobernanza\n- ¿Cómo se relacionan regulación, aseguramiento de calidad y financiamiento?\n- ¿Qué capacidades se buscan fortalecer en el sistema?\n\n\nMeta:\n- País: Chile\n- Periodo: 2026–2038\n- Sección: Desafío 4 (p.26–29)\n- Audiencia: policymakers,IES\n- Documento: Estrategia ES.pdf\n- Tags: desafío-4, gobernanza, financiamiento",
      "tags": [
        "desafío-4",
        "gobernanza",
        "financiamiento"
      ],
      "meta": {
        "country": "Chile",
        "timeframe": "2026–2038",
        "section": "Desafío 4 (p.26–29)",
        "audience": "policymakers,IES",
        "base": "estrategia_es_QA_50_enriquecido"
      }
    },
    {
      "id": "estrategia_es_QA_50_enriquecido__021",
      "title": "¿Qué funciones tendría el Consejo para el Desarrollo Estratégico de la Educación Superior (línea 4.1.1)?",
      "source": "Estrategia ES.pdf",
      "text": "Q: ¿Qué funciones tendría el Consejo para el Desarrollo Estratégico de la Educación Superior (línea 4.1.1)?\n\nA: La 4.1.1 propone crear un Consejo encargado de monitorear el avance del sistema, actualizar desafíos y objetivos, promover colaboración entre instituciones, impulsar internacionalización y proponer orientaciones para financiamiento y desarrollo sostenible del sistema.\n\nVariantes:\n- ¿Para qué se crea el Consejo propuesto en la 4.1.1?\n- ¿Qué roles de monitoreo, actualización y colaboración asumiría?\n- ¿Cómo impulsaría internacionalización y orientaciones de financiamiento?\n- Resume atribuciones clave del Consejo\n\n\nMeta:\n- País: Chile\n- Periodo: 2026–2038\n- Sección: Línea 4.1.1 (p.27)\n- Audiencia: policymakers\n- Documento: Estrategia ES.pdf\n- Tags: línea-4.1.1, consejo-estratégico, gobernanza",
      "tags": [
        "línea-4.1.1",
        "consejo-estratégico",
        "gobernanza"
      ],
      "meta": {
        "country": "Chile",
        "timeframe": "2026–2038",
        "section": "Línea 4.1.1 (p.27)",
        "audience": "policymakers",
        "base": "estrategia_es_QA_50_enriquecido"
      }
    },
    {
      "id": "estrategia_es_QA_50_enriquecido__022",
      "title": "¿Cómo se fortalece el papel articulador del Sinaces según la línea 4.1.2?",
      "source": "Estrategia ES.pdf",
      "text": "Q: ¿Cómo se fortalece el papel articulador del Sinaces según la línea 4.1.2?\n\nA: La 4.1.2 fortalece el papel articulador del Sinaces respecto de funciones y atribuciones de agencias estatales en gobernanza, financiamiento y regulación de la educación superior, para mejorar coherencia, eficiencia y orientación estratégica del sistema.\n\nVariantes:\n- ¿Qué coordinación con agencias estatales propone la 4.1.2?\n- ¿Cómo mejora gobernanza y regulación del sistema?\n- Explica el rol articulador del Sinaces\n- ¿Qué resultados se esperan de la articulación propuesta?\n\n\nMeta:\n- País: Chile\n- Periodo: 2026–2038\n- Sección: Línea 4.1.2 (p.27)\n- Audiencia: policymakers,agencias\n- Documento: Estrategia ES.pdf\n- Tags: línea-4.1.2, Sinaces, articulación",
      "tags": [
        "línea-4.1.2",
        "Sinaces",
        "articulación"
      ],
      "meta": {
        "country": "Chile",
        "timeframe": "2026–2038",
        "section": "Línea 4.1.2 (p.27)",
        "audience": "policymakers,agencias",
        "base": "estrategia_es_QA_50_enriquecido"
      }
    },
    {
      "id": "estrategia_es_QA_50_enriquecido__023",
      "title": "¿Qué modernizaciones se plantean para universidades estatales en la línea 4.2.1?",
      "source": "Estrategia ES.pdf",
      "text": "Q: ¿Qué modernizaciones se plantean para universidades estatales en la línea 4.2.1?\n\nA: La 4.2.1 propone modernizar el régimen jurídico de universidades estatales para dotarlas de normas que permitan gestión administrativa, financiera y estratégica más flexible y ágil, fortaleciendo su autonomía y capacidad para cumplir propósitos científicos, tecnológicos, culturales y territoriales.\n\nVariantes:\n- ¿Por qué actualizar el régimen jurídico especial (Ley 21.094)?\n- ¿Qué flexibilidades administrativas y estratégicas se buscan?\n- ¿Cómo impacta en autonomía y propósito institucional?\n- Resume la línea 4.2.1\n\n\nMeta:\n- País: Chile\n- Periodo: 2026–2038\n- Sección: Línea 4.2.1 (p.27)\n- Audiencia: policymakers,IES-estatales\n- Documento: Estrategia ES.pdf\n- Tags: línea-4.2.1, universidades-estatales, modernización",
      "tags": [
        "línea-4.2.1",
        "universidades-estatales",
        "modernización"
      ],
      "meta": {
        "country": "Chile",
        "timeframe": "2026–2038",
        "section": "Línea 4.2.1 (p.27)",
        "audience": "policymakers,IES-estatales",
        "base": "estrategia_es_QA_50_enriquecido"
      }
    },
    {
      "id": "estrategia_es_QA_50_enriquecido__024",
      "title": "¿Qué adecuaciones se proponen para CFT estatales en la línea 4.2.2?",
      "source": "Estrategia ES.pdf",
      "text": "Q: ¿Qué adecuaciones se proponen para CFT estatales en la línea 4.2.2?\n\nA: La 4.2.2 plantea adecuar el régimen jurídico de CFT estatales para modernizar su marco y fortalecer gestión institucional, alineando su misión territorial y vinculación con sectores productivos, mejorando su aporte al desarrollo regional.\n\nVariantes:\n- ¿Qué cambios al marco de la Ley 20.910 se buscan?\n- ¿Cómo fortalecer capacidad de gestión institucional en CFT estatales?\n- ¿Qué misión territorial y productiva se refuerza?\n- Explica la línea 4.2.2\n\n\nMeta:\n- País: Chile\n- Periodo: 2026–2038\n- Sección: Línea 4.2.2 (p.27)\n- Audiencia: policymakers,CFT\n- Documento: Estrategia ES.pdf\n- Tags: línea-4.2.2, CFT-estatales, gestión",
      "tags": [
        "línea-4.2.2",
        "CFT-estatales",
        "gestión"
      ],
      "meta": {
        "country": "Chile",
        "timeframe": "2026–2038",
        "section": "Línea 4.2.2 (p.27)",
        "audience": "policymakers,CFT",
        "base": "estrategia_es_QA_50_enriquecido"
      }
    },
    {
      "id": "estrategia_es_QA_50_enriquecido__025",
      "title": "¿Cómo se articula la planificación de IES estatales para aportar al desarrollo sostenible (línea 4.2.3)?",
      "source": "Estrategia ES.pdf",
      "text": "Q: ¿Cómo se articula la planificación de IES estatales para aportar al desarrollo sostenible (línea 4.2.3)?\n\nA: La 4.2.3 promueve articular la planificación de IES estatales mediante mecanismos de integración y coordinación para mejorar su funcionamiento, incrementar capacidades y abordar colaborativamente, en red, los desafíos estratégicos del país y sus regiones.\n\nVariantes:\n- ¿Qué mecanismos de integración y coordinación se proponen?\n- ¿Cómo abordar desafíos estratégicos del país en red?\n- ¿Qué mejora de funcionamiento se busca con la 4.2.3?\n- Explica los resultados esperados de la planificación articulada\n\n\nMeta:\n- País: Chile\n- Periodo: 2026–2038\n- Sección: Línea 4.2.3 (p.27)\n- Audiencia: IES-estatales,policymakers\n- Documento: Estrategia ES.pdf\n- Tags: línea-4.2.3, planificación, red-estatal",
      "tags": [
        "línea-4.2.3",
        "planificación",
        "red-estatal"
      ],
      "meta": {
        "country": "Chile",
        "timeframe": "2026–2038",
        "section": "Línea 4.2.3 (p.27)",
        "audience": "IES-estatales,policymakers",
        "base": "estrategia_es_QA_50_enriquecido"
      }
    },
    {
      "id": "estrategia_es_QA_50_enriquecido__026",
      "title": "¿Qué tipo de planes y programas debe impulsar la línea 4.2.4 en IES estatales?",
      "source": "Estrategia ES.pdf",
      "text": "Q: ¿Qué tipo de planes y programas debe impulsar la línea 4.2.4 en IES estatales?\n\nA: La 4.2.4 sugiere generar planes y programas para que IES estatales asuman rol activo en iniciativas vinculadas a desafíos estratégicos del país, fortaleciendo contribución al desarrollo científico, tecnológico, cultural y territorial.\n\nVariantes:\n- ¿Cómo promover rol activo de IES estatales en desafíos estratégicos?\n- ¿Qué iniciativas se esperan en desarrollo nacional y regional?\n- Explica el sentido de la línea 4.2.4\n- ¿Qué vínculos con sectores estratégicos se consideran?\n\n\nMeta:\n- País: Chile\n- Periodo: 2026–2038\n- Sección: Línea 4.2.4 (p.27)\n- Audiencia: IES-estatales\n- Documento: Estrategia ES.pdf\n- Tags: línea-4.2.4, programas, desarrollo-estratégico",
      "tags": [
        "línea-4.2.4",
        "programas",
        "desarrollo-estratégico"
      ],
      "meta": {
        "country": "Chile",
        "timeframe": "2026–2038",
        "section": "Línea 4.2.4 (p.27)",
        "audience": "IES-estatales",
        "base": "estrategia_es_QA_50_enriquecido"
      }
    },
    {
      "id": "estrategia_es_QA_50_enriquecido__027",
      "title": "¿Qué mecanismos de arquitectura cooperativa entre IES propone la línea 4.3.1?",
      "source": "Estrategia ES.pdf",
      "text": "Q: ¿Qué mecanismos de arquitectura cooperativa entre IES propone la línea 4.3.1?\n\nA: La 4.3.1 plantea fortalecer mecanismos, incentivos e indicadores que promuevan una arquitectura cooperativa entre IES para abordar desafíos compartidos del desarrollo científico, cultural, productivo, económico y social a nivel país y regiones.\n\nVariantes:\n- ¿Cómo avanzar hacia cooperación para desafíos compartidos?\n- ¿Qué incentivos e indicadores habilitan la arquitectura cooperativa?\n- ¿Qué ámbitos (científico, cultural, productivo) se abordan?\n- Resume la línea 4.3.1\n\n\nMeta:\n- País: Chile\n- Periodo: 2026–2038\n- Sección: Línea 4.3.1 (p.28)\n- Audiencia: IES\n- Documento: Estrategia ES.pdf\n- Tags: línea-4.3.1, cooperación, arquitectura-sistémica",
      "tags": [
        "línea-4.3.1",
        "cooperación",
        "arquitectura-sistémica"
      ],
      "meta": {
        "country": "Chile",
        "timeframe": "2026–2038",
        "section": "Línea 4.3.1 (p.28)",
        "audience": "IES",
        "base": "estrategia_es_QA_50_enriquecido"
      }
    },
    {
      "id": "estrategia_es_QA_50_enriquecido__028",
      "title": "¿Qué vías de integración, fusión o reorganización entre IES contempla la línea 4.3.2?",
      "source": "Estrategia ES.pdf",
      "text": "Q: ¿Qué vías de integración, fusión o reorganización entre IES contempla la línea 4.3.2?\n\nA: La 4.3.2 propone desarrollar mecanismos de integración, fusión y/o reorganización entre IES para consolidar sostenibilidad y fortalecer capacidad de cumplir propósitos institucionales, evaluando impactos en calidad, eficiencia y pertinencia.\n\nVariantes:\n- ¿Para qué integrar o reorganizar IES según la 4.3.2?\n- ¿Qué efectos busca en sostenibilidad y cumplimiento de misión?\n- Explica opciones de fusión y reorganización en la Estrategia\n- ¿Cómo se evaluaría el aporte institucional tras estos cambios?\n\n\nMeta:\n- País: Chile\n- Periodo: 2026–2038\n- Sección: Línea 4.3.2 (p.28)\n- Audiencia: policymakers,IES\n- Documento: Estrategia ES.pdf\n- Tags: línea-4.3.2, integración, sostenibilidad",
      "tags": [
        "línea-4.3.2",
        "integración",
        "sostenibilidad"
      ],
      "meta": {
        "country": "Chile",
        "timeframe": "2026–2038",
        "section": "Línea 4.3.2 (p.28)",
        "audience": "policymakers,IES",
        "base": "estrategia_es_QA_50_enriquecido"
      }
    },
    {
      "id": "estrategia_es_QA_50_enriquecido__029",
      "title": "¿Cómo se orienta el aseguramiento de la calidad hacia resultados e impactos (línea 4.4.1)?",
      "source": "Estrategia ES.pdf",
      "text": "Q: ¿Cómo se orienta el aseguramiento de la calidad hacia resultados e impactos (línea 4.4.1)?\n\nA: La 4.4.1 orienta regulación y aseguramiento de calidad hacia resultados e impactos sustantivos (más allá del proceso), incentivando iniciativas innovadoras con foco en calidad integral y pertinencia con objetivos de desarrollo del país.\n\nVariantes:\n- ¿Qué cambia respecto de indicadores de proceso en calidad?\n- ¿Cómo se incentiva la innovación con foco en calidad integral?\n- Explica el enfoque a resultados de la 4.4.1\n- ¿Qué pertinencia con objetivos de desarrollo del país se busca?\n\n\nMeta:\n- País: Chile\n- Periodo: 2026–2038\n- Sección: Línea 4.4.1 (p.28–29)\n- Audiencia: agencias,IES\n- Documento: Estrategia ES.pdf\n- Tags: línea-4.4.1, calidad, impacto",
      "tags": [
        "línea-4.4.1",
        "calidad",
        "impacto"
      ],
      "meta": {
        "country": "Chile",
        "timeframe": "2026–2038",
        "section": "Línea 4.4.1 (p.28–29)",
        "audience": "agencias,IES",
        "base": "estrategia_es_QA_50_enriquecido"
      }
    },
    {
      "id": "estrategia_es_QA_50_enriquecido__030",
      "title": "¿Qué sistema de acreditación obligatoria propone la línea 4.4.2 y cómo evita la forma de ranking?",
      "source": "Estrategia ES.pdf",
      "text": "Q: ¿Qué sistema de acreditación obligatoria propone la línea 4.4.2 y cómo evita la forma de ranking?\n\nA: La 4.4.2 plantea una acreditación institucional obligatoria que supera la lógica de ranking, diferenciando estándares por tipos de misiones institucionales y orientando a cada IES al mejoramiento sostenido de la calidad.\n\nVariantes:\n- ¿Cómo se diferencian estándares según misiones institucionales?\n- ¿Qué orientación al mejoramiento sostenido se plantea?\n- Explica el nuevo modelo de acreditación propuesto\n- ¿Qué limita la dependencia de años o tramos de acreditación?\n\n\nMeta:\n- País: Chile\n- Periodo: 2026–2038\n- Sección: Línea 4.4.2 (p.28–29)\n- Audiencia: agencias,IES\n- Documento: Estrategia ES.pdf\n- Tags: línea-4.4.2, acreditación, mejoramiento",
      "tags": [
        "línea-4.4.2",
        "acreditación",
        "mejoramiento"
      ],
      "meta": {
        "country": "Chile",
        "timeframe": "2026–2038",
        "section": "Línea 4.4.2 (p.28–29)",
        "audience": "agencias,IES",
        "base": "estrategia_es_QA_50_enriquecido"
      }
    },
    {
      "id": "estrategia_es_QA_50_enriquecido__031",
      "title": "¿Para qué incorporar estándares de calidad con reconocimiento internacional en IES de excelencia (línea 4.4.3)?",
      "source": "Estrategia ES.pdf",
      "text": "Q: ¿Para qué incorporar estándares de calidad con reconocimiento internacional en IES de excelencia (línea 4.4.3)?\n\nA: La 4.4.3 incorpora estándares de acreditación que permitan sostener calidad con reconocimiento internacional en IES de excelencia consolidada, fortaleciendo posicionamiento y comparabilidad del sistema a nivel global.\n\nVariantes:\n- ¿Qué busca proyectar y sostener la 4.4.3?\n- ¿Cómo se reconoce calidad internacional en IES con excelencia?\n- Explica el sentido de los estándares internacionales\n- ¿Qué efectos tiene en posicionamiento del sistema?\n\n\nMeta:\n- País: Chile\n- Periodo: 2026–2038\n- Sección: Línea 4.4.3 (p.29)\n- Audiencia: IES,agencias\n- Documento: Estrategia ES.pdf\n- Tags: línea-4.4.3, estándares, internacional",
      "tags": [
        "línea-4.4.3",
        "estándares",
        "internacional"
      ],
      "meta": {
        "country": "Chile",
        "timeframe": "2026–2038",
        "section": "Línea 4.4.3 (p.29)",
        "audience": "IES,agencias",
        "base": "estrategia_es_QA_50_enriquecido"
      }
    },
    {
      "id": "estrategia_es_QA_50_enriquecido__032",
      "title": "¿Cómo armoniza la línea 4.5.1 el financiamiento público según funciones institucionales?",
      "source": "Estrategia ES.pdf",
      "text": "Q: ¿Cómo armoniza la línea 4.5.1 el financiamiento público según funciones institucionales?\n\nA: La 4.5.1 propone diferenciar líneas de financiamiento público según funciones (docencia, investigación, innovación/creación y vinculación), considerando aseguramiento de calidad, transparencia, desempeño y compromiso con metas estratégicas de impacto e internacionalización, para mejorar asignación y eficacia del gasto.\n\nVariantes:\n- ¿Qué diferenciación por docencia, investigación, innovación y vinculación se propone?\n- ¿Qué criterios de calidad, transparencia y desempeño se consideran?\n- Explica el vínculo con metas estratégicas de impacto e internacionalización\n- ¿Cómo mejorar la asignación de recursos?\n\n\nMeta:\n- País: Chile\n- Periodo: 2026–2038\n- Sección: Línea 4.5.1 (p.28–29)\n- Audiencia: policymakers,IES\n- Documento: Estrategia ES.pdf\n- Tags: línea-4.5.1, financiamiento, funciones",
      "tags": [
        "línea-4.5.1",
        "financiamiento",
        "funciones"
      ],
      "meta": {
        "country": "Chile",
        "timeframe": "2026–2038",
        "section": "Línea 4.5.1 (p.28–29)",
        "audience": "policymakers,IES",
        "base": "estrategia_es_QA_50_enriquecido"
      }
    },
    {
      "id": "estrategia_es_QA_50_enriquecido__033",
      "title": "¿Qué cambio propone la línea 4.5.2 respecto del financiamiento ligado a tramos de acreditación?",
      "source": "Estrategia ES.pdf",
      "text": "Q: ¿Qué cambio propone la línea 4.5.2 respecto del financiamiento ligado a tramos de acreditación?\n\nA: La 4.5.2 sugiere desacoplar financiamiento institucional de la forma de ranking de años/tramos de acreditación y avanzar a un modelo basado en cumplimiento de estándares de calidad diferenciados por tipo de misión, considerando alcance, complejidad y desempeño.\n\nVariantes:\n- ¿Por qué desacoplar financiamiento de años de acreditación?\n- ¿Qué nuevo modelo basado en estándares diferenciados se sugiere?\n- Explica cómo se consideran alcance, complejidad y desempeño\n- ¿Qué beneficios trae para diversidad de misiones institucionales?\n\n\nMeta:\n- País: Chile\n- Periodo: 2026–2038\n- Sección: Línea 4.5.2 (p.29)\n- Audiencia: policymakers,IES\n- Documento: Estrategia ES.pdf\n- Tags: línea-4.5.2, financiamiento, estándares",
      "tags": [
        "línea-4.5.2",
        "financiamiento",
        "estándares"
      ],
      "meta": {
        "country": "Chile",
        "timeframe": "2026–2038",
        "section": "Línea 4.5.2 (p.29)",
        "audience": "policymakers,IES",
        "base": "estrategia_es_QA_50_enriquecido"
      }
    },
    {
      "id": "estrategia_es_QA_50_enriquecido__034",
      "title": "¿Cómo se coordinan los instrumentos de financiamiento público a I+D+i en IES (línea 4.5.3)?",
      "source": "Estrategia ES.pdf",
      "text": "Q: ¿Cómo se coordinan los instrumentos de financiamiento público a I+D+i en IES (línea 4.5.3)?\n\nA: La 4.5.3 propone coordinar e integrar instrumentos de financiamiento público a investigación e innovación en IES con base en objetivos estratégicos y metas del sistema, priorizando calidad e impacto de publicaciones y otras iniciativas por sobre su mera cantidad.\n\nVariantes:\n- ¿Qué integración se propone según objetivos y metas del sistema?\n- ¿Cómo se prioriza calidad e impacto de publicaciones e iniciativas?\n- Explica la coordinación de instrumentos de financiamiento\n- ¿Qué evita el enfoque en cantidad sin calidad?\n\n\nMeta:\n- País: Chile\n- Periodo: 2026–2038\n- Sección: Línea 4.5.3 (p.29)\n- Audiencia: agencias,IES\n- Documento: Estrategia ES.pdf\n- Tags: línea-4.5.3, financiamiento-I+D+i, impacto",
      "tags": [
        "línea-4.5.3",
        "financiamiento-I+D+i",
        "impacto"
      ],
      "meta": {
        "country": "Chile",
        "timeframe": "2026–2038",
        "section": "Línea 4.5.3 (p.29)",
        "audience": "agencias,IES",
        "base": "estrategia_es_QA_50_enriquecido"
      }
    },
    {
      "id": "estrategia_es_QA_50_enriquecido__035",
      "title": "¿Por qué incorporar ponderaciones en aranceles regulados según resultados formativos (línea 4.5.4)?",
      "source": "Estrategia ES.pdf",
      "text": "Q: ¿Por qué incorporar ponderaciones en aranceles regulados según resultados formativos (línea 4.5.4)?\n\nA: La 4.5.4 propone incorporar a aranceles regulados ponderaciones asociadas a resultados del proceso formativo, considerando eficiencia en progresión académica e inserción ocupacional de egresados, para alinear financiamiento con desempeño y resultados.\n\nVariantes:\n- ¿Qué indicadores de progresión académica y inserción ocupacional se consideran?\n- ¿Cómo se vincula financiamiento con desempeño estudiantil?\n- Explica el objetivo de ponderaciones en aranceles\n- ¿Qué incentivos genera en mejora de resultados?\n\n\nMeta:\n- País: Chile\n- Periodo: 2026–2038\n- Sección: Línea 4.5.4 (p.29)\n- Audiencia: policymakers,IES\n- Documento: Estrategia ES.pdf\n- Tags: línea-4.5.4, aranceles, resultados",
      "tags": [
        "línea-4.5.4",
        "aranceles",
        "resultados"
      ],
      "meta": {
        "country": "Chile",
        "timeframe": "2026–2038",
        "section": "Línea 4.5.4 (p.29)",
        "audience": "policymakers,IES",
        "base": "estrategia_es_QA_50_enriquecido"
      }
    },
    {
      "id": "estrategia_es_QA_50_enriquecido__036",
      "title": "¿Qué mecanismos incentivan la diversificación de fuentes de ingresos en IES (línea 4.5.5)?",
      "source": "Estrategia ES.pdf",
      "text": "Q: ¿Qué mecanismos incentivan la diversificación de fuentes de ingresos en IES (línea 4.5.5)?\n\nA: La 4.5.5 incentiva diversificación de fuentes de ingresos para reducir dependencia del financiamiento público, fortaleciendo capacidad de las IES para financiar iniciativas de desarrollo institucional y mejorar sostenibilidad de largo plazo.\n\nVariantes:\n- ¿Por qué reducir dependencia del financiamiento público?\n- ¿Qué iniciativas de generación de ingresos se promueven?\n- Explica beneficios de diversificación para sostenibilidad\n- ¿Qué relación tiene con financiar desarrollo institucional?\n\n\nMeta:\n- País: Chile\n- Periodo: 2026–2038\n- Sección: Línea 4.5.5 (p.29)\n- Audiencia: IES,policymakers\n- Documento: Estrategia ES.pdf\n- Tags: línea-4.5.5, ingresos, sostenibilidad",
      "tags": [
        "línea-4.5.5",
        "ingresos",
        "sostenibilidad"
      ],
      "meta": {
        "country": "Chile",
        "timeframe": "2026–2038",
        "section": "Línea 4.5.5 (p.29)",
        "audience": "IES,policymakers",
        "base": "estrategia_es_QA_50_enriquecido"
      }
    },
    {
      "id": "estrategia_es_QA_50_enriquecido__037",
      "title": "¿Qué se entiende por aprendizaje a lo largo de la vida en el contexto de la Estrategia?",
      "source": "Estrategia ES.pdf",
      "text": "Q: ¿Qué se entiende por aprendizaje a lo largo de la vida en el contexto de la Estrategia?\n\nA: El aprendizaje a lo largo de la vida comprende actividades educativas emprendidas durante toda la vida para mejorar conocimientos, capacidades y competencias. Se distingue por su intencionalidad formativa y sustenta trayectorias flexibles, articulando educación formal y no formal en clave personal, cívica, social y laboral.\n\nVariantes:\n- Define aprendizaje permanente en educación superior\n- ¿Cómo se diferencia de actividades culturales o deportivas?\n- ¿Qué objetivos persigue en dimensiones personal, cívica y laboral?\n- Explica su relevancia para trayectorias flexibles\n\n\nMeta:\n- País: Chile\n- Periodo: 2026–2038\n- Sección: Glosario (p.30)\n- Audiencia: estudiantes,docentes,IES\n- Documento: Estrategia ES.pdf\n- Tags: glosario, lifelong-learning",
      "tags": [
        "glosario",
        "lifelong-learning"
      ],
      "meta": {
        "country": "Chile",
        "timeframe": "2026–2038",
        "section": "Glosario (p.30)",
        "audience": "estudiantes,docentes,IES",
        "base": "estrategia_es_QA_50_enriquecido"
      }
    },
    {
      "id": "estrategia_es_QA_50_enriquecido__038",
      "title": "¿Qué es la articulación de la formación y cómo habilita trayectorias educativas y laborales?",
      "source": "Estrategia ES.pdf",
      "text": "Q: ¿Qué es la articulación de la formación y cómo habilita trayectorias educativas y laborales?\n\nA: La articulación de la formación son mecanismos que facilitan reconocimientos entre distintos tipos de enseñanza y aprendizajes adquiridos en sectores económicos, habilitando trayectorias educativas y laborales entre instituciones formativas, industria y sector público, con reconocimiento de aprendizajes previos.\n\nVariantes:\n- Define articulación de la formación según la Estrategia\n- ¿Qué mecanismos facilitan reconocimientos entre enseñanzas?\n- ¿Cómo integra aprendizajes formales y no formales?\n- Explica su vínculo con sectores productivos\n\n\nMeta:\n- País: Chile\n- Periodo: 2026–2038\n- Sección: Glosario (p.30)\n- Audiencia: IES,policymakers\n- Documento: Estrategia ES.pdf\n- Tags: glosario, articulación, RAP",
      "tags": [
        "glosario",
        "articulación",
        "RAP"
      ],
      "meta": {
        "country": "Chile",
        "timeframe": "2026–2038",
        "section": "Glosario (p.30)",
        "audience": "IES,policymakers",
        "base": "estrategia_es_QA_50_enriquecido"
      }
    },
    {
      "id": "estrategia_es_QA_50_enriquecido__039",
      "title": "¿Cómo define la Estrategia la gobernanza en educación superior?",
      "source": "Estrategia ES.pdf",
      "text": "Q: ¿Cómo define la Estrategia la gobernanza en educación superior?\n\nA: La gobernanza comprende estructuras y procesos que garantizan rendición de cuentas, transparencia, capacidad de respuesta, estado de derecho, estabilidad, equidad, inclusión y participación amplia. Incluye normas y valores mediante los cuales se gestionan asuntos públicos de forma transparente y participativa, más allá de los órganos formales.\n\nVariantes:\n- Describe estructuras y procesos de gobernanza\n- ¿Qué valores y reglas del juego incorpora?\n- ¿Por qué excede a los órganos de gobierno?\n- Explica su relación con participación y rendición de cuentas\n\n\nMeta:\n- País: Chile\n- Periodo: 2026–2038\n- Sección: Glosario (p.33)\n- Audiencia: policymakers,IES\n- Documento: Estrategia ES.pdf\n- Tags: glosario, gobernanza",
      "tags": [
        "glosario",
        "gobernanza"
      ],
      "meta": {
        "country": "Chile",
        "timeframe": "2026–2038",
        "section": "Glosario (p.33)",
        "audience": "policymakers,IES",
        "base": "estrategia_es_QA_50_enriquecido"
      }
    },
    {
      "id": "estrategia_es_QA_50_enriquecido__040",
      "title": "¿Qué diferencia la innovación aplicada en educación superior?",
      "source": "Estrategia ES.pdf",
      "text": "Q: ¿Qué diferencia la innovación aplicada en educación superior?\n\nA: La innovación aplicada implementa soluciones nuevas o significativamente mejoradas en productos, servicios, procesos u organización, orientadas a problemas concretos de sectores productivos, sociales o territoriales. En educación superior, incluye I+D vinculada directamente a necesidades del entorno, con énfasis en transferencia y contextualización.\n\nVariantes:\n- Define innovación aplicada y su foco\n- ¿Qué tipos de soluciones contempla?\n- ¿Cómo se orienta a problemas de sectores específicos?\n- Explica su vínculo con transferencia tecnológica\n\n\nMeta:\n- País: Chile\n- Periodo: 2026–2038\n- Sección: Glosario (p.34)\n- Audiencia: IES,empresas\n- Documento: Estrategia ES.pdf\n- Tags: glosario, innovación-aplicada",
      "tags": [
        "glosario",
        "innovación-aplicada"
      ],
      "meta": {
        "country": "Chile",
        "timeframe": "2026–2038",
        "section": "Glosario (p.34)",
        "audience": "IES,empresas",
        "base": "estrategia_es_QA_50_enriquecido"
      }
    },
    {
      "id": "estrategia_es_QA_50_enriquecido__041",
      "title": "¿Qué es el Marco Nacional de Cualificaciones Técnico‑Profesional y para qué sirve?",
      "source": "Estrategia ES.pdf",
      "text": "Q: ¿Qué es el Marco Nacional de Cualificaciones Técnico‑Profesional y para qué sirve?\n\nA: El MCTP es un instrumento que organiza y reconoce aprendizajes en niveles graduales de conocimientos, habilidades y competencias. Promueve aprendizaje a lo largo de la vida, articula niveles educativos y educación formal/no formal, y conecta demandas del trabajo y la sociedad con oferta formativa.\n\nVariantes:\n- Define el MCTP en la Estrategia\n- ¿Cómo organiza aprendizajes y niveles?\n- ¿Qué articulaciones habilita entre educación y trabajo?\n- Explica su aporte a aprendizaje permanente\n\n\nMeta:\n- País: Chile\n- Periodo: 2026–2038\n- Sección: Glosario (p.34)\n- Audiencia: estudiantes,IES\n- Documento: Estrategia ES.pdf\n- Tags: glosario, MCTP, cualificaciones",
      "tags": [
        "glosario",
        "MCTP",
        "cualificaciones"
      ],
      "meta": {
        "country": "Chile",
        "timeframe": "2026–2038",
        "section": "Glosario (p.34)",
        "audience": "estudiantes,IES",
        "base": "estrategia_es_QA_50_enriquecido"
      }
    },
    {
      "id": "estrategia_es_QA_50_enriquecido__042",
      "title": "¿Qué define la empleabilidad en educación superior según la Estrategia?",
      "source": "Estrategia ES.pdf",
      "text": "Q: ¿Qué define la empleabilidad en educación superior según la Estrategia?\n\nA: La empleabilidad integra competencias técnicas específicas y transversales, capacidad de adaptación y desarrollo de trayectorias ocupacionales pertinentes. En educación superior se vincula a acceso, mantenimiento y progreso en educación, formación y empleo decente a lo largo de la vida.\n\nVariantes:\n- Describe competencias técnicas y transversales para empleabilidad\n- ¿Qué relación tiene con adaptación al cambio?\n- Explica trayectorias ocupacionales pertinentes\n- ¿Qué significa empleo decente en este contexto?\n\n\nMeta:\n- País: Chile\n- Periodo: 2026–2038\n- Sección: Glosario (p.32–36)\n- Audiencia: estudiantes,IES,empresas\n- Documento: Estrategia ES.pdf\n- Tags: glosario, empleabilidad, trabajo-decente",
      "tags": [
        "glosario",
        "empleabilidad",
        "trabajo-decente"
      ],
      "meta": {
        "country": "Chile",
        "timeframe": "2026–2038",
        "section": "Glosario (p.32–36)",
        "audience": "estudiantes,IES,empresas",
        "base": "estrategia_es_QA_50_enriquecido"
      }
    },
    {
      "id": "estrategia_es_QA_50_enriquecido__043",
      "title": "¿Qué implica la vinculación con el medio en el marco de calidad institucional?",
      "source": "Estrategia ES.pdf",
      "text": "Q: ¿Qué implica la vinculación con el medio en el marco de calidad institucional?\n\nA: La vinculación con el medio son nexos con ámbitos disciplinarios, artísticos, tecnológicos, productivos o profesionales que mejoran desempeño institucional, facilitan desarrollo académico y profesional y contribuyen al cumplimiento de objetivos y actualización de la comunidad.\n\nVariantes:\n- Define vinculación con el medio\n- ¿Qué nexos establece con ámbitos disciplinarios y productivos?\n- ¿Cómo mejora desempeño de funciones institucionales?\n- Explica su aporte a actualización y objetivos institucionales\n\n\nMeta:\n- País: Chile\n- Periodo: 2026–2038\n- Sección: Glosario (p.36)\n- Audiencia: IES,docentes,territorios\n- Documento: Estrategia ES.pdf\n- Tags: glosario, vinculación, calidad",
      "tags": [
        "glosario",
        "vinculación",
        "calidad"
      ],
      "meta": {
        "country": "Chile",
        "timeframe": "2026–2038",
        "section": "Glosario (p.36)",
        "audience": "IES,docentes,territorios",
        "base": "estrategia_es_QA_50_enriquecido"
      }
    },
    {
      "id": "estrategia_es_QA_50_enriquecido__044",
      "title": "¿Qué fenómenos se consideran desafíos de futuro en la Estrategia?",
      "source": "Estrategia ES.pdf",
      "text": "Q: ¿Qué fenómenos se consideran desafíos de futuro en la Estrategia?\n\nA: Se destacan seis fenómenos globales: transición digital; seguridad alimentaria y salud integral; sustentabilidad planetaria; crisis de la democracia y gobernanza global; desigualdad social y contrato intergeneracional; y fragmentación geopolítica y económica. Informan la anticipación y articulación de agendas y políticas CTCI.\n\nVariantes:\n- Enumera los seis grandes fenómenos de transformación\n- ¿Cómo informan la anticipación de escenarios?\n- Explica su impacto en configuración de futuros\n- ¿Qué relación tienen con políticas CTCI?\n\n\nMeta:\n- País: Chile\n- Periodo: 2026–2038\n- Sección: Glosario (p.32)\n- Audiencia: policymakers,IES\n- Documento: Estrategia ES.pdf\n- Tags: glosario, desafíos-de-futuro, CTCI",
      "tags": [
        "glosario",
        "desafíos-de-futuro",
        "CTCI"
      ],
      "meta": {
        "country": "Chile",
        "timeframe": "2026–2038",
        "section": "Glosario (p.32)",
        "audience": "policymakers,IES",
        "base": "estrategia_es_QA_50_enriquecido"
      }
    },
    {
      "id": "estrategia_es_QA_50_enriquecido__045",
      "title": "¿Cómo define la Estrategia pertinencia en educación superior?",
      "source": "Estrategia ES.pdf",
      "text": "Q: ¿Cómo define la Estrategia pertinencia en educación superior?\n\nA: La pertinencia es la capacidad de las IES para contribuir permanentemente, conforme a sus fines, al desarrollo del país, sus regiones y comunidades. Se fomenta, particularmente a través del Sinaces, la vinculación con necesidades de la sociedad en las funciones institucionales.\n\nVariantes:\n- ¿Qué relación tiene con desarrollo del país y regiones?\n- Explica el fomento de vinculación con necesidades sociales\n- ¿Cómo se evalúa pertinencia en funciones institucionales?\n- Define el enfoque de pertinencia en la ley\n\n\nMeta:\n- País: Chile\n- Periodo: 2026–2038\n- Sección: Glosario (p.34–35)\n- Audiencia: IES,agencias,policymakers\n- Documento: Estrategia ES.pdf\n- Tags: glosario, pertinencia, Sinaces",
      "tags": [
        "glosario",
        "pertinencia",
        "Sinaces"
      ],
      "meta": {
        "country": "Chile",
        "timeframe": "2026–2038",
        "section": "Glosario (p.34–35)",
        "audience": "IES,agencias,policymakers",
        "base": "estrategia_es_QA_50_enriquecido"
      }
    },
    {
      "id": "estrategia_es_QA_50_enriquecido__046",
      "title": "¿Con qué políticas y estrategias nacionales se articula la Estrategia de Educación Superior?",
      "source": "Estrategia ES.pdf",
      "text": "Q: ¿Con qué políticas y estrategias nacionales se articula la Estrategia de Educación Superior?\n\nA: La Estrategia se articula con la Política y Estrategia Nacional de CTCI, la Estrategia Nacional de Educación Pública, la Estrategia Nacional de Formación Técnico‑Profesional, la Estrategia Nacional de Prospección Laboral y la Política Nacional de Inteligencia Artificial. Se despliega en 12 años (2026–2038) con revisiones cuatrienales para ajustar énfasis y líneas de acción.\n\nVariantes:\n- Enumera políticas CTCI, Educación Pública, Formación TP, Prospección Laboral e IA\n- ¿Por qué la articulación intersistemas es necesaria?\n- Explica el horizonte temporal y revisiones cuatrienales\n- ¿Cómo se coordinan ciclos extendidos de gestión?\n\n\nMeta:\n- País: Chile\n- Periodo: 2026–2038\n- Sección: Introducción y articulación con políticas (p.10–11)\n- Audiencia: policymakers,IES\n- Documento: Estrategia ES.pdf\n- Tags: articulación, CTCI, IA, formación-TP",
      "tags": [
        "articulación",
        "CTCI",
        "IA",
        "formación-TP"
      ],
      "meta": {
        "country": "Chile",
        "timeframe": "2026–2038",
        "section": "Introducción y articulación con políticas (p.10–11)",
        "audience": "policymakers,IES",
        "base": "estrategia_es_QA_50_enriquecido"
      }
    },
    {
      "id": "estrategia_es_QA_50_enriquecido__047",
      "title": "¿Qué metodología de diagnóstico sustenta los nudos críticos de la Estrategia?",
      "source": "Estrategia ES.pdf",
      "text": "Q: ¿Qué metodología de diagnóstico sustenta los nudos críticos de la Estrategia?\n\nA: El diagnóstico se estructuró en cuatro ejes: trayectorias y procesos académicos; asociatividad para conocimiento, innovación e internacionalización; articulación con entornos y desarrollo sostenible; y arquitectura y gobernanza del sistema. Por eje se definieron campos de análisis con temas y subtemas que facilitaron identificar nudos críticos respaldados por evidencia.\n\nVariantes:\n- ¿Qué ejes de trabajo se usaron para el diagnóstico?\n- ¿Cómo se definieron temas y subtemas por eje?\n- Explica el proceso para identificar nudos críticos\n- ¿Qué evidencia respalda los nudos?\n\n\nMeta:\n- País: Chile\n- Periodo: 2026–2038\n- Sección: Organización y Figura 1 (p.13–14)\n- Audiencia: IES,policymakers\n- Documento: Estrategia ES.pdf\n- Tags: diagnóstico, nudos-críticos, ejes",
      "tags": [
        "diagnóstico",
        "nudos-críticos",
        "ejes"
      ],
      "meta": {
        "country": "Chile",
        "timeframe": "2026–2038",
        "section": "Organización y Figura 1 (p.13–14)",
        "audience": "IES,policymakers",
        "base": "estrategia_es_QA_50_enriquecido"
      }
    },
    {
      "id": "estrategia_es_QA_50_enriquecido__048",
      "title": "¿Qué propósito y alcance tiene la Estrategia como carta de navegación del sistema?",
      "source": "Estrategia ES.pdf",
      "text": "Q: ¿Qué propósito y alcance tiene la Estrategia como carta de navegación del sistema?\n\nA: La Estrategia fija rutas y lineamientos para desarrollo del sistema en el mediano y largo plazo sin establecer metas específicas de implementación, otorgando flexibilidad a tomadores de decisión. Convoca coordinación con educación escolar, CTCI, capacitación laboral, certificación de competencias y apoyos y cuidados, en una visión integral y sistémica.\n\nVariantes:\n- ¿Por qué no fija metas concretas de implementación?\n- ¿Qué margen de libertad otorga a tomadores de decisión?\n- Explica la visión integral y comprensiva adoptada\n- ¿Con qué otros sistemas convoca coordinación?\n\n\nMeta:\n- País: Chile\n- Periodo: 2026–2038\n- Sección: Introducción (p.10)\n- Audiencia: policymakers,IES\n- Documento: Estrategia ES.pdf\n- Tags: alcance, propósito, coordinación",
      "tags": [
        "alcance",
        "propósito",
        "coordinación"
      ],
      "meta": {
        "country": "Chile",
        "timeframe": "2026–2038",
        "section": "Introducción (p.10)",
        "audience": "policymakers,IES",
        "base": "estrategia_es_QA_50_enriquecido"
      }
    },
    {
      "id": "estrategia_es_QA_50_enriquecido__049",
      "title": "¿Cómo podría una IES operacionalizar el Desafío 1 en una carrera de alta demanda regional?",
      "source": "Estrategia ES.pdf",
      "text": "Q: ¿Cómo podría una IES operacionalizar el Desafío 1 en una carrera de alta demanda regional?\n\nA: Una IES puede: revisar mallas para opciones de salida intermedia y articulación vertical, adecuar títulos/grados para itinerarios modulares, instalar procesos RAP con microcredenciales, reforzar formación general en habilidades interpersonales y ciudadanas, y desplegar políticas de bienestar con monitoreo de carga académica. Indicadores: tasas de reconocimiento, progresión y titulación oportuna; satisfacción y retención; inserción ocupacional regional.\n\nVariantes:\n- Diseña acciones para trayectorias flexibles en una carrera\n- ¿Qué ajustes de títulos/grados y RAP serían pertinentes?\n- ¿Cómo integrar formación general y bienestar?\n- Propón indicadores para medir avances\n\n\nMeta:\n- País: Chile\n- Periodo: 2026–2038\n- Sección: Desafío 1 y Objetivos 1.1–1.5 (p.16–19)\n- Audiencia: IES,escuelas\n- Documento: Estrategia ES.pdf\n- Tags: implementación, trayectorias, indicadores",
      "tags": [
        "implementación",
        "trayectorias",
        "indicadores"
      ],
      "meta": {
        "country": "Chile",
        "timeframe": "2026–2038",
        "section": "Desafío 1 y Objetivos 1.1–1.5 (p.16–19)",
        "audience": "IES,escuelas",
        "base": "estrategia_es_QA_50_enriquecido"
      }
    },
    {
      "id": "estrategia_es_QA_50_enriquecido__050",
      "title": "¿Qué pasos puede seguir una agencia pública para alinear financiamiento con calidad e impacto (Desafío 4)?",
      "source": "Estrategia ES.pdf",
      "text": "Q: ¿Qué pasos puede seguir una agencia pública para alinear financiamiento con calidad e impacto (Desafío 4)?\n\nA: Pasos: definir estándares diferenciados por misión institucional; diseñar programas de financiamiento por funciones (docencia, investigación, innovación y vinculación) con criterios de calidad, transparencia y desempeño; coordinar instrumentos de I+D+i priorizando impacto; incorporar métricas de progresión e inserción ocupacional a aranceles regulados; y crear incentivos regulatorios y fondos concursables para diversificación de ingresos institucionales.\n\nVariantes:\n- Propón hoja de ruta para implementar líneas 4.5.1–4.5.5\n- ¿Cómo coordinar instrumentos de I+D+i con metas del sistema?\n- ¿Qué métricas usar para resultados formativos en aranceles?\n- ¿Cómo incentivar diversificación de ingresos en IES?\n\n\nMeta:\n- País: Chile\n- Periodo: 2026–2038\n- Sección: Desafío 4 y líneas 4.5.1–4.5.5 (p.28–29)\n- Audiencia: agencias,policymakers\n- Documento: Estrategia ES.pdf\n- Tags: implementación, financiamiento, calidad",
      "tags": [
        "implementación",
        "financiamiento",
        "calidad"
      ],
      "meta": {
        "country": "Chile",
        "timeframe": "2026–2038",
        "section": "Desafío 4 y líneas 4.5.1–4.5.5 (p.28–29)",
        "audience": "agencias,policymakers",
        "base": "estrategia_es_QA_50_enriquecido"
      }
    },
    {
      "id": "universidades_futuro_QA_50__001",
      "title": "¿Qué significa el concepto de universidad por capas?",
      "source": "universidades_futuro_QA_50",
      "text": "Q: ¿Qué significa el concepto de universidad por capas?\n\nA: La universidad por capas concibe la institución como un sistema flexible con un núcleo estable, procesos fluidos y espacios flexibles, integrando campus físicos y digitales.\n\nVariantes:\n- ¿Qué significa el concepto de universidad por capas?\n- ¿Puedes explicar Qué significa el concepto de universidad por capas?\n- ¿En qué consiste Qué significa el concepto de universidad por capas?\n- ¿Cómo se define Qué significa el concepto de universidad por capas?\n\n\nMeta:\n- Documento: universidades_futuro_QA_50\n- Tags: universidad-por-capas",
      "tags": [
        "universidad-por-capas"
      ],
      "meta": {
        "country": "",
        "timeframe": "",
        "section": "",
        "audience": "",
        "base": "universidades_futuro_QA_50"
      }
    },
    {
      "id": "universidades_futuro_QA_50__002",
      "title": "¿Cómo cambia la evaluación del desempeño universitario en este enfoque?",
      "source": "universidades_futuro_QA_50",
      "text": "Q: ¿Cómo cambia la evaluación del desempeño universitario en este enfoque?\n\nA: La evaluación se desplaza desde resultados académicos hacia métricas de impacto social, transformación del entorno y desarrollo de personas.\n\nVariantes:\n- ¿Cómo cambia la evaluación del desempeño universitario en este enfoque?\n- ¿Puedes explicar Cómo cambia la evaluación del desempeño universitario en este enfoque?\n- ¿En qué consiste Cómo cambia la evaluación del desempeño universitario en este enfoque?\n- ¿Cómo se define Cómo cambia la evaluación del desempeño universitario en este enfoque?\n\n\nMeta:\n- Documento: universidades_futuro_QA_50\n- Tags: evaluación-por-impacto",
      "tags": [
        "evaluación-por-impacto"
      ],
      "meta": {
        "country": "",
        "timeframe": "",
        "section": "",
        "audience": "",
        "base": "universidades_futuro_QA_50"
      }
    },
    {
      "id": "universidades_futuro_QA_50__003",
      "title": "¿Qué implica la idea de 'menos universidades y más posibilidades'?",
      "source": "universidades_futuro_QA_50",
      "text": "Q: ¿Qué implica la idea de 'menos universidades y más posibilidades'?\n\nA: El sistema se abre a múltiples proveedores y credenciales alternativas que acompañan el aprendizaje a lo largo de la vida.\n\nVariantes:\n- ¿Qué implica la idea de 'menos universidades y más posibilidades'?\n- ¿Puedes explicar Qué implica la idea de 'menos universidades y más posibilidades'?\n- ¿En qué consiste Qué implica la idea de 'menos universidades y más posibilidades'?\n- ¿Cómo se define Qué implica la idea de 'menos universidades y más posibilidades'?\n\n\nMeta:\n- Documento: universidades_futuro_QA_50\n- Tags: diversidad-de-proveedores",
      "tags": [
        "diversidad-de-proveedores"
      ],
      "meta": {
        "country": "",
        "timeframe": "",
        "section": "",
        "audience": "",
        "base": "universidades_futuro_QA_50"
      }
    },
    {
      "id": "universidades_futuro_QA_50__004",
      "title": "¿Qué es una multiversidad y qué beneficios aporta?",
      "source": "universidades_futuro_QA_50",
      "text": "Q: ¿Qué es una multiversidad y qué beneficios aporta?\n\nA: Ofrece múltiples rutas y certificaciones personalizables, apoyada en tecnologías para acceso inclusivo y flexible.\n\nVariantes:\n- ¿Qué es una multiversidad y qué beneficios aporta?\n- ¿Puedes explicar Qué es una multiversidad y qué beneficios aporta?\n- ¿En qué consiste Qué es una multiversidad y qué beneficios aporta?\n- ¿Cómo se define Qué es una multiversidad y qué beneficios aporta?\n\n\nMeta:\n- Documento: universidades_futuro_QA_50\n- Tags: multiversidad",
      "tags": [
        "multiversidad"
      ],
      "meta": {
        "country": "",
        "timeframe": "",
        "section": "",
        "audience": "",
        "base": "universidades_futuro_QA_50"
      }
    },
    {
      "id": "universidades_futuro_QA_50__005",
      "title": "¿Qué significa que la universidad sea ecosistémica?",
      "source": "universidades_futuro_QA_50",
      "text": "Q: ¿Qué significa que la universidad sea ecosistémica?\n\nA: Implica conectarse con empresas, gobiernos y organizaciones sociales para co-desarrollar docencia, investigación y transferencia.\n\nVariantes:\n- ¿Qué significa que la universidad sea ecosistémica?\n- ¿Puedes explicar Qué significa que la universidad sea ecosistémica?\n- ¿En qué consiste Qué significa que la universidad sea ecosistémica?\n- ¿Cómo se define Qué significa que la universidad sea ecosistémica?\n\n\nMeta:\n- Documento: universidades_futuro_QA_50\n- Tags: ecosistema",
      "tags": [
        "ecosistema"
      ],
      "meta": {
        "country": "",
        "timeframe": "",
        "section": "",
        "audience": "",
        "base": "universidades_futuro_QA_50"
      }
    },
    {
      "id": "universidades_futuro_QA_50__006",
      "title": "¿Qué son los 'viajes y caminos' del estudiante?",
      "source": "universidades_futuro_QA_50",
      "text": "Q: ¿Qué son los 'viajes y caminos' del estudiante?\n\nA: Cada persona diseña su itinerario con combinaciones de formatos, tiempos y modalidades.\n\nVariantes:\n- ¿Qué son los 'viajes y caminos' del estudiante?\n- ¿Puedes explicar Qué son los 'viajes y caminos' del estudiante?\n- ¿En qué consiste Qué son los 'viajes y caminos' del estudiante?\n- ¿Cómo se define Qué son los 'viajes y caminos' del estudiante?\n\n\nMeta:\n- Documento: universidades_futuro_QA_50\n- Tags: viajes-del-estudiante",
      "tags": [
        "viajes-del-estudiante"
      ],
      "meta": {
        "country": "",
        "timeframe": "",
        "section": "",
        "audience": "",
        "base": "universidades_futuro_QA_50"
      }
    },
    {
      "id": "universidades_futuro_QA_50__007",
      "title": "¿Qué son las experiencias de aprendizaje aumentadas?",
      "source": "universidades_futuro_QA_50",
      "text": "Q: ¿Qué son las experiencias de aprendizaje aumentadas?\n\nA: Combinan entornos físicos y digitales, datos, analítica e IA para aprendizajes interactivos y relevantes.\n\nVariantes:\n- ¿Qué son las experiencias de aprendizaje aumentadas?\n- ¿Puedes explicar Qué son las experiencias de aprendizaje aumentadas?\n- ¿En qué consiste Qué son las experiencias de aprendizaje aumentadas?\n- ¿Cómo se define Qué son las experiencias de aprendizaje aumentadas?\n\n\nMeta:\n- Documento: universidades_futuro_QA_50\n- Tags: aprendizaje-aumentado",
      "tags": [
        "aprendizaje-aumentado"
      ],
      "meta": {
        "country": "",
        "timeframe": "",
        "section": "",
        "audience": "",
        "base": "universidades_futuro_QA_50"
      }
    },
    {
      "id": "universidades_futuro_QA_50__008",
      "title": "¿Qué se propone para pasar de sobrevivir a prosperar en la incertidumbre?",
      "source": "universidades_futuro_QA_50",
      "text": "Q: ¿Qué se propone para pasar de sobrevivir a prosperar en la incertidumbre?\n\nA: Anticipación, innovación y aprendizaje continuo con experimentación controlada.\n\nVariantes:\n- ¿Qué se propone para pasar de sobrevivir a prosperar en la incertidumbre?\n- ¿Puedes explicar Qué se propone para pasar de sobrevivir a prosperar en la incertidumbre?\n- ¿En qué consiste Qué se propone para pasar de sobrevivir a prosperar en la incertidumbre?\n- ¿Cómo se define Qué se propone para pasar de sobrevivir a prosperar en la incertidumbre?\n\n\nMeta:\n- Documento: universidades_futuro_QA_50\n- Tags: incertidumbre",
      "tags": [
        "incertidumbre"
      ],
      "meta": {
        "country": "",
        "timeframe": "",
        "section": "",
        "audience": "",
        "base": "universidades_futuro_QA_50"
      }
    },
    {
      "id": "universidades_futuro_QA_50__009",
      "title": "¿Qué capacidades habilitan la universidad por capas?",
      "source": "universidades_futuro_QA_50",
      "text": "Q: ¿Qué capacidades habilitan la universidad por capas?\n\nA: Gobernanza para innovar, datos como insumo estratégico, colaboración abierta y enfoque de equidad.\n\nVariantes:\n- ¿Qué capacidades habilitan la universidad por capas?\n- ¿Puedes explicar Qué capacidades habilitan la universidad por capas?\n- ¿En qué consiste Qué capacidades habilitan la universidad por capas?\n- ¿Cómo se define Qué capacidades habilitan la universidad por capas?\n\n\nMeta:\n- Documento: universidades_futuro_QA_50\n- Tags: capacidades-institucionales",
      "tags": [
        "capacidades-institucionales"
      ],
      "meta": {
        "country": "",
        "timeframe": "",
        "section": "",
        "audience": "",
        "base": "universidades_futuro_QA_50"
      }
    },
    {
      "id": "universidades_futuro_QA_50__010",
      "title": "¿Cuál es el papel de la tecnología en la transformación universitaria?",
      "source": "universidades_futuro_QA_50",
      "text": "Q: ¿Cuál es el papel de la tecnología en la transformación universitaria?\n\nA: Habilitador transversal que permite personalización, escalabilidad y pertinencia.\n\nVariantes:\n- ¿Cuál es el papel de la tecnología en la transformación universitaria?\n- ¿Puedes explicar Cuál es el papel de la tecnología en la transformación universitaria?\n- ¿En qué consiste Cuál es el papel de la tecnología en la transformación universitaria?\n- ¿Cómo se define Cuál es el papel de la tecnología en la transformación universitaria?\n\n\nMeta:\n- Documento: universidades_futuro_QA_50\n- Tags: tecnología-habilitadora",
      "tags": [
        "tecnología-habilitadora"
      ],
      "meta": {
        "country": "",
        "timeframe": "",
        "section": "",
        "audience": "",
        "base": "universidades_futuro_QA_50"
      }
    },
    {
      "id": "universidades_futuro_QA_50__011",
      "title": "¿Qué caracteriza gobernanza emprendedora en la universidad del futuro?",
      "source": "universidades_futuro_QA_50",
      "text": "Q: ¿Qué caracteriza gobernanza emprendedora en la universidad del futuro?\n\nA: Gobernanza emprendedora se concibe como un componente clave de la transformación universitaria, alineando prácticas y decisiones con impacto, calidad, equidad y adaptación tecnológica.\n\nVariantes:\n- ¿Qué caracteriza gobernanza emprendedora en la universidad del futuro?\n- ¿Puedes explicar Qué caracteriza gobernanza emprendedora en la universidad del futuro?\n- ¿En qué consiste Qué caracteriza gobernanza emprendedora en la universidad del futuro?\n- ¿Cómo se define Qué caracteriza gobernanza emprendedora en la universidad del futuro?\n\n\nMeta:\n- Documento: universidades_futuro_QA_50\n- Tags: gobernanza-emprendedora",
      "tags": [
        "gobernanza-emprendedora"
      ],
      "meta": {
        "country": "",
        "timeframe": "",
        "section": "",
        "audience": "",
        "base": "universidades_futuro_QA_50"
      }
    },
    {
      "id": "universidades_futuro_QA_50__012",
      "title": "¿Qué caracteriza campus híbrido en la universidad del futuro?",
      "source": "universidades_futuro_QA_50",
      "text": "Q: ¿Qué caracteriza campus híbrido en la universidad del futuro?\n\nA: Campus híbrido se concibe como un componente clave de la transformación universitaria, alineando prácticas y decisiones con impacto, calidad, equidad y adaptación tecnológica.\n\nVariantes:\n- ¿Qué caracteriza campus híbrido en la universidad del futuro?\n- ¿Puedes explicar Qué caracteriza campus híbrido en la universidad del futuro?\n- ¿En qué consiste Qué caracteriza campus híbrido en la universidad del futuro?\n- ¿Cómo se define Qué caracteriza campus híbrido en la universidad del futuro?\n\n\nMeta:\n- Documento: universidades_futuro_QA_50\n- Tags: campus-híbrido",
      "tags": [
        "campus-híbrido"
      ],
      "meta": {
        "country": "",
        "timeframe": "",
        "section": "",
        "audience": "",
        "base": "universidades_futuro_QA_50"
      }
    },
    {
      "id": "universidades_futuro_QA_50__013",
      "title": "¿Qué caracteriza rol docente en la universidad del futuro?",
      "source": "universidades_futuro_QA_50",
      "text": "Q: ¿Qué caracteriza rol docente en la universidad del futuro?\n\nA: Rol docente se concibe como un componente clave de la transformación universitaria, alineando prácticas y decisiones con impacto, calidad, equidad y adaptación tecnológica.\n\nVariantes:\n- ¿Qué caracteriza rol docente en la universidad del futuro?\n- ¿Puedes explicar Qué caracteriza rol docente en la universidad del futuro?\n- ¿En qué consiste Qué caracteriza rol docente en la universidad del futuro?\n- ¿Cómo se define Qué caracteriza rol docente en la universidad del futuro?\n\n\nMeta:\n- Documento: universidades_futuro_QA_50\n- Tags: rol-docente",
      "tags": [
        "rol-docente"
      ],
      "meta": {
        "country": "",
        "timeframe": "",
        "section": "",
        "audience": "",
        "base": "universidades_futuro_QA_50"
      }
    },
    {
      "id": "universidades_futuro_QA_50__014",
      "title": "¿Qué caracteriza corresponsabilidad laboral en la universidad del futuro?",
      "source": "universidades_futuro_QA_50",
      "text": "Q: ¿Qué caracteriza corresponsabilidad laboral en la universidad del futuro?\n\nA: Corresponsabilidad laboral se concibe como un componente clave de la transformación universitaria, alineando prácticas y decisiones con impacto, calidad, equidad y adaptación tecnológica.\n\nVariantes:\n- ¿Qué caracteriza corresponsabilidad laboral en la universidad del futuro?\n- ¿Puedes explicar Qué caracteriza corresponsabilidad laboral en la universidad del futuro?\n- ¿En qué consiste Qué caracteriza corresponsabilidad laboral en la universidad del futuro?\n- ¿Cómo se define Qué caracteriza corresponsabilidad laboral en la universidad del futuro?\n\n\nMeta:\n- Documento: universidades_futuro_QA_50\n- Tags: corresponsabilidad-laboral",
      "tags": [
        "corresponsabilidad-laboral"
      ],
      "meta": {
        "country": "",
        "timeframe": "",
        "section": "",
        "audience": "",
        "base": "universidades_futuro_QA_50"
      }
    },
    {
      "id": "universidades_futuro_QA_50__015",
      "title": "¿Qué caracteriza comunicación del conocimiento en la universidad del futuro?",
      "source": "universidades_futuro_QA_50",
      "text": "Q: ¿Qué caracteriza comunicación del conocimiento en la universidad del futuro?\n\nA: Comunicación del conocimiento se concibe como un componente clave de la transformación universitaria, alineando prácticas y decisiones con impacto, calidad, equidad y adaptación tecnológica.\n\nVariantes:\n- ¿Qué caracteriza comunicación del conocimiento en la universidad del futuro?\n- ¿Puedes explicar Qué caracteriza comunicación del conocimiento en la universidad del futuro?\n- ¿En qué consiste Qué caracteriza comunicación del conocimiento en la universidad del futuro?\n- ¿Cómo se define Qué caracteriza comunicación del conocimiento en la universidad del futuro?\n\n\nMeta:\n- Documento: universidades_futuro_QA_50\n- Tags: comunicación-del-conocimiento",
      "tags": [
        "comunicación-del-conocimiento"
      ],
      "meta": {
        "country": "",
        "timeframe": "",
        "section": "",
        "audience": "",
        "base": "universidades_futuro_QA_50"
      }
    },
    {
      "id": "universidades_futuro_QA_50__016",
      "title": "¿Qué caracteriza innovación bajo restricciones en la universidad del futuro?",
      "source": "universidades_futuro_QA_50",
      "text": "Q: ¿Qué caracteriza innovación bajo restricciones en la universidad del futuro?\n\nA: Innovación bajo restricciones se concibe como un componente clave de la transformación universitaria, alineando prácticas y decisiones con impacto, calidad, equidad y adaptación tecnológica.\n\nVariantes:\n- ¿Qué caracteriza innovación bajo restricciones en la universidad del futuro?\n- ¿Puedes explicar Qué caracteriza innovación bajo restricciones en la universidad del futuro?\n- ¿En qué consiste Qué caracteriza innovación bajo restricciones en la universidad del futuro?\n- ¿Cómo se define Qué caracteriza innovación bajo restricciones en la universidad del futuro?\n\n\nMeta:\n- Documento: universidades_futuro_QA_50\n- Tags: innovación-bajo-restricciones",
      "tags": [
        "innovación-bajo-restricciones"
      ],
      "meta": {
        "country": "",
        "timeframe": "",
        "section": "",
        "audience": "",
        "base": "universidades_futuro_QA_50"
      }
    },
    {
      "id": "universidades_futuro_QA_50__017",
      "title": "¿Qué caracteriza tic e ia en enseñanza en la universidad del futuro?",
      "source": "universidades_futuro_QA_50",
      "text": "Q: ¿Qué caracteriza tic e ia en enseñanza en la universidad del futuro?\n\nA: TIC e IA en enseñanza se concibe como un componente clave de la transformación universitaria, alineando prácticas y decisiones con impacto, calidad, equidad y adaptación tecnológica.\n\nVariantes:\n- ¿Qué caracteriza tic e ia en enseñanza en la universidad del futuro?\n- ¿Puedes explicar Qué caracteriza tic e ia en enseñanza en la universidad del futuro?\n- ¿En qué consiste Qué caracteriza tic e ia en enseñanza en la universidad del futuro?\n- ¿Cómo se define Qué caracteriza tic e ia en enseñanza en la universidad del futuro?\n\n\nMeta:\n- Documento: universidades_futuro_QA_50\n- Tags: tic-e-ia-en-enseñanza",
      "tags": [
        "tic-e-ia-en-enseñanza"
      ],
      "meta": {
        "country": "",
        "timeframe": "",
        "section": "",
        "audience": "",
        "base": "universidades_futuro_QA_50"
      }
    },
    {
      "id": "universidades_futuro_QA_50__018",
      "title": "¿Qué caracteriza competencias digitales docentes en la universidad del futuro?",
      "source": "universidades_futuro_QA_50",
      "text": "Q: ¿Qué caracteriza competencias digitales docentes en la universidad del futuro?\n\nA: Competencias digitales docentes se concibe como un componente clave de la transformación universitaria, alineando prácticas y decisiones con impacto, calidad, equidad y adaptación tecnológica.\n\nVariantes:\n- ¿Qué caracteriza competencias digitales docentes en la universidad del futuro?\n- ¿Puedes explicar Qué caracteriza competencias digitales docentes en la universidad del futuro?\n- ¿En qué consiste Qué caracteriza competencias digitales docentes en la universidad del futuro?\n- ¿Cómo se define Qué caracteriza competencias digitales docentes en la universidad del futuro?\n\n\nMeta:\n- Documento: universidades_futuro_QA_50\n- Tags: competencias-digitales-docentes",
      "tags": [
        "competencias-digitales-docentes"
      ],
      "meta": {
        "country": "",
        "timeframe": "",
        "section": "",
        "audience": "",
        "base": "universidades_futuro_QA_50"
      }
    },
    {
      "id": "universidades_futuro_QA_50__019",
      "title": "¿Qué caracteriza infraestructura y equidad en la universidad del futuro?",
      "source": "universidades_futuro_QA_50",
      "text": "Q: ¿Qué caracteriza infraestructura y equidad en la universidad del futuro?\n\nA: Infraestructura y equidad se concibe como un componente clave de la transformación universitaria, alineando prácticas y decisiones con impacto, calidad, equidad y adaptación tecnológica.\n\nVariantes:\n- ¿Qué caracteriza infraestructura y equidad en la universidad del futuro?\n- ¿Puedes explicar Qué caracteriza infraestructura y equidad en la universidad del futuro?\n- ¿En qué consiste Qué caracteriza infraestructura y equidad en la universidad del futuro?\n- ¿Cómo se define Qué caracteriza infraestructura y equidad en la universidad del futuro?\n\n\nMeta:\n- Documento: universidades_futuro_QA_50\n- Tags: infraestructura-y-equidad",
      "tags": [
        "infraestructura-y-equidad"
      ],
      "meta": {
        "country": "",
        "timeframe": "",
        "section": "",
        "audience": "",
        "base": "universidades_futuro_QA_50"
      }
    },
    {
      "id": "universidades_futuro_QA_50__020",
      "title": "¿Qué caracteriza ética y datos en la universidad del futuro?",
      "source": "universidades_futuro_QA_50",
      "text": "Q: ¿Qué caracteriza ética y datos en la universidad del futuro?\n\nA: Ética y datos se concibe como un componente clave de la transformación universitaria, alineando prácticas y decisiones con impacto, calidad, equidad y adaptación tecnológica.\n\nVariantes:\n- ¿Qué caracteriza ética y datos en la universidad del futuro?\n- ¿Puedes explicar Qué caracteriza ética y datos en la universidad del futuro?\n- ¿En qué consiste Qué caracteriza ética y datos en la universidad del futuro?\n- ¿Cómo se define Qué caracteriza ética y datos en la universidad del futuro?\n\n\nMeta:\n- Documento: universidades_futuro_QA_50\n- Tags: ética-y-datos",
      "tags": [
        "ética-y-datos"
      ],
      "meta": {
        "country": "",
        "timeframe": "",
        "section": "",
        "audience": "",
        "base": "universidades_futuro_QA_50"
      }
    },
    {
      "id": "universidades_futuro_QA_50__021",
      "title": "¿Qué caracteriza cultura de innovación en la universidad del futuro?",
      "source": "universidades_futuro_QA_50",
      "text": "Q: ¿Qué caracteriza cultura de innovación en la universidad del futuro?\n\nA: Cultura de innovación se concibe como un componente clave de la transformación universitaria, alineando prácticas y decisiones con impacto, calidad, equidad y adaptación tecnológica.\n\nVariantes:\n- ¿Qué caracteriza cultura de innovación en la universidad del futuro?\n- ¿Puedes explicar Qué caracteriza cultura de innovación en la universidad del futuro?\n- ¿En qué consiste Qué caracteriza cultura de innovación en la universidad del futuro?\n- ¿Cómo se define Qué caracteriza cultura de innovación en la universidad del futuro?\n\n\nMeta:\n- Documento: universidades_futuro_QA_50\n- Tags: cultura-de-innovación",
      "tags": [
        "cultura-de-innovación"
      ],
      "meta": {
        "country": "",
        "timeframe": "",
        "section": "",
        "audience": "",
        "base": "universidades_futuro_QA_50"
      }
    },
    {
      "id": "universidades_futuro_QA_50__022",
      "title": "¿Qué caracteriza evaluación de impactos en la universidad del futuro?",
      "source": "universidades_futuro_QA_50",
      "text": "Q: ¿Qué caracteriza evaluación de impactos en la universidad del futuro?\n\nA: Evaluación de impactos se concibe como un componente clave de la transformación universitaria, alineando prácticas y decisiones con impacto, calidad, equidad y adaptación tecnológica.\n\nVariantes:\n- ¿Qué caracteriza evaluación de impactos en la universidad del futuro?\n- ¿Puedes explicar Qué caracteriza evaluación de impactos en la universidad del futuro?\n- ¿En qué consiste Qué caracteriza evaluación de impactos en la universidad del futuro?\n- ¿Cómo se define Qué caracteriza evaluación de impactos en la universidad del futuro?\n\n\nMeta:\n- Documento: universidades_futuro_QA_50\n- Tags: evaluación-de-impactos",
      "tags": [
        "evaluación-de-impactos"
      ],
      "meta": {
        "country": "",
        "timeframe": "",
        "section": "",
        "audience": "",
        "base": "universidades_futuro_QA_50"
      }
    },
    {
      "id": "universidades_futuro_QA_50__023",
      "title": "¿Qué caracteriza universidad ubicua en la universidad del futuro?",
      "source": "universidades_futuro_QA_50",
      "text": "Q: ¿Qué caracteriza universidad ubicua en la universidad del futuro?\n\nA: Universidad ubicua se concibe como un componente clave de la transformación universitaria, alineando prácticas y decisiones con impacto, calidad, equidad y adaptación tecnológica.\n\nVariantes:\n- ¿Qué caracteriza universidad ubicua en la universidad del futuro?\n- ¿Puedes explicar Qué caracteriza universidad ubicua en la universidad del futuro?\n- ¿En qué consiste Qué caracteriza universidad ubicua en la universidad del futuro?\n- ¿Cómo se define Qué caracteriza universidad ubicua en la universidad del futuro?\n\n\nMeta:\n- Documento: universidades_futuro_QA_50\n- Tags: universidad-ubicua",
      "tags": [
        "universidad-ubicua"
      ],
      "meta": {
        "country": "",
        "timeframe": "",
        "section": "",
        "audience": "",
        "base": "universidades_futuro_QA_50"
      }
    },
    {
      "id": "universidades_futuro_QA_50__024",
      "title": "¿Qué caracteriza presiones globales en la universidad del futuro?",
      "source": "universidades_futuro_QA_50",
      "text": "Q: ¿Qué caracteriza presiones globales en la universidad del futuro?\n\nA: Presiones globales se concibe como un componente clave de la transformación universitaria, alineando prácticas y decisiones con impacto, calidad, equidad y adaptación tecnológica.\n\nVariantes:\n- ¿Qué caracteriza presiones globales en la universidad del futuro?\n- ¿Puedes explicar Qué caracteriza presiones globales en la universidad del futuro?\n- ¿En qué consiste Qué caracteriza presiones globales en la universidad del futuro?\n- ¿Cómo se define Qué caracteriza presiones globales en la universidad del futuro?\n\n\nMeta:\n- Documento: universidades_futuro_QA_50\n- Tags: presiones-globales",
      "tags": [
        "presiones-globales"
      ],
      "meta": {
        "country": "",
        "timeframe": "",
        "section": "",
        "audience": "",
        "base": "universidades_futuro_QA_50"
      }
    },
    {
      "id": "universidades_futuro_QA_50__025",
      "title": "¿Qué caracteriza exploración de lo desconocido en la universidad del futuro?",
      "source": "universidades_futuro_QA_50",
      "text": "Q: ¿Qué caracteriza exploración de lo desconocido en la universidad del futuro?\n\nA: Exploración de lo desconocido se concibe como un componente clave de la transformación universitaria, alineando prácticas y decisiones con impacto, calidad, equidad y adaptación tecnológica.\n\nVariantes:\n- ¿Qué caracteriza exploración de lo desconocido en la universidad del futuro?\n- ¿Puedes explicar Qué caracteriza exploración de lo desconocido en la universidad del futuro?\n- ¿En qué consiste Qué caracteriza exploración de lo desconocido en la universidad del futuro?\n- ¿Cómo se define Qué caracteriza exploración de lo desconocido en la universidad del futuro?\n\n\nMeta:\n- Documento: universidades_futuro_QA_50\n- Tags: exploración-de-lo-desconocido",
      "tags": [
        "exploración-de-lo-desconocido"
      ],
      "meta": {
        "country": "",
        "timeframe": "",
        "section": "",
        "audience": "",
        "base": "universidades_futuro_QA_50"
      }
    },
    {
      "id": "universidades_futuro_QA_50__026",
      "title": "¿Qué caracteriza gobernanza anticipatoria en la universidad del futuro?",
      "source": "universidades_futuro_QA_50",
      "text": "Q: ¿Qué caracteriza gobernanza anticipatoria en la universidad del futuro?\n\nA: Gobernanza anticipatoria se concibe como un componente clave de la transformación universitaria, alineando prácticas y decisiones con impacto, calidad, equidad y adaptación tecnológica.\n\nVariantes:\n- ¿Qué caracteriza gobernanza anticipatoria en la universidad del futuro?\n- ¿Puedes explicar Qué caracteriza gobernanza anticipatoria en la universidad del futuro?\n- ¿En qué consiste Qué caracteriza gobernanza anticipatoria en la universidad del futuro?\n- ¿Cómo se define Qué caracteriza gobernanza anticipatoria en la universidad del futuro?\n\n\nMeta:\n- Documento: universidades_futuro_QA_50\n- Tags: gobernanza-anticipatoria",
      "tags": [
        "gobernanza-anticipatoria"
      ],
      "meta": {
        "country": "",
        "timeframe": "",
        "section": "",
        "audience": "",
        "base": "universidades_futuro_QA_50"
      }
    },
    {
      "id": "universidades_futuro_QA_50__027",
      "title": "¿Qué caracteriza instrumentos de anticipación en la universidad del futuro?",
      "source": "universidades_futuro_QA_50",
      "text": "Q: ¿Qué caracteriza instrumentos de anticipación en la universidad del futuro?\n\nA: Instrumentos de anticipación se concibe como un componente clave de la transformación universitaria, alineando prácticas y decisiones con impacto, calidad, equidad y adaptación tecnológica.\n\nVariantes:\n- ¿Qué caracteriza instrumentos de anticipación en la universidad del futuro?\n- ¿Puedes explicar Qué caracteriza instrumentos de anticipación en la universidad del futuro?\n- ¿En qué consiste Qué caracteriza instrumentos de anticipación en la universidad del futuro?\n- ¿Cómo se define Qué caracteriza instrumentos de anticipación en la universidad del futuro?\n\n\nMeta:\n- Documento: universidades_futuro_QA_50\n- Tags: instrumentos-de-anticipación",
      "tags": [
        "instrumentos-de-anticipación"
      ],
      "meta": {
        "country": "",
        "timeframe": "",
        "section": "",
        "audience": "",
        "base": "universidades_futuro_QA_50"
      }
    },
    {
      "id": "universidades_futuro_QA_50__028",
      "title": "¿Qué caracteriza diagnóstico de competencias en la universidad del futuro?",
      "source": "universidades_futuro_QA_50",
      "text": "Q: ¿Qué caracteriza diagnóstico de competencias en la universidad del futuro?\n\nA: Diagnóstico de competencias se concibe como un componente clave de la transformación universitaria, alineando prácticas y decisiones con impacto, calidad, equidad y adaptación tecnológica.\n\nVariantes:\n- ¿Qué caracteriza diagnóstico de competencias en la universidad del futuro?\n- ¿Puedes explicar Qué caracteriza diagnóstico de competencias en la universidad del futuro?\n- ¿En qué consiste Qué caracteriza diagnóstico de competencias en la universidad del futuro?\n- ¿Cómo se define Qué caracteriza diagnóstico de competencias en la universidad del futuro?\n\n\nMeta:\n- Documento: universidades_futuro_QA_50\n- Tags: diagnóstico-de-competencias",
      "tags": [
        "diagnóstico-de-competencias"
      ],
      "meta": {
        "country": "",
        "timeframe": "",
        "section": "",
        "audience": "",
        "base": "universidades_futuro_QA_50"
      }
    },
    {
      "id": "universidades_futuro_QA_50__029",
      "title": "¿Qué caracteriza formación docente en la universidad del futuro?",
      "source": "universidades_futuro_QA_50",
      "text": "Q: ¿Qué caracteriza formación docente en la universidad del futuro?\n\nA: Formación docente se concibe como un componente clave de la transformación universitaria, alineando prácticas y decisiones con impacto, calidad, equidad y adaptación tecnológica.\n\nVariantes:\n- ¿Qué caracteriza formación docente en la universidad del futuro?\n- ¿Puedes explicar Qué caracteriza formación docente en la universidad del futuro?\n- ¿En qué consiste Qué caracteriza formación docente en la universidad del futuro?\n- ¿Cómo se define Qué caracteriza formación docente en la universidad del futuro?\n\n\nMeta:\n- Documento: universidades_futuro_QA_50\n- Tags: formación-docente",
      "tags": [
        "formación-docente"
      ],
      "meta": {
        "country": "",
        "timeframe": "",
        "section": "",
        "audience": "",
        "base": "universidades_futuro_QA_50"
      }
    },
    {
      "id": "universidades_futuro_QA_50__030",
      "title": "¿Qué caracteriza ciudadanía digital en la universidad del futuro?",
      "source": "universidades_futuro_QA_50",
      "text": "Q: ¿Qué caracteriza ciudadanía digital en la universidad del futuro?\n\nA: Ciudadanía digital se concibe como un componente clave de la transformación universitaria, alineando prácticas y decisiones con impacto, calidad, equidad y adaptación tecnológica.\n\nVariantes:\n- ¿Qué caracteriza ciudadanía digital en la universidad del futuro?\n- ¿Puedes explicar Qué caracteriza ciudadanía digital en la universidad del futuro?\n- ¿En qué consiste Qué caracteriza ciudadanía digital en la universidad del futuro?\n- ¿Cómo se define Qué caracteriza ciudadanía digital en la universidad del futuro?\n\n\nMeta:\n- Documento: universidades_futuro_QA_50\n- Tags: ciudadanía-digital",
      "tags": [
        "ciudadanía-digital"
      ],
      "meta": {
        "country": "",
        "timeframe": "",
        "section": "",
        "audience": "",
        "base": "universidades_futuro_QA_50"
      }
    },
    {
      "id": "universidades_futuro_QA_50__031",
      "title": "¿Qué caracteriza creatividad estudiantil en la universidad del futuro?",
      "source": "universidades_futuro_QA_50",
      "text": "Q: ¿Qué caracteriza creatividad estudiantil en la universidad del futuro?\n\nA: Creatividad estudiantil se concibe como un componente clave de la transformación universitaria, alineando prácticas y decisiones con impacto, calidad, equidad y adaptación tecnológica.\n\nVariantes:\n- ¿Qué caracteriza creatividad estudiantil en la universidad del futuro?\n- ¿Puedes explicar Qué caracteriza creatividad estudiantil en la universidad del futuro?\n- ¿En qué consiste Qué caracteriza creatividad estudiantil en la universidad del futuro?\n- ¿Cómo se define Qué caracteriza creatividad estudiantil en la universidad del futuro?\n\n\nMeta:\n- Documento: universidades_futuro_QA_50\n- Tags: creatividad-estudiantil",
      "tags": [
        "creatividad-estudiantil"
      ],
      "meta": {
        "country": "",
        "timeframe": "",
        "section": "",
        "audience": "",
        "base": "universidades_futuro_QA_50"
      }
    },
    {
      "id": "universidades_futuro_QA_50__032",
      "title": "¿Qué caracteriza brechas digitales en la universidad del futuro?",
      "source": "universidades_futuro_QA_50",
      "text": "Q: ¿Qué caracteriza brechas digitales en la universidad del futuro?\n\nA: Brechas digitales se concibe como un componente clave de la transformación universitaria, alineando prácticas y decisiones con impacto, calidad, equidad y adaptación tecnológica.\n\nVariantes:\n- ¿Qué caracteriza brechas digitales en la universidad del futuro?\n- ¿Puedes explicar Qué caracteriza brechas digitales en la universidad del futuro?\n- ¿En qué consiste Qué caracteriza brechas digitales en la universidad del futuro?\n- ¿Cómo se define Qué caracteriza brechas digitales en la universidad del futuro?\n\n\nMeta:\n- Documento: universidades_futuro_QA_50\n- Tags: brechas-digitales",
      "tags": [
        "brechas-digitales"
      ],
      "meta": {
        "country": "",
        "timeframe": "",
        "section": "",
        "audience": "",
        "base": "universidades_futuro_QA_50"
      }
    },
    {
      "id": "universidades_futuro_QA_50__033",
      "title": "¿Qué caracteriza diversificación y autonomía en la universidad del futuro?",
      "source": "universidades_futuro_QA_50",
      "text": "Q: ¿Qué caracteriza diversificación y autonomía en la universidad del futuro?\n\nA: Diversificación y autonomía se concibe como un componente clave de la transformación universitaria, alineando prácticas y decisiones con impacto, calidad, equidad y adaptación tecnológica.\n\nVariantes:\n- ¿Qué caracteriza diversificación y autonomía en la universidad del futuro?\n- ¿Puedes explicar Qué caracteriza diversificación y autonomía en la universidad del futuro?\n- ¿En qué consiste Qué caracteriza diversificación y autonomía en la universidad del futuro?\n- ¿Cómo se define Qué caracteriza diversificación y autonomía en la universidad del futuro?\n\n\nMeta:\n- Documento: universidades_futuro_QA_50\n- Tags: diversificación-y-autonomía",
      "tags": [
        "diversificación-y-autonomía"
      ],
      "meta": {
        "country": "",
        "timeframe": "",
        "section": "",
        "audience": "",
        "base": "universidades_futuro_QA_50"
      }
    },
    {
      "id": "universidades_futuro_QA_50__034",
      "title": "¿Qué caracteriza meritocracia en la universidad del futuro?",
      "source": "universidades_futuro_QA_50",
      "text": "Q: ¿Qué caracteriza meritocracia en la universidad del futuro?\n\nA: Meritocracia se concibe como un componente clave de la transformación universitaria, alineando prácticas y decisiones con impacto, calidad, equidad y adaptación tecnológica.\n\nVariantes:\n- ¿Qué caracteriza meritocracia en la universidad del futuro?\n- ¿Puedes explicar Qué caracteriza meritocracia en la universidad del futuro?\n- ¿En qué consiste Qué caracteriza meritocracia en la universidad del futuro?\n- ¿Cómo se define Qué caracteriza meritocracia en la universidad del futuro?\n\n\nMeta:\n- Documento: universidades_futuro_QA_50\n- Tags: meritocracia",
      "tags": [
        "meritocracia"
      ],
      "meta": {
        "country": "",
        "timeframe": "",
        "section": "",
        "audience": "",
        "base": "universidades_futuro_QA_50"
      }
    },
    {
      "id": "universidades_futuro_QA_50__035",
      "title": "¿Qué caracteriza docencia como legitimidad en la universidad del futuro?",
      "source": "universidades_futuro_QA_50",
      "text": "Q: ¿Qué caracteriza docencia como legitimidad en la universidad del futuro?\n\nA: Docencia como legitimidad se concibe como un componente clave de la transformación universitaria, alineando prácticas y decisiones con impacto, calidad, equidad y adaptación tecnológica.\n\nVariantes:\n- ¿Qué caracteriza docencia como legitimidad en la universidad del futuro?\n- ¿Puedes explicar Qué caracteriza docencia como legitimidad en la universidad del futuro?\n- ¿En qué consiste Qué caracteriza docencia como legitimidad en la universidad del futuro?\n- ¿Cómo se define Qué caracteriza docencia como legitimidad en la universidad del futuro?\n\n\nMeta:\n- Documento: universidades_futuro_QA_50\n- Tags: docencia-como-legitimidad",
      "tags": [
        "docencia-como-legitimidad"
      ],
      "meta": {
        "country": "",
        "timeframe": "",
        "section": "",
        "audience": "",
        "base": "universidades_futuro_QA_50"
      }
    },
    {
      "id": "universidades_futuro_QA_50__036",
      "title": "¿Qué caracteriza profesionalización docente en la universidad del futuro?",
      "source": "universidades_futuro_QA_50",
      "text": "Q: ¿Qué caracteriza profesionalización docente en la universidad del futuro?\n\nA: Profesionalización docente se concibe como un componente clave de la transformación universitaria, alineando prácticas y decisiones con impacto, calidad, equidad y adaptación tecnológica.\n\nVariantes:\n- ¿Qué caracteriza profesionalización docente en la universidad del futuro?\n- ¿Puedes explicar Qué caracteriza profesionalización docente en la universidad del futuro?\n- ¿En qué consiste Qué caracteriza profesionalización docente en la universidad del futuro?\n- ¿Cómo se define Qué caracteriza profesionalización docente en la universidad del futuro?\n\n\nMeta:\n- Documento: universidades_futuro_QA_50\n- Tags: profesionalización-docente",
      "tags": [
        "profesionalización-docente"
      ],
      "meta": {
        "country": "",
        "timeframe": "",
        "section": "",
        "audience": "",
        "base": "universidades_futuro_QA_50"
      }
    },
    {
      "id": "universidades_futuro_QA_50__037",
      "title": "¿Qué caracteriza carreras flexibles en la universidad del futuro?",
      "source": "universidades_futuro_QA_50",
      "text": "Q: ¿Qué caracteriza carreras flexibles en la universidad del futuro?\n\nA: Carreras flexibles se concibe como un componente clave de la transformación universitaria, alineando prácticas y decisiones con impacto, calidad, equidad y adaptación tecnológica.\n\nVariantes:\n- ¿Qué caracteriza carreras flexibles en la universidad del futuro?\n- ¿Puedes explicar Qué caracteriza carreras flexibles en la universidad del futuro?\n- ¿En qué consiste Qué caracteriza carreras flexibles en la universidad del futuro?\n- ¿Cómo se define Qué caracteriza carreras flexibles en la universidad del futuro?\n\n\nMeta:\n- Documento: universidades_futuro_QA_50\n- Tags: carreras-flexibles",
      "tags": [
        "carreras-flexibles"
      ],
      "meta": {
        "country": "",
        "timeframe": "",
        "section": "",
        "audience": "",
        "base": "universidades_futuro_QA_50"
      }
    },
    {
      "id": "universidades_futuro_QA_50__038",
      "title": "¿Qué caracteriza gobernanza robusta en la universidad del futuro?",
      "source": "universidades_futuro_QA_50",
      "text": "Q: ¿Qué caracteriza gobernanza robusta en la universidad del futuro?\n\nA: Gobernanza robusta se concibe como un componente clave de la transformación universitaria, alineando prácticas y decisiones con impacto, calidad, equidad y adaptación tecnológica.\n\nVariantes:\n- ¿Qué caracteriza gobernanza robusta en la universidad del futuro?\n- ¿Puedes explicar Qué caracteriza gobernanza robusta en la universidad del futuro?\n- ¿En qué consiste Qué caracteriza gobernanza robusta en la universidad del futuro?\n- ¿Cómo se define Qué caracteriza gobernanza robusta en la universidad del futuro?\n\n\nMeta:\n- Documento: universidades_futuro_QA_50\n- Tags: gobernanza-robusta",
      "tags": [
        "gobernanza-robusta"
      ],
      "meta": {
        "country": "",
        "timeframe": "",
        "section": "",
        "audience": "",
        "base": "universidades_futuro_QA_50"
      }
    },
    {
      "id": "universidades_futuro_QA_50__039",
      "title": "¿Qué caracteriza valor público en la universidad del futuro?",
      "source": "universidades_futuro_QA_50",
      "text": "Q: ¿Qué caracteriza valor público en la universidad del futuro?\n\nA: Valor público se concibe como un componente clave de la transformación universitaria, alineando prácticas y decisiones con impacto, calidad, equidad y adaptación tecnológica.\n\nVariantes:\n- ¿Qué caracteriza valor público en la universidad del futuro?\n- ¿Puedes explicar Qué caracteriza valor público en la universidad del futuro?\n- ¿En qué consiste Qué caracteriza valor público en la universidad del futuro?\n- ¿Cómo se define Qué caracteriza valor público en la universidad del futuro?\n\n\nMeta:\n- Documento: universidades_futuro_QA_50\n- Tags: valor-público",
      "tags": [
        "valor-público"
      ],
      "meta": {
        "country": "",
        "timeframe": "",
        "section": "",
        "audience": "",
        "base": "universidades_futuro_QA_50"
      }
    },
    {
      "id": "universidades_futuro_QA_50__040",
      "title": "¿Qué caracteriza acceso universal en la universidad del futuro?",
      "source": "universidades_futuro_QA_50",
      "text": "Q: ¿Qué caracteriza acceso universal en la universidad del futuro?\n\nA: Acceso universal se concibe como un componente clave de la transformación universitaria, alineando prácticas y decisiones con impacto, calidad, equidad y adaptación tecnológica.\n\nVariantes:\n- ¿Qué caracteriza acceso universal en la universidad del futuro?\n- ¿Puedes explicar Qué caracteriza acceso universal en la universidad del futuro?\n- ¿En qué consiste Qué caracteriza acceso universal en la universidad del futuro?\n- ¿Cómo se define Qué caracteriza acceso universal en la universidad del futuro?\n\n\nMeta:\n- Documento: universidades_futuro_QA_50\n- Tags: acceso-universal",
      "tags": [
        "acceso-universal"
      ],
      "meta": {
        "country": "",
        "timeframe": "",
        "section": "",
        "audience": "",
        "base": "universidades_futuro_QA_50"
      }
    },
    {
      "id": "universidades_futuro_QA_50__041",
      "title": "¿Qué caracteriza ecualización de formatos en la universidad del futuro?",
      "source": "universidades_futuro_QA_50",
      "text": "Q: ¿Qué caracteriza ecualización de formatos en la universidad del futuro?\n\nA: Ecualización de formatos se concibe como un componente clave de la transformación universitaria, alineando prácticas y decisiones con impacto, calidad, equidad y adaptación tecnológica.\n\nVariantes:\n- ¿Qué caracteriza ecualización de formatos en la universidad del futuro?\n- ¿Puedes explicar Qué caracteriza ecualización de formatos en la universidad del futuro?\n- ¿En qué consiste Qué caracteriza ecualización de formatos en la universidad del futuro?\n- ¿Cómo se define Qué caracteriza ecualización de formatos en la universidad del futuro?\n\n\nMeta:\n- Documento: universidades_futuro_QA_50\n- Tags: ecualización-de-formatos",
      "tags": [
        "ecualización-de-formatos"
      ],
      "meta": {
        "country": "",
        "timeframe": "",
        "section": "",
        "audience": "",
        "base": "universidades_futuro_QA_50"
      }
    },
    {
      "id": "universidades_futuro_QA_50__042",
      "title": "¿Qué caracteriza financiamiento en la universidad del futuro?",
      "source": "universidades_futuro_QA_50",
      "text": "Q: ¿Qué caracteriza financiamiento en la universidad del futuro?\n\nA: Financiamiento se concibe como un componente clave de la transformación universitaria, alineando prácticas y decisiones con impacto, calidad, equidad y adaptación tecnológica.\n\nVariantes:\n- ¿Qué caracteriza financiamiento en la universidad del futuro?\n- ¿Puedes explicar Qué caracteriza financiamiento en la universidad del futuro?\n- ¿En qué consiste Qué caracteriza financiamiento en la universidad del futuro?\n- ¿Cómo se define Qué caracteriza financiamiento en la universidad del futuro?\n\n\nMeta:\n- Documento: universidades_futuro_QA_50\n- Tags: financiamiento",
      "tags": [
        "financiamiento"
      ],
      "meta": {
        "country": "",
        "timeframe": "",
        "section": "",
        "audience": "",
        "base": "universidades_futuro_QA_50"
      }
    },
    {
      "id": "universidades_futuro_QA_50__043",
      "title": "¿Qué caracteriza carrera académica en la universidad del futuro?",
      "source": "universidades_futuro_QA_50",
      "text": "Q: ¿Qué caracteriza carrera académica en la universidad del futuro?\n\nA: Carrera académica se concibe como un componente clave de la transformación universitaria, alineando prácticas y decisiones con impacto, calidad, equidad y adaptación tecnológica.\n\nVariantes:\n- ¿Qué caracteriza carrera académica en la universidad del futuro?\n- ¿Puedes explicar Qué caracteriza carrera académica en la universidad del futuro?\n- ¿En qué consiste Qué caracteriza carrera académica en la universidad del futuro?\n- ¿Cómo se define Qué caracteriza carrera académica en la universidad del futuro?\n\n\nMeta:\n- Documento: universidades_futuro_QA_50\n- Tags: carrera-académica",
      "tags": [
        "carrera-académica"
      ],
      "meta": {
        "country": "",
        "timeframe": "",
        "section": "",
        "audience": "",
        "base": "universidades_futuro_QA_50"
      }
    },
    {
      "id": "universidades_futuro_QA_50__044",
      "title": "¿Qué caracteriza vinculación territorial en la universidad del futuro?",
      "source": "universidades_futuro_QA_50",
      "text": "Q: ¿Qué caracteriza vinculación territorial en la universidad del futuro?\n\nA: Vinculación territorial se concibe como un componente clave de la transformación universitaria, alineando prácticas y decisiones con impacto, calidad, equidad y adaptación tecnológica.\n\nVariantes:\n- ¿Qué caracteriza vinculación territorial en la universidad del futuro?\n- ¿Puedes explicar Qué caracteriza vinculación territorial en la universidad del futuro?\n- ¿En qué consiste Qué caracteriza vinculación territorial en la universidad del futuro?\n- ¿Cómo se define Qué caracteriza vinculación territorial en la universidad del futuro?\n\n\nMeta:\n- Documento: universidades_futuro_QA_50\n- Tags: vinculación-territorial",
      "tags": [
        "vinculación-territorial"
      ],
      "meta": {
        "country": "",
        "timeframe": "",
        "section": "",
        "audience": "",
        "base": "universidades_futuro_QA_50"
      }
    },
    {
      "id": "universidades_futuro_QA_50__045",
      "title": "¿Qué caracteriza sistemas de información en la universidad del futuro?",
      "source": "universidades_futuro_QA_50",
      "text": "Q: ¿Qué caracteriza sistemas de información en la universidad del futuro?\n\nA: Sistemas de información se concibe como un componente clave de la transformación universitaria, alineando prácticas y decisiones con impacto, calidad, equidad y adaptación tecnológica.\n\nVariantes:\n- ¿Qué caracteriza sistemas de información en la universidad del futuro?\n- ¿Puedes explicar Qué caracteriza sistemas de información en la universidad del futuro?\n- ¿En qué consiste Qué caracteriza sistemas de información en la universidad del futuro?\n- ¿Cómo se define Qué caracteriza sistemas de información en la universidad del futuro?\n\n\nMeta:\n- Documento: universidades_futuro_QA_50\n- Tags: sistemas-de-información",
      "tags": [
        "sistemas-de-información"
      ],
      "meta": {
        "country": "",
        "timeframe": "",
        "section": "",
        "audience": "",
        "base": "universidades_futuro_QA_50"
      }
    },
    {
      "id": "universidades_futuro_QA_50__046",
      "title": "¿Qué caracteriza andragogía en la universidad del futuro?",
      "source": "universidades_futuro_QA_50",
      "text": "Q: ¿Qué caracteriza andragogía en la universidad del futuro?\n\nA: Andragogía se concibe como un componente clave de la transformación universitaria, alineando prácticas y decisiones con impacto, calidad, equidad y adaptación tecnológica.\n\nVariantes:\n- ¿Qué caracteriza andragogía en la universidad del futuro?\n- ¿Puedes explicar Qué caracteriza andragogía en la universidad del futuro?\n- ¿En qué consiste Qué caracteriza andragogía en la universidad del futuro?\n- ¿Cómo se define Qué caracteriza andragogía en la universidad del futuro?\n\n\nMeta:\n- Documento: universidades_futuro_QA_50\n- Tags: andragogía",
      "tags": [
        "andragogía"
      ],
      "meta": {
        "country": "",
        "timeframe": "",
        "section": "",
        "audience": "",
        "base": "universidades_futuro_QA_50"
      }
    },
    {
      "id": "universidades_futuro_QA_50__047",
      "title": "¿Qué caracteriza revolución digital en la universidad del futuro?",
      "source": "universidades_futuro_QA_50",
      "text": "Q: ¿Qué caracteriza revolución digital en la universidad del futuro?\n\nA: Revolución digital se concibe como un componente clave de la transformación universitaria, alineando prácticas y decisiones con impacto, calidad, equidad y adaptación tecnológica.\n\nVariantes:\n- ¿Qué caracteriza revolución digital en la universidad del futuro?\n- ¿Puedes explicar Qué caracteriza revolución digital en la universidad del futuro?\n- ¿En qué consiste Qué caracteriza revolución digital en la universidad del futuro?\n- ¿Cómo se define Qué caracteriza revolución digital en la universidad del futuro?\n\n\nMeta:\n- Documento: universidades_futuro_QA_50\n- Tags: revolución-digital",
      "tags": [
        "revolución-digital"
      ],
      "meta": {
        "country": "",
        "timeframe": "",
        "section": "",
        "audience": "",
        "base": "universidades_futuro_QA_50"
      }
    },
    {
      "id": "universidades_futuro_QA_50__048",
      "title": "¿Qué caracteriza competencias digitales en la universidad del futuro?",
      "source": "universidades_futuro_QA_50",
      "text": "Q: ¿Qué caracteriza competencias digitales en la universidad del futuro?\n\nA: Competencias digitales se concibe como un componente clave de la transformación universitaria, alineando prácticas y decisiones con impacto, calidad, equidad y adaptación tecnológica.\n\nVariantes:\n- ¿Qué caracteriza competencias digitales en la universidad del futuro?\n- ¿Puedes explicar Qué caracteriza competencias digitales en la universidad del futuro?\n- ¿En qué consiste Qué caracteriza competencias digitales en la universidad del futuro?\n- ¿Cómo se define Qué caracteriza competencias digitales en la universidad del futuro?\n\n\nMeta:\n- Documento: universidades_futuro_QA_50\n- Tags: competencias-digitales",
      "tags": [
        "competencias-digitales"
      ],
      "meta": {
        "country": "",
        "timeframe": "",
        "section": "",
        "audience": "",
        "base": "universidades_futuro_QA_50"
      }
    },
    {
      "id": "universidades_futuro_QA_50__049",
      "title": "¿Qué caracteriza gobernanza flexible en la universidad del futuro?",
      "source": "universidades_futuro_QA_50",
      "text": "Q: ¿Qué caracteriza gobernanza flexible en la universidad del futuro?\n\nA: Gobernanza flexible se concibe como un componente clave de la transformación universitaria, alineando prácticas y decisiones con impacto, calidad, equidad y adaptación tecnológica.\n\nVariantes:\n- ¿Qué caracteriza gobernanza flexible en la universidad del futuro?\n- ¿Puedes explicar Qué caracteriza gobernanza flexible en la universidad del futuro?\n- ¿En qué consiste Qué caracteriza gobernanza flexible en la universidad del futuro?\n- ¿Cómo se define Qué caracteriza gobernanza flexible en la universidad del futuro?\n\n\nMeta:\n- Documento: universidades_futuro_QA_50\n- Tags: gobernanza-flexible",
      "tags": [
        "gobernanza-flexible"
      ],
      "meta": {
        "country": "",
        "timeframe": "",
        "section": "",
        "audience": "",
        "base": "universidades_futuro_QA_50"
      }
    },
    {
      "id": "universidades_futuro_QA_50__050",
      "title": "¿Qué caracteriza sostenibilidad ambiental en la universidad del futuro?",
      "source": "universidades_futuro_QA_50",
      "text": "Q: ¿Qué caracteriza sostenibilidad ambiental en la universidad del futuro?\n\nA: Sostenibilidad ambiental se concibe como un componente clave de la transformación universitaria, alineando prácticas y decisiones con impacto, calidad, equidad y adaptación tecnológica.\n\nVariantes:\n- ¿Qué caracteriza sostenibilidad ambiental en la universidad del futuro?\n- ¿Puedes explicar Qué caracteriza sostenibilidad ambiental en la universidad del futuro?\n- ¿En qué consiste Qué caracteriza sostenibilidad ambiental en la universidad del futuro?\n- ¿Cómo se define Qué caracteriza sostenibilidad ambiental en la universidad del futuro?\n\n\nMeta:\n- Documento: universidades_futuro_QA_50\n- Tags: sostenibilidad-ambiental",
      "tags": [
        "sostenibilidad-ambiental"
      ],
      "meta": {
        "country": "",
        "timeframe": "",
        "section": "",
        "audience": "",
        "base": "universidades_futuro_QA_50"
      }
    },
    {
      "id": "autores_vs_objetivos_QA_50_enriquecido__001",
      "title": "¿Cómo conversa el enfoque de Universidad por capas con los objetivos estratégicos de UDALBA?",
      "source": "Autores vs Objetivos.pdf",
      "text": "Q: ¿Cómo conversa el enfoque de Universidad por capas con los objetivos estratégicos de UDALBA?\n\nA: Universidad por capas propone: Modelo flexible con núcleo en transformación, campus diferenciado que integra entornos físicos, digitales y mixtos; combina elementos fijos, fluidos y flexibles. Esto se alinea con objetivos como 1, 2, 6, 7, 8, 10, 13, 14, 15, 17, 19, fortaleciendo capacidades institucionales, calidad educativa, transformación digital y pertinencia territorial.\n\nVariantes:\n- ¿De qué manera Universidad por capas se alinea con las metas institucionales?\n- ¿Qué aporta Universidad por capas a la hoja de ruta 2025–2045 de UDALBA?\n- Explica la relación entre Universidad por capas y los objetivos priorizados\n\n\nMeta:\n- País: Chile\n- Periodo: 2025–2045\n- Sección: p.2–3\n- Audiencia: IES,policymakers,docentes\n- Documento: Autores vs Objetivos.pdf\n- Tags: universidad-por-capas, relación-objetivos",
      "tags": [
        "universidad-por-capas",
        "relación-objetivos"
      ],
      "meta": {
        "country": "Chile",
        "timeframe": "2025–2045",
        "section": "p.2–3",
        "audience": "IES,policymakers,docentes",
        "base": "autores_vs_objetivos_QA_50_enriquecido"
      }
    },
    {
      "id": "autores_vs_objetivos_QA_50_enriquecido__002",
      "title": "¿Cómo Universidad por capas respalda el objetivo 1 de UDALBA?",
      "source": "Autores vs Objetivos.pdf",
      "text": "Q: ¿Cómo Universidad por capas respalda el objetivo 1 de UDALBA?\n\nA: El enfoque de Universidad por capas entrega una justificación conceptual y operativa para el objetivo 1, conectando políticas, procesos y capacidades con resultados esperados en ese ámbito, según la tabla comparativa (p.2–3).\n\nVariantes:\n- ¿Qué evidencia del documento vincula Universidad por capas con el objetivo 1?\n- Describe el aporte de Universidad por capas al objetivo 1\n- ¿Por qué Universidad por capas es coherente con el objetivo 1?\n\n\nMeta:\n- País: Chile\n- Periodo: 2025–2045\n- Sección: p.2–3\n- Audiencia: IES,policymakers\n- Documento: Autores vs Objetivos.pdf\n- Tags: universidad-por-capas, objetivo-1",
      "tags": [
        "universidad-por-capas",
        "objetivo-1"
      ],
      "meta": {
        "country": "Chile",
        "timeframe": "2025–2045",
        "section": "p.2–3",
        "audience": "IES,policymakers",
        "base": "autores_vs_objetivos_QA_50_enriquecido"
      }
    },
    {
      "id": "autores_vs_objetivos_QA_50_enriquecido__003",
      "title": "¿Qué acciones concretas permitirían operativizar Universidad por capas en UDALBA?",
      "source": "Autores vs Objetivos.pdf",
      "text": "Q: ¿Qué acciones concretas permitirían operativizar Universidad por capas en UDALBA?\n\nA: Acciones: diseñar pilotos y escalamiento, ajustar mallas y credenciales, reforzar plataformas y datos, formar talento (docente/gestión), y vincular con territorios y empleo. Indicadores: progresión, titulación oportuna, satisfacción, empleabilidad, impacto territorial y métricas de uso digital.\n\nVariantes:\n- Propón medidas para implementar Universidad por capas en programas y campus\n- ¿Qué indicadores usar para seguir la implementación de Universidad por capas?\n- ¿Cómo integrar Universidad por capas en gobernanza y evaluación?\n\n\nMeta:\n- País: Chile\n- Periodo: 2025–2045\n- Sección: p.2–3\n- Audiencia: IES,escuelas\n- Documento: Autores vs Objetivos.pdf\n- Tags: universidad-por-capas, implementación",
      "tags": [
        "universidad-por-capas",
        "implementación"
      ],
      "meta": {
        "country": "Chile",
        "timeframe": "2025–2045",
        "section": "p.2–3",
        "audience": "IES,escuelas",
        "base": "autores_vs_objetivos_QA_50_enriquecido"
      }
    },
    {
      "id": "autores_vs_objetivos_QA_50_enriquecido__004",
      "title": "¿En qué se diferencia Universidad por capas de Universidad híbrida y expandida respecto a hibridez y transformación digital?",
      "source": "Autores vs Objetivos.pdf",
      "text": "Q: ¿En qué se diferencia Universidad por capas de Universidad híbrida y expandida respecto a hibridez y transformación digital?\n\nA: Universidad por capas enfatiza modelo flexible con núcleo en transformación, campus diferenciado que integra entornos físicos, digitales y mixtos mientras Universidad híbrida y expandida pone foco en gobernanza basada en datos y expansión operativa del campus físico–virtual (según sus apartados respectivos). Ambos convergen en transformación digital, pero difieren en el punto de partida y prioridades de implementación.\n\nVariantes:\n- Compara Universidad por capas y Universidad híbrida y expandida en campus físico–virtual y datos\n- ¿Qué enfoque es más adecuado para trayectorias flexibles en UDALBA?\n- ¿Cómo varían sus implicancias en gobernanza y talento humano?\n\n\nMeta:\n- País: Chile\n- Periodo: 2025–2045\n- Sección: p.2–3\n- Audiencia: IES,policymakers,docentes\n- Documento: Autores vs Objetivos.pdf\n- Tags: universidad-por-capas, universidad-híbrida-y-expandida, comparativa",
      "tags": [
        "universidad-por-capas",
        "universidad-híbrida-y-expandida",
        "comparativa"
      ],
      "meta": {
        "country": "Chile",
        "timeframe": "2025–2045",
        "section": "p.2–3",
        "audience": "IES,policymakers,docentes",
        "base": "autores_vs_objetivos_QA_50_enriquecido"
      }
    },
    {
      "id": "autores_vs_objetivos_QA_50_enriquecido__005",
      "title": "¿Qué riesgos y mitigaciones se deben considerar al adoptar Universidad por capas en UDALBA?",
      "source": "Autores vs Objetivos.pdf",
      "text": "Q: ¿Qué riesgos y mitigaciones se deben considerar al adoptar Universidad por capas en UDALBA?\n\nA: Riesgos: sesgos y privacidad de datos, inequidades de acceso digital, sobrecarga de cambio organizacional. Mitigaciones: marcos éticos, gobernanza de datos, inversión en conectividad y soporte, formación continua, participación de comunidades y pilotaje con evaluación de impacto.\n\nVariantes:\n- ¿Qué salvaguardas éticas y de datos acompañan Universidad por capas?\n- ¿Cómo evitar brechas y resistencias en la implementación de Universidad por capas?\n- ¿Qué prácticas de gestión del cambio requiere Universidad por capas?\n\n\nMeta:\n- País: Chile\n- Periodo: 2025–2045\n- Sección: p.2–3\n- Audiencia: IES,policymakers\n- Documento: Autores vs Objetivos.pdf\n- Tags: universidad-por-capas, riesgos, mitigaciones",
      "tags": [
        "universidad-por-capas",
        "riesgos",
        "mitigaciones"
      ],
      "meta": {
        "country": "Chile",
        "timeframe": "2025–2045",
        "section": "p.2–3",
        "audience": "IES,policymakers",
        "base": "autores_vs_objetivos_QA_50_enriquecido"
      }
    },
    {
      "id": "autores_vs_objetivos_QA_50_enriquecido__006",
      "title": "¿Cómo conversa el enfoque de Universidad híbrida y expandida con los objetivos estratégicos de UDALBA?",
      "source": "Autores vs Objetivos.pdf",
      "text": "Q: ¿Cómo conversa el enfoque de Universidad híbrida y expandida con los objetivos estratégicos de UDALBA?\n\nA: Universidad híbrida y expandida propone: Integración intencional de campus físico y virtual, gobernanza emprendedora basada en datos, diversificación de ingresos y rol docente como diseñador de experiencias. Esto se alinea con objetivos como 1, 4, 5, 6, 7, 8, 10, 11, 13, 15, 17, 19, fortaleciendo capacidades institucionales, calidad educativa, transformación digital y pertinencia territorial.\n\nVariantes:\n- ¿De qué manera Universidad híbrida y expandida se alinea con las metas institucionales?\n- ¿Qué aporta Universidad híbrida y expandida a la hoja de ruta 2025–2045 de UDALBA?\n- Explica la relación entre Universidad híbrida y expandida y los objetivos priorizados\n\n\nMeta:\n- País: Chile\n- Periodo: 2025–2045\n- Sección: p.3–4\n- Audiencia: IES,policymakers,docentes\n- Documento: Autores vs Objetivos.pdf\n- Tags: universidad-híbrida-y-expandida, relación-objetivos",
      "tags": [
        "universidad-híbrida-y-expandida",
        "relación-objetivos"
      ],
      "meta": {
        "country": "Chile",
        "timeframe": "2025–2045",
        "section": "p.3–4",
        "audience": "IES,policymakers,docentes",
        "base": "autores_vs_objetivos_QA_50_enriquecido"
      }
    },
    {
      "id": "autores_vs_objetivos_QA_50_enriquecido__007",
      "title": "¿Cómo Universidad híbrida y expandida respalda el objetivo 1 de UDALBA?",
      "source": "Autores vs Objetivos.pdf",
      "text": "Q: ¿Cómo Universidad híbrida y expandida respalda el objetivo 1 de UDALBA?\n\nA: El enfoque de Universidad híbrida y expandida entrega una justificación conceptual y operativa para el objetivo 1, conectando políticas, procesos y capacidades con resultados esperados en ese ámbito, según la tabla comparativa (p.3–4).\n\nVariantes:\n- ¿Qué evidencia del documento vincula Universidad híbrida y expandida con el objetivo 1?\n- Describe el aporte de Universidad híbrida y expandida al objetivo 1\n- ¿Por qué Universidad híbrida y expandida es coherente con el objetivo 1?\n\n\nMeta:\n- País: Chile\n- Periodo: 2025–2045\n- Sección: p.3–4\n- Audiencia: IES,policymakers\n- Documento: Autores vs Objetivos.pdf\n- Tags: universidad-híbrida-y-expandida, objetivo-1",
      "tags": [
        "universidad-híbrida-y-expandida",
        "objetivo-1"
      ],
      "meta": {
        "country": "Chile",
        "timeframe": "2025–2045",
        "section": "p.3–4",
        "audience": "IES,policymakers",
        "base": "autores_vs_objetivos_QA_50_enriquecido"
      }
    },
    {
      "id": "autores_vs_objetivos_QA_50_enriquecido__008",
      "title": "¿Qué acciones concretas permitirían operativizar Universidad híbrida y expandida en UDALBA?",
      "source": "Autores vs Objetivos.pdf",
      "text": "Q: ¿Qué acciones concretas permitirían operativizar Universidad híbrida y expandida en UDALBA?\n\nA: Acciones: diseñar pilotos y escalamiento, ajustar mallas y credenciales, reforzar plataformas y datos, formar talento (docente/gestión), y vincular con territorios y empleo. Indicadores: progresión, titulación oportuna, satisfacción, empleabilidad, impacto territorial y métricas de uso digital.\n\nVariantes:\n- Propón medidas para implementar Universidad híbrida y expandida en programas y campus\n- ¿Qué indicadores usar para seguir la implementación de Universidad híbrida y expandida?\n- ¿Cómo integrar Universidad híbrida y expandida en gobernanza y evaluación?\n\n\nMeta:\n- País: Chile\n- Periodo: 2025–2045\n- Sección: p.3–4\n- Audiencia: IES,escuelas\n- Documento: Autores vs Objetivos.pdf\n- Tags: universidad-híbrida-y-expandida, implementación",
      "tags": [
        "universidad-híbrida-y-expandida",
        "implementación"
      ],
      "meta": {
        "country": "Chile",
        "timeframe": "2025–2045",
        "section": "p.3–4",
        "audience": "IES,escuelas",
        "base": "autores_vs_objetivos_QA_50_enriquecido"
      }
    },
    {
      "id": "autores_vs_objetivos_QA_50_enriquecido__009",
      "title": "¿En qué se diferencia Universidad híbrida y expandida de TIC e IA para mejorar enseñanza y evaluación respecto a hibridez y transformación d",
      "source": "Autores vs Objetivos.pdf",
      "text": "Q: ¿En qué se diferencia Universidad híbrida y expandida de TIC e IA para mejorar enseñanza y evaluación respecto a hibridez y transformación digital?\n\nA: Universidad híbrida y expandida enfatiza integración intencional de campus físico y virtual, gobernanza emprendedora basada en datos, diversificación de ingresos y rol docente como diseñador de experiencias. mientras TIC e IA para mejorar enseñanza y evaluación pone foco en gobernanza basada en datos y expansión operativa del campus físico–virtual (según sus apartados respectivos). Ambos convergen en transformación digital, pero difieren en el punto de partida y prioridades de implementación.\n\nVariantes:\n- Compara Universidad híbrida y expandida y TIC e IA para mejorar enseñanza y evaluación en campus físico–virtual y datos\n- ¿Qué enfoque es más adecuado para trayectorias flexibles en UDALBA?\n- ¿Cómo varían sus implicancias en gobernanza y talento humano?\n\n\nMeta:\n- País: Chile\n- Periodo: 2025–2045\n- Sección: p.3–4\n- Audiencia: IES,policymakers,docentes\n- Documento: Autores vs Objetivos.pdf\n- Tags: universidad-híbrida-y-expandida, tic-e-ia-para-mejorar-enseñanza-y-evaluación, comparativa",
      "tags": [
        "universidad-híbrida-y-expandida",
        "tic-e-ia-para-mejorar-enseñanza-y-evaluación",
        "comparativa"
      ],
      "meta": {
        "country": "Chile",
        "timeframe": "2025–2045",
        "section": "p.3–4",
        "audience": "IES,policymakers,docentes",
        "base": "autores_vs_objetivos_QA_50_enriquecido"
      }
    },
    {
      "id": "autores_vs_objetivos_QA_50_enriquecido__010",
      "title": "¿Qué riesgos y mitigaciones se deben considerar al adoptar Universidad híbrida y expandida en UDALBA?",
      "source": "Autores vs Objetivos.pdf",
      "text": "Q: ¿Qué riesgos y mitigaciones se deben considerar al adoptar Universidad híbrida y expandida en UDALBA?\n\nA: Riesgos: sesgos y privacidad de datos, inequidades de acceso digital, sobrecarga de cambio organizacional. Mitigaciones: marcos éticos, gobernanza de datos, inversión en conectividad y soporte, formación continua, participación de comunidades y pilotaje con evaluación de impacto.\n\nVariantes:\n- ¿Qué salvaguardas éticas y de datos acompañan Universidad híbrida y expandida?\n- ¿Cómo evitar brechas y resistencias en la implementación de Universidad híbrida y expandida?\n- ¿Qué prácticas de gestión del cambio requiere Universidad híbrida y expandida?\n\n\nMeta:\n- País: Chile\n- Periodo: 2025–2045\n- Sección: p.3–4\n- Audiencia: IES,policymakers\n- Documento: Autores vs Objetivos.pdf\n- Tags: universidad-híbrida-y-expandida, riesgos, mitigaciones",
      "tags": [
        "universidad-híbrida-y-expandida",
        "riesgos",
        "mitigaciones"
      ],
      "meta": {
        "country": "Chile",
        "timeframe": "2025–2045",
        "section": "p.3–4",
        "audience": "IES,policymakers",
        "base": "autores_vs_objetivos_QA_50_enriquecido"
      }
    },
    {
      "id": "autores_vs_objetivos_QA_50_enriquecido__011",
      "title": "¿Cómo conversa el enfoque de TIC e IA para mejorar enseñanza y evaluación con los objetivos estratégicos de UDALBA?",
      "source": "Autores vs Objetivos.pdf",
      "text": "Q: ¿Cómo conversa el enfoque de TIC e IA para mejorar enseñanza y evaluación con los objetivos estratégicos de UDALBA?\n\nA: TIC e IA para mejorar enseñanza y evaluación propone: Personalización del aprendizaje con retroalimentación en tiempo real, evaluación continua y automatizada, desarrollo de capacidades digitales docentes y ética de datos. Esto se alinea con objetivos como 2, 4, 6, 7, 8, 9, 10, 13, 16, 17, fortaleciendo capacidades institucionales, calidad educativa, transformación digital y pertinencia territorial.\n\nVariantes:\n- ¿De qué manera TIC e IA para mejorar enseñanza y evaluación se alinea con las metas institucionales?\n- ¿Qué aporta TIC e IA para mejorar enseñanza y evaluación a la hoja de ruta 2025–2045 de UDALBA?\n- Explica la relación entre TIC e IA para mejorar enseñanza y evaluación y los objetivos priorizados\n\n\nMeta:\n- País: Chile\n- Periodo: 2025–2045\n- Sección: p.4–5\n- Audiencia: IES,policymakers,docentes\n- Documento: Autores vs Objetivos.pdf\n- Tags: tic-e-ia-para-mejorar-enseñanza-y-evaluación, relación-objetivos",
      "tags": [
        "tic-e-ia-para-mejorar-enseñanza-y-evaluación",
        "relación-objetivos"
      ],
      "meta": {
        "country": "Chile",
        "timeframe": "2025–2045",
        "section": "p.4–5",
        "audience": "IES,policymakers,docentes",
        "base": "autores_vs_objetivos_QA_50_enriquecido"
      }
    },
    {
      "id": "autores_vs_objetivos_QA_50_enriquecido__012",
      "title": "¿Cómo TIC e IA para mejorar enseñanza y evaluación respalda el objetivo 2 de UDALBA?",
      "source": "Autores vs Objetivos.pdf",
      "text": "Q: ¿Cómo TIC e IA para mejorar enseñanza y evaluación respalda el objetivo 2 de UDALBA?\n\nA: El enfoque de TIC e IA para mejorar enseñanza y evaluación entrega una justificación conceptual y operativa para el objetivo 2, conectando políticas, procesos y capacidades con resultados esperados en ese ámbito, según la tabla comparativa (p.4–5).\n\nVariantes:\n- ¿Qué evidencia del documento vincula TIC e IA para mejorar enseñanza y evaluación con el objetivo 2?\n- Describe el aporte de TIC e IA para mejorar enseñanza y evaluación al objetivo 2\n- ¿Por qué TIC e IA para mejorar enseñanza y evaluación es coherente con el objetivo 2?\n\n\nMeta:\n- País: Chile\n- Periodo: 2025–2045\n- Sección: p.4–5\n- Audiencia: IES,policymakers\n- Documento: Autores vs Objetivos.pdf\n- Tags: tic-e-ia-para-mejorar-enseñanza-y-evaluación, objetivo-2",
      "tags": [
        "tic-e-ia-para-mejorar-enseñanza-y-evaluación",
        "objetivo-2"
      ],
      "meta": {
        "country": "Chile",
        "timeframe": "2025–2045",
        "section": "p.4–5",
        "audience": "IES,policymakers",
        "base": "autores_vs_objetivos_QA_50_enriquecido"
      }
    },
    {
      "id": "autores_vs_objetivos_QA_50_enriquecido__013",
      "title": "¿Qué acciones concretas permitirían operativizar TIC e IA para mejorar enseñanza y evaluación en UDALBA?",
      "source": "Autores vs Objetivos.pdf",
      "text": "Q: ¿Qué acciones concretas permitirían operativizar TIC e IA para mejorar enseñanza y evaluación en UDALBA?\n\nA: Acciones: diseñar pilotos y escalamiento, ajustar mallas y credenciales, reforzar plataformas y datos, formar talento (docente/gestión), y vincular con territorios y empleo. Indicadores: progresión, titulación oportuna, satisfacción, empleabilidad, impacto territorial y métricas de uso digital.\n\nVariantes:\n- Propón medidas para implementar TIC e IA para mejorar enseñanza y evaluación en programas y campus\n- ¿Qué indicadores usar para seguir la implementación de TIC e IA para mejorar enseñanza y evaluación?\n- ¿Cómo integrar TIC e IA para mejorar enseñanza y evaluación en gobernanza y evaluación?\n\n\nMeta:\n- País: Chile\n- Periodo: 2025–2045\n- Sección: p.4–5\n- Audiencia: IES,escuelas\n- Documento: Autores vs Objetivos.pdf\n- Tags: tic-e-ia-para-mejorar-enseñanza-y-evaluación, implementación",
      "tags": [
        "tic-e-ia-para-mejorar-enseñanza-y-evaluación",
        "implementación"
      ],
      "meta": {
        "country": "Chile",
        "timeframe": "2025–2045",
        "section": "p.4–5",
        "audience": "IES,escuelas",
        "base": "autores_vs_objetivos_QA_50_enriquecido"
      }
    },
    {
      "id": "autores_vs_objetivos_QA_50_enriquecido__014",
      "title": "¿En qué se diferencia TIC e IA para mejorar enseñanza y evaluación de Universidad ubicua respecto a hibridez y transformación digital?",
      "source": "Autores vs Objetivos.pdf",
      "text": "Q: ¿En qué se diferencia TIC e IA para mejorar enseñanza y evaluación de Universidad ubicua respecto a hibridez y transformación digital?\n\nA: TIC e IA para mejorar enseñanza y evaluación enfatiza personalización del aprendizaje con retroalimentación en tiempo real, evaluación continua y automatizada, desarrollo de capacidades digitales docentes y ética de datos. mientras Universidad ubicua pone foco en gobernanza basada en datos y expansión operativa del campus físico–virtual (según sus apartados respectivos). Ambos convergen en transformación digital, pero difieren en el punto de partida y prioridades de implementación.\n\nVariantes:\n- Compara TIC e IA para mejorar enseñanza y evaluación y Universidad ubicua en campus físico–virtual y datos\n- ¿Qué enfoque es más adecuado para trayectorias flexibles en UDALBA?\n- ¿Cómo varían sus implicancias en gobernanza y talento humano?\n\n\nMeta:\n- País: Chile\n- Periodo: 2025–2045\n- Sección: p.4–5\n- Audiencia: IES,policymakers,docentes\n- Documento: Autores vs Objetivos.pdf\n- Tags: tic-e-ia-para-mejorar-enseñanza-y-evaluación, universidad-ubicua, comparativa",
      "tags": [
        "tic-e-ia-para-mejorar-enseñanza-y-evaluación",
        "universidad-ubicua",
        "comparativa"
      ],
      "meta": {
        "country": "Chile",
        "timeframe": "2025–2045",
        "section": "p.4–5",
        "audience": "IES,policymakers,docentes",
        "base": "autores_vs_objetivos_QA_50_enriquecido"
      }
    },
    {
      "id": "autores_vs_objetivos_QA_50_enriquecido__015",
      "title": "¿Qué riesgos y mitigaciones se deben considerar al adoptar TIC e IA para mejorar enseñanza y evaluación en UDALBA?",
      "source": "Autores vs Objetivos.pdf",
      "text": "Q: ¿Qué riesgos y mitigaciones se deben considerar al adoptar TIC e IA para mejorar enseñanza y evaluación en UDALBA?\n\nA: Riesgos: sesgos y privacidad de datos, inequidades de acceso digital, sobrecarga de cambio organizacional. Mitigaciones: marcos éticos, gobernanza de datos, inversión en conectividad y soporte, formación continua, participación de comunidades y pilotaje con evaluación de impacto.\n\nVariantes:\n- ¿Qué salvaguardas éticas y de datos acompañan TIC e IA para mejorar enseñanza y evaluación?\n- ¿Cómo evitar brechas y resistencias en la implementación de TIC e IA para mejorar enseñanza y evaluación?\n- ¿Qué prácticas de gestión del cambio requiere TIC e IA para mejorar enseñanza y evaluación?\n\n\nMeta:\n- País: Chile\n- Periodo: 2025–2045\n- Sección: p.4–5\n- Audiencia: IES,policymakers\n- Documento: Autores vs Objetivos.pdf\n- Tags: tic-e-ia-para-mejorar-enseñanza-y-evaluación, riesgos, mitigaciones",
      "tags": [
        "tic-e-ia-para-mejorar-enseñanza-y-evaluación",
        "riesgos",
        "mitigaciones"
      ],
      "meta": {
        "country": "Chile",
        "timeframe": "2025–2045",
        "section": "p.4–5",
        "audience": "IES,policymakers",
        "base": "autores_vs_objetivos_QA_50_enriquecido"
      }
    },
    {
      "id": "autores_vs_objetivos_QA_50_enriquecido__016",
      "title": "¿Cómo conversa el enfoque de Universidad ubicua con los objetivos estratégicos de UDALBA?",
      "source": "Autores vs Objetivos.pdf",
      "text": "Q: ¿Cómo conversa el enfoque de Universidad ubicua con los objetivos estratégicos de UDALBA?\n\nA: Universidad ubicua propone: Crítica a planificación lineal; universidad presente en todas partes articulando inteligencia social y artificial; de transmitir contenidos a explorar lo desconocido. Esto se alinea con objetivos como 1, 6, 7, 8, 10, 16, 17, 19, fortaleciendo capacidades institucionales, calidad educativa, transformación digital y pertinencia territorial.\n\nVariantes:\n- ¿De qué manera Universidad ubicua se alinea con las metas institucionales?\n- ¿Qué aporta Universidad ubicua a la hoja de ruta 2025–2045 de UDALBA?\n- Explica la relación entre Universidad ubicua y los objetivos priorizados\n\n\nMeta:\n- País: Chile\n- Periodo: 2025–2045\n- Sección: p.5\n- Audiencia: IES,policymakers,docentes\n- Documento: Autores vs Objetivos.pdf\n- Tags: universidad-ubicua, relación-objetivos",
      "tags": [
        "universidad-ubicua",
        "relación-objetivos"
      ],
      "meta": {
        "country": "Chile",
        "timeframe": "2025–2045",
        "section": "p.5",
        "audience": "IES,policymakers,docentes",
        "base": "autores_vs_objetivos_QA_50_enriquecido"
      }
    },
    {
      "id": "autores_vs_objetivos_QA_50_enriquecido__017",
      "title": "¿Cómo Universidad ubicua respalda el objetivo 1 de UDALBA?",
      "source": "Autores vs Objetivos.pdf",
      "text": "Q: ¿Cómo Universidad ubicua respalda el objetivo 1 de UDALBA?\n\nA: El enfoque de Universidad ubicua entrega una justificación conceptual y operativa para el objetivo 1, conectando políticas, procesos y capacidades con resultados esperados en ese ámbito, según la tabla comparativa (p.5).\n\nVariantes:\n- ¿Qué evidencia del documento vincula Universidad ubicua con el objetivo 1?\n- Describe el aporte de Universidad ubicua al objetivo 1\n- ¿Por qué Universidad ubicua es coherente con el objetivo 1?\n\n\nMeta:\n- País: Chile\n- Periodo: 2025–2045\n- Sección: p.5\n- Audiencia: IES,policymakers\n- Documento: Autores vs Objetivos.pdf\n- Tags: universidad-ubicua, objetivo-1",
      "tags": [
        "universidad-ubicua",
        "objetivo-1"
      ],
      "meta": {
        "country": "Chile",
        "timeframe": "2025–2045",
        "section": "p.5",
        "audience": "IES,policymakers",
        "base": "autores_vs_objetivos_QA_50_enriquecido"
      }
    },
    {
      "id": "autores_vs_objetivos_QA_50_enriquecido__018",
      "title": "¿Qué acciones concretas permitirían operativizar Universidad ubicua en UDALBA?",
      "source": "Autores vs Objetivos.pdf",
      "text": "Q: ¿Qué acciones concretas permitirían operativizar Universidad ubicua en UDALBA?\n\nA: Acciones: diseñar pilotos y escalamiento, ajustar mallas y credenciales, reforzar plataformas y datos, formar talento (docente/gestión), y vincular con territorios y empleo. Indicadores: progresión, titulación oportuna, satisfacción, empleabilidad, impacto territorial y métricas de uso digital.\n\nVariantes:\n- Propón medidas para implementar Universidad ubicua en programas y campus\n- ¿Qué indicadores usar para seguir la implementación de Universidad ubicua?\n- ¿Cómo integrar Universidad ubicua en gobernanza y evaluación?\n\n\nMeta:\n- País: Chile\n- Periodo: 2025–2045\n- Sección: p.5\n- Audiencia: IES,escuelas\n- Documento: Autores vs Objetivos.pdf\n- Tags: universidad-ubicua, implementación",
      "tags": [
        "universidad-ubicua",
        "implementación"
      ],
      "meta": {
        "country": "Chile",
        "timeframe": "2025–2045",
        "section": "p.5",
        "audience": "IES,escuelas",
        "base": "autores_vs_objetivos_QA_50_enriquecido"
      }
    },
    {
      "id": "autores_vs_objetivos_QA_50_enriquecido__019",
      "title": "¿En qué se diferencia Universidad ubicua de Gobernanza anticipatoria respecto a hibridez y transformación digital?",
      "source": "Autores vs Objetivos.pdf",
      "text": "Q: ¿En qué se diferencia Universidad ubicua de Gobernanza anticipatoria respecto a hibridez y transformación digital?\n\nA: Universidad ubicua enfatiza crítica a planificación lineal mientras Gobernanza anticipatoria pone foco en gobernanza basada en datos y expansión operativa del campus físico–virtual (según sus apartados respectivos). Ambos convergen en transformación digital, pero difieren en el punto de partida y prioridades de implementación.\n\nVariantes:\n- Compara Universidad ubicua y Gobernanza anticipatoria en campus físico–virtual y datos\n- ¿Qué enfoque es más adecuado para trayectorias flexibles en UDALBA?\n- ¿Cómo varían sus implicancias en gobernanza y talento humano?\n\n\nMeta:\n- País: Chile\n- Periodo: 2025–2045\n- Sección: p.5\n- Audiencia: IES,policymakers,docentes\n- Documento: Autores vs Objetivos.pdf\n- Tags: universidad-ubicua, gobernanza-anticipatoria, comparativa",
      "tags": [
        "universidad-ubicua",
        "gobernanza-anticipatoria",
        "comparativa"
      ],
      "meta": {
        "country": "Chile",
        "timeframe": "2025–2045",
        "section": "p.5",
        "audience": "IES,policymakers,docentes",
        "base": "autores_vs_objetivos_QA_50_enriquecido"
      }
    },
    {
      "id": "autores_vs_objetivos_QA_50_enriquecido__020",
      "title": "¿Qué riesgos y mitigaciones se deben considerar al adoptar Universidad ubicua en UDALBA?",
      "source": "Autores vs Objetivos.pdf",
      "text": "Q: ¿Qué riesgos y mitigaciones se deben considerar al adoptar Universidad ubicua en UDALBA?\n\nA: Riesgos: sesgos y privacidad de datos, inequidades de acceso digital, sobrecarga de cambio organizacional. Mitigaciones: marcos éticos, gobernanza de datos, inversión en conectividad y soporte, formación continua, participación de comunidades y pilotaje con evaluación de impacto.\n\nVariantes:\n- ¿Qué salvaguardas éticas y de datos acompañan Universidad ubicua?\n- ¿Cómo evitar brechas y resistencias en la implementación de Universidad ubicua?\n- ¿Qué prácticas de gestión del cambio requiere Universidad ubicua?\n\n\nMeta:\n- País: Chile\n- Periodo: 2025–2045\n- Sección: p.5\n- Audiencia: IES,policymakers\n- Documento: Autores vs Objetivos.pdf\n- Tags: universidad-ubicua, riesgos, mitigaciones",
      "tags": [
        "universidad-ubicua",
        "riesgos",
        "mitigaciones"
      ],
      "meta": {
        "country": "Chile",
        "timeframe": "2025–2045",
        "section": "p.5",
        "audience": "IES,policymakers",
        "base": "autores_vs_objetivos_QA_50_enriquecido"
      }
    },
    {
      "id": "autores_vs_objetivos_QA_50_enriquecido__021",
      "title": "¿Cómo conversa el enfoque de Gobernanza anticipatoria con los objetivos estratégicos de UDALBA?",
      "source": "Autores vs Objetivos.pdf",
      "text": "Q: ¿Cómo conversa el enfoque de Gobernanza anticipatoria con los objetivos estratégicos de UDALBA?\n\nA: Gobernanza anticipatoria propone: Incorporar el largo plazo en decisiones; vigilancia de tendencias, escenarios y pilotaje de innovaciones para orientar oferta, investigación e infraestructura. Esto se alinea con objetivos como 1, 5, 6, 7, 14, 17, 19, fortaleciendo capacidades institucionales, calidad educativa, transformación digital y pertinencia territorial.\n\nVariantes:\n- ¿De qué manera Gobernanza anticipatoria se alinea con las metas institucionales?\n- ¿Qué aporta Gobernanza anticipatoria a la hoja de ruta 2025–2045 de UDALBA?\n- Explica la relación entre Gobernanza anticipatoria y los objetivos priorizados\n\n\nMeta:\n- País: Chile\n- Periodo: 2025–2045\n- Sección: p.5–6\n- Audiencia: IES,policymakers,docentes\n- Documento: Autores vs Objetivos.pdf\n- Tags: gobernanza-anticipatoria, relación-objetivos",
      "tags": [
        "gobernanza-anticipatoria",
        "relación-objetivos"
      ],
      "meta": {
        "country": "Chile",
        "timeframe": "2025–2045",
        "section": "p.5–6",
        "audience": "IES,policymakers,docentes",
        "base": "autores_vs_objetivos_QA_50_enriquecido"
      }
    },
    {
      "id": "autores_vs_objetivos_QA_50_enriquecido__022",
      "title": "¿Cómo Gobernanza anticipatoria respalda el objetivo 1 de UDALBA?",
      "source": "Autores vs Objetivos.pdf",
      "text": "Q: ¿Cómo Gobernanza anticipatoria respalda el objetivo 1 de UDALBA?\n\nA: El enfoque de Gobernanza anticipatoria entrega una justificación conceptual y operativa para el objetivo 1, conectando políticas, procesos y capacidades con resultados esperados en ese ámbito, según la tabla comparativa (p.5–6).\n\nVariantes:\n- ¿Qué evidencia del documento vincula Gobernanza anticipatoria con el objetivo 1?\n- Describe el aporte de Gobernanza anticipatoria al objetivo 1\n- ¿Por qué Gobernanza anticipatoria es coherente con el objetivo 1?\n\n\nMeta:\n- País: Chile\n- Periodo: 2025–2045\n- Sección: p.5–6\n- Audiencia: IES,policymakers\n- Documento: Autores vs Objetivos.pdf\n- Tags: gobernanza-anticipatoria, objetivo-1",
      "tags": [
        "gobernanza-anticipatoria",
        "objetivo-1"
      ],
      "meta": {
        "country": "Chile",
        "timeframe": "2025–2045",
        "section": "p.5–6",
        "audience": "IES,policymakers",
        "base": "autores_vs_objetivos_QA_50_enriquecido"
      }
    },
    {
      "id": "autores_vs_objetivos_QA_50_enriquecido__023",
      "title": "¿Qué acciones concretas permitirían operativizar Gobernanza anticipatoria en UDALBA?",
      "source": "Autores vs Objetivos.pdf",
      "text": "Q: ¿Qué acciones concretas permitirían operativizar Gobernanza anticipatoria en UDALBA?\n\nA: Acciones: diseñar pilotos y escalamiento, ajustar mallas y credenciales, reforzar plataformas y datos, formar talento (docente/gestión), y vincular con territorios y empleo. Indicadores: progresión, titulación oportuna, satisfacción, empleabilidad, impacto territorial y métricas de uso digital.\n\nVariantes:\n- Propón medidas para implementar Gobernanza anticipatoria en programas y campus\n- ¿Qué indicadores usar para seguir la implementación de Gobernanza anticipatoria?\n- ¿Cómo integrar Gobernanza anticipatoria en gobernanza y evaluación?\n\n\nMeta:\n- País: Chile\n- Periodo: 2025–2045\n- Sección: p.5–6\n- Audiencia: IES,escuelas\n- Documento: Autores vs Objetivos.pdf\n- Tags: gobernanza-anticipatoria, implementación",
      "tags": [
        "gobernanza-anticipatoria",
        "implementación"
      ],
      "meta": {
        "country": "Chile",
        "timeframe": "2025–2045",
        "section": "p.5–6",
        "audience": "IES,escuelas",
        "base": "autores_vs_objetivos_QA_50_enriquecido"
      }
    },
    {
      "id": "autores_vs_objetivos_QA_50_enriquecido__024",
      "title": "¿En qué se diferencia Gobernanza anticipatoria de Competencias digitales docentes (CD) respecto a hibridez y transformación digital?",
      "source": "Autores vs Objetivos.pdf",
      "text": "Q: ¿En qué se diferencia Gobernanza anticipatoria de Competencias digitales docentes (CD) respecto a hibridez y transformación digital?\n\nA: Gobernanza anticipatoria enfatiza incorporar el largo plazo en decisiones mientras Competencias digitales docentes (CD) pone foco en gobernanza basada en datos y expansión operativa del campus físico–virtual (según sus apartados respectivos). Ambos convergen en transformación digital, pero difieren en el punto de partida y prioridades de implementación.\n\nVariantes:\n- Compara Gobernanza anticipatoria y Competencias digitales docentes (CD) en campus físico–virtual y datos\n- ¿Qué enfoque es más adecuado para trayectorias flexibles en UDALBA?\n- ¿Cómo varían sus implicancias en gobernanza y talento humano?\n\n\nMeta:\n- País: Chile\n- Periodo: 2025–2045\n- Sección: p.5–6\n- Audiencia: IES,policymakers,docentes\n- Documento: Autores vs Objetivos.pdf\n- Tags: gobernanza-anticipatoria, competencias-digitales-docentes-(cd), comparativa",
      "tags": [
        "gobernanza-anticipatoria",
        "competencias-digitales-docentes-(cd)",
        "comparativa"
      ],
      "meta": {
        "country": "Chile",
        "timeframe": "2025–2045",
        "section": "p.5–6",
        "audience": "IES,policymakers,docentes",
        "base": "autores_vs_objetivos_QA_50_enriquecido"
      }
    },
    {
      "id": "autores_vs_objetivos_QA_50_enriquecido__025",
      "title": "¿Qué riesgos y mitigaciones se deben considerar al adoptar Gobernanza anticipatoria en UDALBA?",
      "source": "Autores vs Objetivos.pdf",
      "text": "Q: ¿Qué riesgos y mitigaciones se deben considerar al adoptar Gobernanza anticipatoria en UDALBA?\n\nA: Riesgos: sesgos y privacidad de datos, inequidades de acceso digital, sobrecarga de cambio organizacional. Mitigaciones: marcos éticos, gobernanza de datos, inversión en conectividad y soporte, formación continua, participación de comunidades y pilotaje con evaluación de impacto.\n\nVariantes:\n- ¿Qué salvaguardas éticas y de datos acompañan Gobernanza anticipatoria?\n- ¿Cómo evitar brechas y resistencias en la implementación de Gobernanza anticipatoria?\n- ¿Qué prácticas de gestión del cambio requiere Gobernanza anticipatoria?\n\n\nMeta:\n- País: Chile\n- Periodo: 2025–2045\n- Sección: p.5–6\n- Audiencia: IES,policymakers\n- Documento: Autores vs Objetivos.pdf\n- Tags: gobernanza-anticipatoria, riesgos, mitigaciones",
      "tags": [
        "gobernanza-anticipatoria",
        "riesgos",
        "mitigaciones"
      ],
      "meta": {
        "country": "Chile",
        "timeframe": "2025–2045",
        "section": "p.5–6",
        "audience": "IES,policymakers",
        "base": "autores_vs_objetivos_QA_50_enriquecido"
      }
    },
    {
      "id": "autores_vs_objetivos_QA_50_enriquecido__026",
      "title": "¿Cómo conversa el enfoque de Competencias digitales docentes (CD) con los objetivos estratégicos de UDALBA?",
      "source": "Autores vs Objetivos.pdf",
      "text": "Q: ¿Cómo conversa el enfoque de Competencias digitales docentes (CD) con los objetivos estratégicos de UDALBA?\n\nA: Competencias digitales docentes (CD) propone: Priorizar competencia digital docente, diagnóstico sistemático de brechas, formación continua diferenciada, integración pedagógica de TIC, ciudadanía digital y ética. Esto se alinea con objetivos como 2, 3, 4, 6, 7, 10, 12, 13, 19, fortaleciendo capacidades institucionales, calidad educativa, transformación digital y pertinencia territorial.\n\nVariantes:\n- ¿De qué manera Competencias digitales docentes (CD) se alinea con las metas institucionales?\n- ¿Qué aporta Competencias digitales docentes (CD) a la hoja de ruta 2025–2045 de UDALBA?\n- Explica la relación entre Competencias digitales docentes (CD) y los objetivos priorizados\n\n\nMeta:\n- País: Chile\n- Periodo: 2025–2045\n- Sección: p.6–7\n- Audiencia: IES,policymakers,docentes\n- Documento: Autores vs Objetivos.pdf\n- Tags: competencias-digitales-docentes-(cd), relación-objetivos",
      "tags": [
        "competencias-digitales-docentes-(cd)",
        "relación-objetivos"
      ],
      "meta": {
        "country": "Chile",
        "timeframe": "2025–2045",
        "section": "p.6–7",
        "audience": "IES,policymakers,docentes",
        "base": "autores_vs_objetivos_QA_50_enriquecido"
      }
    },
    {
      "id": "autores_vs_objetivos_QA_50_enriquecido__027",
      "title": "¿Cómo Competencias digitales docentes (CD) respalda el objetivo 2 de UDALBA?",
      "source": "Autores vs Objetivos.pdf",
      "text": "Q: ¿Cómo Competencias digitales docentes (CD) respalda el objetivo 2 de UDALBA?\n\nA: El enfoque de Competencias digitales docentes (CD) entrega una justificación conceptual y operativa para el objetivo 2, conectando políticas, procesos y capacidades con resultados esperados en ese ámbito, según la tabla comparativa (p.6–7).\n\nVariantes:\n- ¿Qué evidencia del documento vincula Competencias digitales docentes (CD) con el objetivo 2?\n- Describe el aporte de Competencias digitales docentes (CD) al objetivo 2\n- ¿Por qué Competencias digitales docentes (CD) es coherente con el objetivo 2?\n\n\nMeta:\n- País: Chile\n- Periodo: 2025–2045\n- Sección: p.6–7\n- Audiencia: IES,policymakers\n- Documento: Autores vs Objetivos.pdf\n- Tags: competencias-digitales-docentes-(cd), objetivo-2",
      "tags": [
        "competencias-digitales-docentes-(cd)",
        "objetivo-2"
      ],
      "meta": {
        "country": "Chile",
        "timeframe": "2025–2045",
        "section": "p.6–7",
        "audience": "IES,policymakers",
        "base": "autores_vs_objetivos_QA_50_enriquecido"
      }
    },
    {
      "id": "autores_vs_objetivos_QA_50_enriquecido__028",
      "title": "¿Qué acciones concretas permitirían operativizar Competencias digitales docentes (CD) en UDALBA?",
      "source": "Autores vs Objetivos.pdf",
      "text": "Q: ¿Qué acciones concretas permitirían operativizar Competencias digitales docentes (CD) en UDALBA?\n\nA: Acciones: diseñar pilotos y escalamiento, ajustar mallas y credenciales, reforzar plataformas y datos, formar talento (docente/gestión), y vincular con territorios y empleo. Indicadores: progresión, titulación oportuna, satisfacción, empleabilidad, impacto territorial y métricas de uso digital.\n\nVariantes:\n- Propón medidas para implementar Competencias digitales docentes (CD) en programas y campus\n- ¿Qué indicadores usar para seguir la implementación de Competencias digitales docentes (CD)?\n- ¿Cómo integrar Competencias digitales docentes (CD) en gobernanza y evaluación?\n\n\nMeta:\n- País: Chile\n- Periodo: 2025–2045\n- Sección: p.6–7\n- Audiencia: IES,escuelas\n- Documento: Autores vs Objetivos.pdf\n- Tags: competencias-digitales-docentes-(cd), implementación",
      "tags": [
        "competencias-digitales-docentes-(cd)",
        "implementación"
      ],
      "meta": {
        "country": "Chile",
        "timeframe": "2025–2045",
        "section": "p.6–7",
        "audience": "IES,escuelas",
        "base": "autores_vs_objetivos_QA_50_enriquecido"
      }
    },
    {
      "id": "autores_vs_objetivos_QA_50_enriquecido__029",
      "title": "¿En qué se diferencia Competencias digitales docentes (CD) de Gobernanza meritocrática y docencia reinventada respecto a hibridez y transfor",
      "source": "Autores vs Objetivos.pdf",
      "text": "Q: ¿En qué se diferencia Competencias digitales docentes (CD) de Gobernanza meritocrática y docencia reinventada respecto a hibridez y transformación digital?\n\nA: Competencias digitales docentes (CD) enfatiza priorizar competencia digital docente, diagnóstico sistemático de brechas, formación continua diferenciada, integración pedagógica de tic, ciudadanía digital y ética. mientras Gobernanza meritocrática y docencia reinventada pone foco en gobernanza basada en datos y expansión operativa del campus físico–virtual (según sus apartados respectivos). Ambos convergen en transformación digital, pero difieren en el punto de partida y prioridades de implementación.\n\nVariantes:\n- Compara Competencias digitales docentes (CD) y Gobernanza meritocrática y docencia reinventada en campus físico–virtual y datos\n- ¿Qué enfoque es más adecuado para trayectorias flexibles en UDALBA?\n- ¿Cómo varían sus implicancias en gobernanza y talento humano?\n\n\nMeta:\n- País: Chile\n- Periodo: 2025–2045\n- Sección: p.6–7\n- Audiencia: IES,policymakers,docentes\n- Documento: Autores vs Objetivos.pdf\n- Tags: competencias-digitales-docentes-(cd), gobernanza-meritocrática-y-docencia-reinventada, comparativa",
      "tags": [
        "competencias-digitales-docentes-(cd)",
        "gobernanza-meritocrática-y-docencia-reinventada",
        "comparativa"
      ],
      "meta": {
        "country": "Chile",
        "timeframe": "2025–2045",
        "section": "p.6–7",
        "audience": "IES,policymakers,docentes",
        "base": "autores_vs_objetivos_QA_50_enriquecido"
      }
    },
    {
      "id": "autores_vs_objetivos_QA_50_enriquecido__030",
      "title": "¿Qué riesgos y mitigaciones se deben considerar al adoptar Competencias digitales docentes (CD) en UDALBA?",
      "source": "Autores vs Objetivos.pdf",
      "text": "Q: ¿Qué riesgos y mitigaciones se deben considerar al adoptar Competencias digitales docentes (CD) en UDALBA?\n\nA: Riesgos: sesgos y privacidad de datos, inequidades de acceso digital, sobrecarga de cambio organizacional. Mitigaciones: marcos éticos, gobernanza de datos, inversión en conectividad y soporte, formación continua, participación de comunidades y pilotaje con evaluación de impacto.\n\nVariantes:\n- ¿Qué salvaguardas éticas y de datos acompañan Competencias digitales docentes (CD)?\n- ¿Cómo evitar brechas y resistencias en la implementación de Competencias digitales docentes (CD)?\n- ¿Qué prácticas de gestión del cambio requiere Competencias digitales docentes (CD)?\n\n\nMeta:\n- País: Chile\n- Periodo: 2025–2045\n- Sección: p.6–7\n- Audiencia: IES,policymakers\n- Documento: Autores vs Objetivos.pdf\n- Tags: competencias-digitales-docentes-(cd), riesgos, mitigaciones",
      "tags": [
        "competencias-digitales-docentes-(cd)",
        "riesgos",
        "mitigaciones"
      ],
      "meta": {
        "country": "Chile",
        "timeframe": "2025–2045",
        "section": "p.6–7",
        "audience": "IES,policymakers",
        "base": "autores_vs_objetivos_QA_50_enriquecido"
      }
    },
    {
      "id": "autores_vs_objetivos_QA_50_enriquecido__031",
      "title": "¿Cómo conversa el enfoque de Gobernanza meritocrática y docencia reinventada con los objetivos estratégicos de UDALBA?",
      "source": "Autores vs Objetivos.pdf",
      "text": "Q: ¿Cómo conversa el enfoque de Gobernanza meritocrática y docencia reinventada con los objetivos estratégicos de UDALBA?\n\nA: Gobernanza meritocrática y docencia reinventada propone: Diversidad y diferenciación por función, meritocracia con rendición de cuentas, docencia como núcleo de legitimidad, profesionalización y carreras flexibles. Esto se alinea con objetivos como 1, 2, 3, 4, 5, 11, 18, 19, fortaleciendo capacidades institucionales, calidad educativa, transformación digital y pertinencia territorial.\n\nVariantes:\n- ¿De qué manera Gobernanza meritocrática y docencia reinventada se alinea con las metas institucionales?\n- ¿Qué aporta Gobernanza meritocrática y docencia reinventada a la hoja de ruta 2025–2045 de UDALBA?\n- Explica la relación entre Gobernanza meritocrática y docencia reinventada y los objetivos priorizados\n\n\nMeta:\n- País: Chile\n- Periodo: 2025–2045\n- Sección: p.7–8\n- Audiencia: IES,policymakers,docentes\n- Documento: Autores vs Objetivos.pdf\n- Tags: gobernanza-meritocrática-y-docencia-reinventada, relación-objetivos",
      "tags": [
        "gobernanza-meritocrática-y-docencia-reinventada",
        "relación-objetivos"
      ],
      "meta": {
        "country": "Chile",
        "timeframe": "2025–2045",
        "section": "p.7–8",
        "audience": "IES,policymakers,docentes",
        "base": "autores_vs_objetivos_QA_50_enriquecido"
      }
    },
    {
      "id": "autores_vs_objetivos_QA_50_enriquecido__032",
      "title": "¿Cómo Gobernanza meritocrática y docencia reinventada respalda el objetivo 1 de UDALBA?",
      "source": "Autores vs Objetivos.pdf",
      "text": "Q: ¿Cómo Gobernanza meritocrática y docencia reinventada respalda el objetivo 1 de UDALBA?\n\nA: El enfoque de Gobernanza meritocrática y docencia reinventada entrega una justificación conceptual y operativa para el objetivo 1, conectando políticas, procesos y capacidades con resultados esperados en ese ámbito, según la tabla comparativa (p.7–8).\n\nVariantes:\n- ¿Qué evidencia del documento vincula Gobernanza meritocrática y docencia reinventada con el objetivo 1?\n- Describe el aporte de Gobernanza meritocrática y docencia reinventada al objetivo 1\n- ¿Por qué Gobernanza meritocrática y docencia reinventada es coherente con el objetivo 1?\n\n\nMeta:\n- País: Chile\n- Periodo: 2025–2045\n- Sección: p.7–8\n- Audiencia: IES,policymakers\n- Documento: Autores vs Objetivos.pdf\n- Tags: gobernanza-meritocrática-y-docencia-reinventada, objetivo-1",
      "tags": [
        "gobernanza-meritocrática-y-docencia-reinventada",
        "objetivo-1"
      ],
      "meta": {
        "country": "Chile",
        "timeframe": "2025–2045",
        "section": "p.7–8",
        "audience": "IES,policymakers",
        "base": "autores_vs_objetivos_QA_50_enriquecido"
      }
    },
    {
      "id": "autores_vs_objetivos_QA_50_enriquecido__033",
      "title": "¿Qué acciones concretas permitirían operativizar Gobernanza meritocrática y docencia reinventada en UDALBA?",
      "source": "Autores vs Objetivos.pdf",
      "text": "Q: ¿Qué acciones concretas permitirían operativizar Gobernanza meritocrática y docencia reinventada en UDALBA?\n\nA: Acciones: diseñar pilotos y escalamiento, ajustar mallas y credenciales, reforzar plataformas y datos, formar talento (docente/gestión), y vincular con territorios y empleo. Indicadores: progresión, titulación oportuna, satisfacción, empleabilidad, impacto territorial y métricas de uso digital.\n\nVariantes:\n- Propón medidas para implementar Gobernanza meritocrática y docencia reinventada en programas y campus\n- ¿Qué indicadores usar para seguir la implementación de Gobernanza meritocrática y docencia reinventada?\n- ¿Cómo integrar Gobernanza meritocrática y docencia reinventada en gobernanza y evaluación?\n\n\nMeta:\n- País: Chile\n- Periodo: 2025–2045\n- Sección: p.7–8\n- Audiencia: IES,escuelas\n- Documento: Autores vs Objetivos.pdf\n- Tags: gobernanza-meritocrática-y-docencia-reinventada, implementación",
      "tags": [
        "gobernanza-meritocrática-y-docencia-reinventada",
        "implementación"
      ],
      "meta": {
        "country": "Chile",
        "timeframe": "2025–2045",
        "section": "p.7–8",
        "audience": "IES,escuelas",
        "base": "autores_vs_objetivos_QA_50_enriquecido"
      }
    },
    {
      "id": "autores_vs_objetivos_QA_50_enriquecido__034",
      "title": "¿En qué se diferencia Gobernanza meritocrática y docencia reinventada de Futuro líquido bien gobernado respecto a hibridez y transformación ",
      "source": "Autores vs Objetivos.pdf",
      "text": "Q: ¿En qué se diferencia Gobernanza meritocrática y docencia reinventada de Futuro líquido bien gobernado respecto a hibridez y transformación digital?\n\nA: Gobernanza meritocrática y docencia reinventada enfatiza diversidad y diferenciación por función, meritocracia con rendición de cuentas, docencia como núcleo de legitimidad, profesionalización y carreras flexibles. mientras Futuro líquido bien gobernado pone foco en gobernanza basada en datos y expansión operativa del campus físico–virtual (según sus apartados respectivos). Ambos convergen en transformación digital, pero difieren en el punto de partida y prioridades de implementación.\n\nVariantes:\n- Compara Gobernanza meritocrática y docencia reinventada y Futuro líquido bien gobernado en campus físico–virtual y datos\n- ¿Qué enfoque es más adecuado para trayectorias flexibles en UDALBA?\n- ¿Cómo varían sus implicancias en gobernanza y talento humano?\n\n\nMeta:\n- País: Chile\n- Periodo: 2025–2045\n- Sección: p.7–8\n- Audiencia: IES,policymakers,docentes\n- Documento: Autores vs Objetivos.pdf\n- Tags: gobernanza-meritocrática-y-docencia-reinventada, futuro-líquido-bien-gobernado, comparativa",
      "tags": [
        "gobernanza-meritocrática-y-docencia-reinventada",
        "futuro-líquido-bien-gobernado",
        "comparativa"
      ],
      "meta": {
        "country": "Chile",
        "timeframe": "2025–2045",
        "section": "p.7–8",
        "audience": "IES,policymakers,docentes",
        "base": "autores_vs_objetivos_QA_50_enriquecido"
      }
    },
    {
      "id": "autores_vs_objetivos_QA_50_enriquecido__035",
      "title": "¿Qué riesgos y mitigaciones se deben considerar al adoptar Gobernanza meritocrática y docencia reinventada en UDALBA?",
      "source": "Autores vs Objetivos.pdf",
      "text": "Q: ¿Qué riesgos y mitigaciones se deben considerar al adoptar Gobernanza meritocrática y docencia reinventada en UDALBA?\n\nA: Riesgos: sesgos y privacidad de datos, inequidades de acceso digital, sobrecarga de cambio organizacional. Mitigaciones: marcos éticos, gobernanza de datos, inversión en conectividad y soporte, formación continua, participación de comunidades y pilotaje con evaluación de impacto.\n\nVariantes:\n- ¿Qué salvaguardas éticas y de datos acompañan Gobernanza meritocrática y docencia reinventada?\n- ¿Cómo evitar brechas y resistencias en la implementación de Gobernanza meritocrática y docencia reinventada?\n- ¿Qué prácticas de gestión del cambio requiere Gobernanza meritocrática y docencia reinventada?\n\n\nMeta:\n- País: Chile\n- Periodo: 2025–2045\n- Sección: p.7–8\n- Audiencia: IES,policymakers\n- Documento: Autores vs Objetivos.pdf\n- Tags: gobernanza-meritocrática-y-docencia-reinventada, riesgos, mitigaciones",
      "tags": [
        "gobernanza-meritocrática-y-docencia-reinventada",
        "riesgos",
        "mitigaciones"
      ],
      "meta": {
        "country": "Chile",
        "timeframe": "2025–2045",
        "section": "p.7–8",
        "audience": "IES,policymakers",
        "base": "autores_vs_objetivos_QA_50_enriquecido"
      }
    },
    {
      "id": "autores_vs_objetivos_QA_50_enriquecido__036",
      "title": "¿Cómo conversa el enfoque de Futuro líquido bien gobernado con los objetivos estratégicos de UDALBA?",
      "source": "Autores vs Objetivos.pdf",
      "text": "Q: ¿Cómo conversa el enfoque de Futuro líquido bien gobernado con los objetivos estratégicos de UDALBA?\n\nA: Futuro líquido bien gobernado propone: Prospectiva y gobernanza anticipatoria para acercarse a escenarios deseables; agenda mínima: valor público, equidad, equilibrio presencial/virtual, financiamiento, carrera académica, vinculación territorial, sistemas de información. Esto se alinea con objetivos como 1, 2, 4, 5, 8, 11, 12, 14, 17, 19, fortaleciendo capacidades institucionales, calidad educativa, transformación digital y pertinencia territorial.\n\nVariantes:\n- ¿De qué manera Futuro líquido bien gobernado se alinea con las metas institucionales?\n- ¿Qué aporta Futuro líquido bien gobernado a la hoja de ruta 2025–2045 de UDALBA?\n- Explica la relación entre Futuro líquido bien gobernado y los objetivos priorizados\n\n\nMeta:\n- País: Chile\n- Periodo: 2025–2045\n- Sección: p.8–9\n- Audiencia: IES,policymakers,docentes\n- Documento: Autores vs Objetivos.pdf\n- Tags: futuro-líquido-bien-gobernado, relación-objetivos",
      "tags": [
        "futuro-líquido-bien-gobernado",
        "relación-objetivos"
      ],
      "meta": {
        "country": "Chile",
        "timeframe": "2025–2045",
        "section": "p.8–9",
        "audience": "IES,policymakers,docentes",
        "base": "autores_vs_objetivos_QA_50_enriquecido"
      }
    },
    {
      "id": "autores_vs_objetivos_QA_50_enriquecido__037",
      "title": "¿Cómo Futuro líquido bien gobernado respalda el objetivo 1 de UDALBA?",
      "source": "Autores vs Objetivos.pdf",
      "text": "Q: ¿Cómo Futuro líquido bien gobernado respalda el objetivo 1 de UDALBA?\n\nA: El enfoque de Futuro líquido bien gobernado entrega una justificación conceptual y operativa para el objetivo 1, conectando políticas, procesos y capacidades con resultados esperados en ese ámbito, según la tabla comparativa (p.8–9).\n\nVariantes:\n- ¿Qué evidencia del documento vincula Futuro líquido bien gobernado con el objetivo 1?\n- Describe el aporte de Futuro líquido bien gobernado al objetivo 1\n- ¿Por qué Futuro líquido bien gobernado es coherente con el objetivo 1?\n\n\nMeta:\n- País: Chile\n- Periodo: 2025–2045\n- Sección: p.8–9\n- Audiencia: IES,policymakers\n- Documento: Autores vs Objetivos.pdf\n- Tags: futuro-líquido-bien-gobernado, objetivo-1",
      "tags": [
        "futuro-líquido-bien-gobernado",
        "objetivo-1"
      ],
      "meta": {
        "country": "Chile",
        "timeframe": "2025–2045",
        "section": "p.8–9",
        "audience": "IES,policymakers",
        "base": "autores_vs_objetivos_QA_50_enriquecido"
      }
    },
    {
      "id": "autores_vs_objetivos_QA_50_enriquecido__038",
      "title": "¿Qué acciones concretas permitirían operativizar Futuro líquido bien gobernado en UDALBA?",
      "source": "Autores vs Objetivos.pdf",
      "text": "Q: ¿Qué acciones concretas permitirían operativizar Futuro líquido bien gobernado en UDALBA?\n\nA: Acciones: diseñar pilotos y escalamiento, ajustar mallas y credenciales, reforzar plataformas y datos, formar talento (docente/gestión), y vincular con territorios y empleo. Indicadores: progresión, titulación oportuna, satisfacción, empleabilidad, impacto territorial y métricas de uso digital.\n\nVariantes:\n- Propón medidas para implementar Futuro líquido bien gobernado en programas y campus\n- ¿Qué indicadores usar para seguir la implementación de Futuro líquido bien gobernado?\n- ¿Cómo integrar Futuro líquido bien gobernado en gobernanza y evaluación?\n\n\nMeta:\n- País: Chile\n- Periodo: 2025–2045\n- Sección: p.8–9\n- Audiencia: IES,escuelas\n- Documento: Autores vs Objetivos.pdf\n- Tags: futuro-líquido-bien-gobernado, implementación",
      "tags": [
        "futuro-líquido-bien-gobernado",
        "implementación"
      ],
      "meta": {
        "country": "Chile",
        "timeframe": "2025–2045",
        "section": "p.8–9",
        "audience": "IES,escuelas",
        "base": "autores_vs_objetivos_QA_50_enriquecido"
      }
    },
    {
      "id": "autores_vs_objetivos_QA_50_enriquecido__039",
      "title": "¿En qué se diferencia Futuro líquido bien gobernado de Universidad en la era digital respecto a hibridez y transformación digital?",
      "source": "Autores vs Objetivos.pdf",
      "text": "Q: ¿En qué se diferencia Futuro líquido bien gobernado de Universidad en la era digital respecto a hibridez y transformación digital?\n\nA: Futuro líquido bien gobernado enfatiza prospectiva y gobernanza anticipatoria para acercarse a escenarios deseables mientras Universidad en la era digital pone foco en gobernanza basada en datos y expansión operativa del campus físico–virtual (según sus apartados respectivos). Ambos convergen en transformación digital, pero difieren en el punto de partida y prioridades de implementación.\n\nVariantes:\n- Compara Futuro líquido bien gobernado y Universidad en la era digital en campus físico–virtual y datos\n- ¿Qué enfoque es más adecuado para trayectorias flexibles en UDALBA?\n- ¿Cómo varían sus implicancias en gobernanza y talento humano?\n\n\nMeta:\n- País: Chile\n- Periodo: 2025–2045\n- Sección: p.8–9\n- Audiencia: IES,policymakers,docentes\n- Documento: Autores vs Objetivos.pdf\n- Tags: futuro-líquido-bien-gobernado, universidad-en-la-era-digital, comparativa",
      "tags": [
        "futuro-líquido-bien-gobernado",
        "universidad-en-la-era-digital",
        "comparativa"
      ],
      "meta": {
        "country": "Chile",
        "timeframe": "2025–2045",
        "section": "p.8–9",
        "audience": "IES,policymakers,docentes",
        "base": "autores_vs_objetivos_QA_50_enriquecido"
      }
    },
    {
      "id": "autores_vs_objetivos_QA_50_enriquecido__040",
      "title": "¿Qué riesgos y mitigaciones se deben considerar al adoptar Futuro líquido bien gobernado en UDALBA?",
      "source": "Autores vs Objetivos.pdf",
      "text": "Q: ¿Qué riesgos y mitigaciones se deben considerar al adoptar Futuro líquido bien gobernado en UDALBA?\n\nA: Riesgos: sesgos y privacidad de datos, inequidades de acceso digital, sobrecarga de cambio organizacional. Mitigaciones: marcos éticos, gobernanza de datos, inversión en conectividad y soporte, formación continua, participación de comunidades y pilotaje con evaluación de impacto.\n\nVariantes:\n- ¿Qué salvaguardas éticas y de datos acompañan Futuro líquido bien gobernado?\n- ¿Cómo evitar brechas y resistencias en la implementación de Futuro líquido bien gobernado?\n- ¿Qué prácticas de gestión del cambio requiere Futuro líquido bien gobernado?\n\n\nMeta:\n- País: Chile\n- Periodo: 2025–2045\n- Sección: p.8–9\n- Audiencia: IES,policymakers\n- Documento: Autores vs Objetivos.pdf\n- Tags: futuro-líquido-bien-gobernado, riesgos, mitigaciones",
      "tags": [
        "futuro-líquido-bien-gobernado",
        "riesgos",
        "mitigaciones"
      ],
      "meta": {
        "country": "Chile",
        "timeframe": "2025–2045",
        "section": "p.8–9",
        "audience": "IES,policymakers",
        "base": "autores_vs_objetivos_QA_50_enriquecido"
      }
    },
    {
      "id": "autores_vs_objetivos_QA_50_enriquecido__041",
      "title": "¿Cómo conversa el enfoque de Universidad en la era digital con los objetivos estratégicos de UDALBA?",
      "source": "Autores vs Objetivos.pdf",
      "text": "Q: ¿Cómo conversa el enfoque de Universidad en la era digital con los objetivos estratégicos de UDALBA?\n\nA: Universidad en la era digital propone: Andragogía universitaria, revolución digital como motor de innovación, desarrollo de competencias digitales, gobernanza flexible, impacto ambiental, equidad y accesibilidad. Esto se alinea con objetivos como 2, 4, 6, 7, 10, 12, 13, 19, fortaleciendo capacidades institucionales, calidad educativa, transformación digital y pertinencia territorial.\n\nVariantes:\n- ¿De qué manera Universidad en la era digital se alinea con las metas institucionales?\n- ¿Qué aporta Universidad en la era digital a la hoja de ruta 2025–2045 de UDALBA?\n- Explica la relación entre Universidad en la era digital y los objetivos priorizados\n\n\nMeta:\n- País: Chile\n- Periodo: 2025–2045\n- Sección: p.9\n- Audiencia: IES,policymakers,docentes\n- Documento: Autores vs Objetivos.pdf\n- Tags: universidad-en-la-era-digital, relación-objetivos",
      "tags": [
        "universidad-en-la-era-digital",
        "relación-objetivos"
      ],
      "meta": {
        "country": "Chile",
        "timeframe": "2025–2045",
        "section": "p.9",
        "audience": "IES,policymakers,docentes",
        "base": "autores_vs_objetivos_QA_50_enriquecido"
      }
    },
    {
      "id": "autores_vs_objetivos_QA_50_enriquecido__042",
      "title": "¿Cómo Universidad en la era digital respalda el objetivo 2 de UDALBA?",
      "source": "Autores vs Objetivos.pdf",
      "text": "Q: ¿Cómo Universidad en la era digital respalda el objetivo 2 de UDALBA?\n\nA: El enfoque de Universidad en la era digital entrega una justificación conceptual y operativa para el objetivo 2, conectando políticas, procesos y capacidades con resultados esperados en ese ámbito, según la tabla comparativa (p.9).\n\nVariantes:\n- ¿Qué evidencia del documento vincula Universidad en la era digital con el objetivo 2?\n- Describe el aporte de Universidad en la era digital al objetivo 2\n- ¿Por qué Universidad en la era digital es coherente con el objetivo 2?\n\n\nMeta:\n- País: Chile\n- Periodo: 2025–2045\n- Sección: p.9\n- Audiencia: IES,policymakers\n- Documento: Autores vs Objetivos.pdf\n- Tags: universidad-en-la-era-digital, objetivo-2",
      "tags": [
        "universidad-en-la-era-digital",
        "objetivo-2"
      ],
      "meta": {
        "country": "Chile",
        "timeframe": "2025–2045",
        "section": "p.9",
        "audience": "IES,policymakers",
        "base": "autores_vs_objetivos_QA_50_enriquecido"
      }
    },
    {
      "id": "autores_vs_objetivos_QA_50_enriquecido__043",
      "title": "¿Qué acciones concretas permitirían operativizar Universidad en la era digital en UDALBA?",
      "source": "Autores vs Objetivos.pdf",
      "text": "Q: ¿Qué acciones concretas permitirían operativizar Universidad en la era digital en UDALBA?\n\nA: Acciones: diseñar pilotos y escalamiento, ajustar mallas y credenciales, reforzar plataformas y datos, formar talento (docente/gestión), y vincular con territorios y empleo. Indicadores: progresión, titulación oportuna, satisfacción, empleabilidad, impacto territorial y métricas de uso digital.\n\nVariantes:\n- Propón medidas para implementar Universidad en la era digital en programas y campus\n- ¿Qué indicadores usar para seguir la implementación de Universidad en la era digital?\n- ¿Cómo integrar Universidad en la era digital en gobernanza y evaluación?\n\n\nMeta:\n- País: Chile\n- Periodo: 2025–2045\n- Sección: p.9\n- Audiencia: IES,escuelas\n- Documento: Autores vs Objetivos.pdf\n- Tags: universidad-en-la-era-digital, implementación",
      "tags": [
        "universidad-en-la-era-digital",
        "implementación"
      ],
      "meta": {
        "country": "Chile",
        "timeframe": "2025–2045",
        "section": "p.9",
        "audience": "IES,escuelas",
        "base": "autores_vs_objetivos_QA_50_enriquecido"
      }
    },
    {
      "id": "autores_vs_objetivos_QA_50_enriquecido__044",
      "title": "¿En qué se diferencia Universidad en la era digital de IA y gobernanza universitaria respecto a hibridez y transformación digital?",
      "source": "Autores vs Objetivos.pdf",
      "text": "Q: ¿En qué se diferencia Universidad en la era digital de IA y gobernanza universitaria respecto a hibridez y transformación digital?\n\nA: Universidad en la era digital enfatiza andragogía universitaria, revolución digital como motor de innovación, desarrollo de competencias digitales, gobernanza flexible, impacto ambiental, equidad y accesibilidad. mientras IA y gobernanza universitaria pone foco en gobernanza basada en datos y expansión operativa del campus físico–virtual (según sus apartados respectivos). Ambos convergen en transformación digital, pero difieren en el punto de partida y prioridades de implementación.\n\nVariantes:\n- Compara Universidad en la era digital y IA y gobernanza universitaria en campus físico–virtual y datos\n- ¿Qué enfoque es más adecuado para trayectorias flexibles en UDALBA?\n- ¿Cómo varían sus implicancias en gobernanza y talento humano?\n\n\nMeta:\n- País: Chile\n- Periodo: 2025–2045\n- Sección: p.9\n- Audiencia: IES,policymakers,docentes\n- Documento: Autores vs Objetivos.pdf\n- Tags: universidad-en-la-era-digital, ia-y-gobernanza-universitaria, comparativa",
      "tags": [
        "universidad-en-la-era-digital",
        "ia-y-gobernanza-universitaria",
        "comparativa"
      ],
      "meta": {
        "country": "Chile",
        "timeframe": "2025–2045",
        "section": "p.9",
        "audience": "IES,policymakers,docentes",
        "base": "autores_vs_objetivos_QA_50_enriquecido"
      }
    },
    {
      "id": "autores_vs_objetivos_QA_50_enriquecido__045",
      "title": "¿Qué riesgos y mitigaciones se deben considerar al adoptar Universidad en la era digital en UDALBA?",
      "source": "Autores vs Objetivos.pdf",
      "text": "Q: ¿Qué riesgos y mitigaciones se deben considerar al adoptar Universidad en la era digital en UDALBA?\n\nA: Riesgos: sesgos y privacidad de datos, inequidades de acceso digital, sobrecarga de cambio organizacional. Mitigaciones: marcos éticos, gobernanza de datos, inversión en conectividad y soporte, formación continua, participación de comunidades y pilotaje con evaluación de impacto.\n\nVariantes:\n- ¿Qué salvaguardas éticas y de datos acompañan Universidad en la era digital?\n- ¿Cómo evitar brechas y resistencias en la implementación de Universidad en la era digital?\n- ¿Qué prácticas de gestión del cambio requiere Universidad en la era digital?\n\n\nMeta:\n- País: Chile\n- Periodo: 2025–2045\n- Sección: p.9\n- Audiencia: IES,policymakers\n- Documento: Autores vs Objetivos.pdf\n- Tags: universidad-en-la-era-digital, riesgos, mitigaciones",
      "tags": [
        "universidad-en-la-era-digital",
        "riesgos",
        "mitigaciones"
      ],
      "meta": {
        "country": "Chile",
        "timeframe": "2025–2045",
        "section": "p.9",
        "audience": "IES,policymakers",
        "base": "autores_vs_objetivos_QA_50_enriquecido"
      }
    },
    {
      "id": "autores_vs_objetivos_QA_50_enriquecido__046",
      "title": "¿Cómo conversa el enfoque de IA y gobernanza universitaria con los objetivos estratégicos de UDALBA?",
      "source": "Autores vs Objetivos.pdf",
      "text": "Q: ¿Cómo conversa el enfoque de IA y gobernanza universitaria con los objetivos estratégicos de UDALBA?\n\nA: IA y gobernanza universitaria propone: IA como eje estratégico de gestión; gobernanza de datos sólida, infraestructura interoperable, gestión del cambio y marcos éticos; mejora de transparencia y decisiones. Esto se alinea con objetivos como 1, 5, 6, 7, 10, 16, 18, 19, fortaleciendo capacidades institucionales, calidad educativa, transformación digital y pertinencia territorial.\n\nVariantes:\n- ¿De qué manera IA y gobernanza universitaria se alinea con las metas institucionales?\n- ¿Qué aporta IA y gobernanza universitaria a la hoja de ruta 2025–2045 de UDALBA?\n- Explica la relación entre IA y gobernanza universitaria y los objetivos priorizados\n\n\nMeta:\n- País: Chile\n- Periodo: 2025–2045\n- Sección: p.9–10\n- Audiencia: IES,policymakers,docentes\n- Documento: Autores vs Objetivos.pdf\n- Tags: ia-y-gobernanza-universitaria, relación-objetivos",
      "tags": [
        "ia-y-gobernanza-universitaria",
        "relación-objetivos"
      ],
      "meta": {
        "country": "Chile",
        "timeframe": "2025–2045",
        "section": "p.9–10",
        "audience": "IES,policymakers,docentes",
        "base": "autores_vs_objetivos_QA_50_enriquecido"
      }
    },
    {
      "id": "autores_vs_objetivos_QA_50_enriquecido__047",
      "title": "¿Cómo IA y gobernanza universitaria respalda el objetivo 1 de UDALBA?",
      "source": "Autores vs Objetivos.pdf",
      "text": "Q: ¿Cómo IA y gobernanza universitaria respalda el objetivo 1 de UDALBA?\n\nA: El enfoque de IA y gobernanza universitaria entrega una justificación conceptual y operativa para el objetivo 1, conectando políticas, procesos y capacidades con resultados esperados en ese ámbito, según la tabla comparativa (p.9–10).\n\nVariantes:\n- ¿Qué evidencia del documento vincula IA y gobernanza universitaria con el objetivo 1?\n- Describe el aporte de IA y gobernanza universitaria al objetivo 1\n- ¿Por qué IA y gobernanza universitaria es coherente con el objetivo 1?\n\n\nMeta:\n- País: Chile\n- Periodo: 2025–2045\n- Sección: p.9–10\n- Audiencia: IES,policymakers\n- Documento: Autores vs Objetivos.pdf\n- Tags: ia-y-gobernanza-universitaria, objetivo-1",
      "tags": [
        "ia-y-gobernanza-universitaria",
        "objetivo-1"
      ],
      "meta": {
        "country": "Chile",
        "timeframe": "2025–2045",
        "section": "p.9–10",
        "audience": "IES,policymakers",
        "base": "autores_vs_objetivos_QA_50_enriquecido"
      }
    },
    {
      "id": "autores_vs_objetivos_QA_50_enriquecido__048",
      "title": "¿Qué acciones concretas permitirían operativizar IA y gobernanza universitaria en UDALBA?",
      "source": "Autores vs Objetivos.pdf",
      "text": "Q: ¿Qué acciones concretas permitirían operativizar IA y gobernanza universitaria en UDALBA?\n\nA: Acciones: diseñar pilotos y escalamiento, ajustar mallas y credenciales, reforzar plataformas y datos, formar talento (docente/gestión), y vincular con territorios y empleo. Indicadores: progresión, titulación oportuna, satisfacción, empleabilidad, impacto territorial y métricas de uso digital.\n\nVariantes:\n- Propón medidas para implementar IA y gobernanza universitaria en programas y campus\n- ¿Qué indicadores usar para seguir la implementación de IA y gobernanza universitaria?\n- ¿Cómo integrar IA y gobernanza universitaria en gobernanza y evaluación?\n\n\nMeta:\n- País: Chile\n- Periodo: 2025–2045\n- Sección: p.9–10\n- Audiencia: IES,escuelas\n- Documento: Autores vs Objetivos.pdf\n- Tags: ia-y-gobernanza-universitaria, implementación",
      "tags": [
        "ia-y-gobernanza-universitaria",
        "implementación"
      ],
      "meta": {
        "country": "Chile",
        "timeframe": "2025–2045",
        "section": "p.9–10",
        "audience": "IES,escuelas",
        "base": "autores_vs_objetivos_QA_50_enriquecido"
      }
    },
    {
      "id": "autores_vs_objetivos_QA_50_enriquecido__049",
      "title": "¿En qué se diferencia IA y gobernanza universitaria de Universidad por capas respecto a hibridez y transformación digital?",
      "source": "Autores vs Objetivos.pdf",
      "text": "Q: ¿En qué se diferencia IA y gobernanza universitaria de Universidad por capas respecto a hibridez y transformación digital?\n\nA: IA y gobernanza universitaria enfatiza ia como eje estratégico de gestión mientras Universidad por capas pone foco en gobernanza basada en datos y expansión operativa del campus físico–virtual (según sus apartados respectivos). Ambos convergen en transformación digital, pero difieren en el punto de partida y prioridades de implementación.\n\nVariantes:\n- Compara IA y gobernanza universitaria y Universidad por capas en campus físico–virtual y datos\n- ¿Qué enfoque es más adecuado para trayectorias flexibles en UDALBA?\n- ¿Cómo varían sus implicancias en gobernanza y talento humano?\n\n\nMeta:\n- País: Chile\n- Periodo: 2025–2045\n- Sección: p.9–10\n- Audiencia: IES,policymakers,docentes\n- Documento: Autores vs Objetivos.pdf\n- Tags: ia-y-gobernanza-universitaria, universidad-por-capas, comparativa",
      "tags": [
        "ia-y-gobernanza-universitaria",
        "universidad-por-capas",
        "comparativa"
      ],
      "meta": {
        "country": "Chile",
        "timeframe": "2025–2045",
        "section": "p.9–10",
        "audience": "IES,policymakers,docentes",
        "base": "autores_vs_objetivos_QA_50_enriquecido"
      }
    },
    {
      "id": "autores_vs_objetivos_QA_50_enriquecido__050",
      "title": "¿Qué riesgos y mitigaciones se deben considerar al adoptar IA y gobernanza universitaria en UDALBA?",
      "source": "Autores vs Objetivos.pdf",
      "text": "Q: ¿Qué riesgos y mitigaciones se deben considerar al adoptar IA y gobernanza universitaria en UDALBA?\n\nA: Riesgos: sesgos y privacidad de datos, inequidades de acceso digital, sobrecarga de cambio organizacional. Mitigaciones: marcos éticos, gobernanza de datos, inversión en conectividad y soporte, formación continua, participación de comunidades y pilotaje con evaluación de impacto.\n\nVariantes:\n- ¿Qué salvaguardas éticas y de datos acompañan IA y gobernanza universitaria?\n- ¿Cómo evitar brechas y resistencias en la implementación de IA y gobernanza universitaria?\n- ¿Qué prácticas de gestión del cambio requiere IA y gobernanza universitaria?\n\n\nMeta:\n- País: Chile\n- Periodo: 2025–2045\n- Sección: p.9–10\n- Audiencia: IES,policymakers\n- Documento: Autores vs Objetivos.pdf\n- Tags: ia-y-gobernanza-universitaria, riesgos, mitigaciones",
      "tags": [
        "ia-y-gobernanza-universitaria",
        "riesgos",
        "mitigaciones"
      ],
      "meta": {
        "country": "Chile",
        "timeframe": "2025–2045",
        "section": "p.9–10",
        "audience": "IES,policymakers",
        "base": "autores_vs_objetivos_QA_50_enriquecido"
      }
    },
    {
      "id": "directrices_paises_QA_50_enriquecido__001",
      "title": "¿Cómo concibe Singapur la universidad del futuro y con qué objetivos estratégicos conversa?",
      "source": "Directrices (paises).pdf",
      "text": "Q: ¿Cómo concibe Singapur la universidad del futuro y con qué objetivos estratégicos conversa?\n\nA: Singapur prioriza: Aprendizaje permanente, credenciales apilables, gobernanza basada en datos y dashboards, subsidios mid-career, IA con políticas claras en NUS.. Esto conversa con objetivos como 1, 7, 10, 13, 15, 16, articulando flexibilidad, calidad, transformación digital, IA y/o impacto territorial según corresponda.\n\nVariantes:\n- Resume la visión de Singapur sobre la universidad del futuro\n- ¿Qué directrices de Singapur se alinean con los objetivos institucionales?\n- ¿Qué elementos clave definen el modelo futuro en Singapur?\n\n\nMeta:\n- País: Singapur\n- Periodo: 2025\n- Sección: p.3–7\n- Audiencia: IES,policymakers,docentes\n- Documento: Directrices (paises).pdf\n- Tags: singapur, overview, directrices",
      "tags": [
        "singapur",
        "overview",
        "directrices"
      ],
      "meta": {
        "country": "Singapur",
        "timeframe": "2025",
        "section": "p.3–7",
        "audience": "IES,policymakers,docentes",
        "base": "directrices_paises_QA_50_enriquecido"
      }
    },
    {
      "id": "directrices_paises_QA_50_enriquecido__002",
      "title": "¿Qué políticas concretas de Singapur respaldan los objetivos 1 y 7?",
      "source": "Directrices (paises).pdf",
      "text": "Q: ¿Qué políticas concretas de Singapur respaldan los objetivos 1 y 7?\n\nA: Singapur despliega instrumentos y marcos que viabilizan los objetivos 1 y 7: según el documento, Aprendizaje permanente, credenciales apilables, gobernanza basada en datos y dashboards, subsidios mid-career, IA con políticas claras en NUS.. Se operacionalizan con estándares, datos, plataformas y financiamiento que aseguran calidad y escalabilidad.\n\nVariantes:\n- Describe medidas clave de Singapur y su relación con objetivos institucionales\n- ¿Qué instrumentos de Singapur permiten avanzar en los objetivos 1 y 7?\n- Ejemplos de implementación en Singapur para dichos objetivos\n\n\nMeta:\n- País: Singapur\n- Periodo: 2025\n- Sección: p.3–7\n- Audiencia: IES,policymakers\n- Documento: Directrices (paises).pdf\n- Tags: singapur, objetivo-1, objetivo-7, policy-detail",
      "tags": [
        "singapur",
        "objetivo-1",
        "objetivo-7",
        "policy-detail"
      ],
      "meta": {
        "country": "Singapur",
        "timeframe": "2025",
        "section": "p.3–7",
        "audience": "IES,policymakers",
        "base": "directrices_paises_QA_50_enriquecido"
      }
    },
    {
      "id": "directrices_paises_QA_50_enriquecido__003",
      "title": "¿Qué acciones podría adoptar UDALBA inspirándose en las directrices de Singapur?",
      "source": "Directrices (paises).pdf",
      "text": "Q: ¿Qué acciones podría adoptar UDALBA inspirándose en las directrices de Singapur?\n\nA: Acciones: diseñar pilotos con métricas claras, modularizar credenciales y rutas, fortalecer interoperabilidad y analítica, formar talento (docente/gestión) y asegurar financiamiento y soporte. Indicadores: progresión, retención, satisfacción, empleabilidad, uso de plataformas, calidad y equidad.\n\nVariantes:\n- Propón medidas aplicables en UDALBA basadas en Singapur\n- ¿Qué pilotos y escalamiento se pueden diseñar tomando como referencia a Singapur?\n- ¿Qué indicadores se usarían para seguir la implementación inspirada en Singapur?\n\n\nMeta:\n- País: Singapur\n- Periodo: 2025–2028\n- Sección: p.3–7\n- Audiencia: IES,escuelas\n- Documento: Directrices (paises).pdf\n- Tags: singapur, aplicación, implementación",
      "tags": [
        "singapur",
        "aplicación",
        "implementación"
      ],
      "meta": {
        "country": "Singapur",
        "timeframe": "2025–2028",
        "section": "p.3–7",
        "audience": "IES,escuelas",
        "base": "directrices_paises_QA_50_enriquecido"
      }
    },
    {
      "id": "directrices_paises_QA_50_enriquecido__004",
      "title": "¿Qué riesgos y mitigaciones son clave al adoptar elementos del modelo de Singapur?",
      "source": "Directrices (paises).pdf",
      "text": "Q: ¿Qué riesgos y mitigaciones son clave al adoptar elementos del modelo de Singapur?\n\nA: Riesgos: sesgos/privacidad de datos, inequidad en acceso digital, fragmentación de calidad, fatiga organizacional. Mitigaciones: marcos éticos y de datos, interoperabilidad y estándares, apoyos y subsidios focalizados, formación continua, comunicación y participación, pilotaje con evaluación de impacto.\n\nVariantes:\n- Identifica salvaguardas éticas y de datos al adaptar prácticas de Singapur\n- ¿Cómo evitar inequidades y resistencias en la implementación de directrices de Singapur?\n- ¿Qué gobernanza del cambio se requiere para adoptar el enfoque de Singapur?\n\n\nMeta:\n- País: Singapur\n- Periodo: 2025\n- Sección: p.3–7\n- Audiencia: IES,policymakers\n- Documento: Directrices (paises).pdf\n- Tags: singapur, riesgos, mitigaciones",
      "tags": [
        "singapur",
        "riesgos",
        "mitigaciones"
      ],
      "meta": {
        "country": "Singapur",
        "timeframe": "2025",
        "section": "p.3–7",
        "audience": "IES,policymakers",
        "base": "directrices_paises_QA_50_enriquecido"
      }
    },
    {
      "id": "directrices_paises_QA_50_enriquecido__005",
      "title": "¿Cómo concibe Alemania la universidad del futuro y con qué objetivos estratégicos conversa?",
      "source": "Directrices (paises).pdf",
      "text": "Q: ¿Cómo concibe Alemania la universidad del futuro y con qué objetivos estratégicos conversa?\n\nA: Alemania prioriza: Calidad estructural y mejora continua, profesionalización del talento académico, interoperabilidad y gobernanza digital, adopción responsable de IA, investigación de excelencia.. Esto conversa con objetivos como 2, 4, 6, 7, 11, 19, articulando flexibilidad, calidad, transformación digital, IA y/o impacto territorial según corresponda.\n\nVariantes:\n- Resume la visión de Alemania sobre la universidad del futuro\n- ¿Qué directrices de Alemania se alinean con los objetivos institucionales?\n- ¿Qué elementos clave definen el modelo futuro en Alemania?\n\n\nMeta:\n- País: Alemania\n- Periodo: 2025\n- Sección: p.7–9\n- Audiencia: IES,policymakers,docentes\n- Documento: Directrices (paises).pdf\n- Tags: alemania, overview, directrices",
      "tags": [
        "alemania",
        "overview",
        "directrices"
      ],
      "meta": {
        "country": "Alemania",
        "timeframe": "2025",
        "section": "p.7–9",
        "audience": "IES,policymakers,docentes",
        "base": "directrices_paises_QA_50_enriquecido"
      }
    },
    {
      "id": "directrices_paises_QA_50_enriquecido__006",
      "title": "¿Qué políticas concretas de Alemania respaldan los objetivos 2 y 4?",
      "source": "Directrices (paises).pdf",
      "text": "Q: ¿Qué políticas concretas de Alemania respaldan los objetivos 2 y 4?\n\nA: Alemania despliega instrumentos y marcos que viabilizan los objetivos 2 y 4: según el documento, Calidad estructural y mejora continua, profesionalización del talento académico, interoperabilidad y gobernanza digital, adopción responsable de IA, investigación de excelencia.. Se operacionalizan con estándares, datos, plataformas y financiamiento que aseguran calidad y escalabilidad.\n\nVariantes:\n- Describe medidas clave de Alemania y su relación con objetivos institucionales\n- ¿Qué instrumentos de Alemania permiten avanzar en los objetivos 2 y 4?\n- Ejemplos de implementación en Alemania para dichos objetivos\n\n\nMeta:\n- País: Alemania\n- Periodo: 2025\n- Sección: p.7–9\n- Audiencia: IES,policymakers\n- Documento: Directrices (paises).pdf\n- Tags: alemania, objetivo-2, objetivo-4, policy-detail",
      "tags": [
        "alemania",
        "objetivo-2",
        "objetivo-4",
        "policy-detail"
      ],
      "meta": {
        "country": "Alemania",
        "timeframe": "2025",
        "section": "p.7–9",
        "audience": "IES,policymakers",
        "base": "directrices_paises_QA_50_enriquecido"
      }
    },
    {
      "id": "directrices_paises_QA_50_enriquecido__007",
      "title": "¿Qué acciones podría adoptar UDALBA inspirándose en las directrices de Alemania?",
      "source": "Directrices (paises).pdf",
      "text": "Q: ¿Qué acciones podría adoptar UDALBA inspirándose en las directrices de Alemania?\n\nA: Acciones: diseñar pilotos con métricas claras, modularizar credenciales y rutas, fortalecer interoperabilidad y analítica, formar talento (docente/gestión) y asegurar financiamiento y soporte. Indicadores: progresión, retención, satisfacción, empleabilidad, uso de plataformas, calidad y equidad.\n\nVariantes:\n- Propón medidas aplicables en UDALBA basadas en Alemania\n- ¿Qué pilotos y escalamiento se pueden diseñar tomando como referencia a Alemania?\n- ¿Qué indicadores se usarían para seguir la implementación inspirada en Alemania?\n\n\nMeta:\n- País: Alemania\n- Periodo: 2025–2028\n- Sección: p.7–9\n- Audiencia: IES,escuelas\n- Documento: Directrices (paises).pdf\n- Tags: alemania, aplicación, implementación",
      "tags": [
        "alemania",
        "aplicación",
        "implementación"
      ],
      "meta": {
        "country": "Alemania",
        "timeframe": "2025–2028",
        "section": "p.7–9",
        "audience": "IES,escuelas",
        "base": "directrices_paises_QA_50_enriquecido"
      }
    },
    {
      "id": "directrices_paises_QA_50_enriquecido__008",
      "title": "¿Qué riesgos y mitigaciones son clave al adoptar elementos del modelo de Alemania?",
      "source": "Directrices (paises).pdf",
      "text": "Q: ¿Qué riesgos y mitigaciones son clave al adoptar elementos del modelo de Alemania?\n\nA: Riesgos: sesgos/privacidad de datos, inequidad en acceso digital, fragmentación de calidad, fatiga organizacional. Mitigaciones: marcos éticos y de datos, interoperabilidad y estándares, apoyos y subsidios focalizados, formación continua, comunicación y participación, pilotaje con evaluación de impacto.\n\nVariantes:\n- Identifica salvaguardas éticas y de datos al adaptar prácticas de Alemania\n- ¿Cómo evitar inequidades y resistencias en la implementación de directrices de Alemania?\n- ¿Qué gobernanza del cambio se requiere para adoptar el enfoque de Alemania?\n\n\nMeta:\n- País: Alemania\n- Periodo: 2025\n- Sección: p.7–9\n- Audiencia: IES,policymakers\n- Documento: Directrices (paises).pdf\n- Tags: alemania, riesgos, mitigaciones",
      "tags": [
        "alemania",
        "riesgos",
        "mitigaciones"
      ],
      "meta": {
        "country": "Alemania",
        "timeframe": "2025",
        "section": "p.7–9",
        "audience": "IES,policymakers",
        "base": "directrices_paises_QA_50_enriquecido"
      }
    },
    {
      "id": "directrices_paises_QA_50_enriquecido__009",
      "title": "¿Cómo concibe Países Bajos la universidad del futuro y con qué objetivos estratégicos conversa?",
      "source": "Directrices (paises).pdf",
      "text": "Q: ¿Cómo concibe Países Bajos la universidad del futuro y con qué objetivos estratégicos conversa?\n\nA: Países Bajos prioriza: Cooperación sistémica, trayectorias flexibles, credenciales portables, infraestructura digital común e interoperable, ciencia abierta y revisión de incentivos.. Esto conversa con objetivos como 1, 2, 8, 10, 13, 15, articulando flexibilidad, calidad, transformación digital, IA y/o impacto territorial según corresponda.\n\nVariantes:\n- Resume la visión de Países Bajos sobre la universidad del futuro\n- ¿Qué directrices de Países Bajos se alinean con los objetivos institucionales?\n- ¿Qué elementos clave definen el modelo futuro en Países Bajos?\n\n\nMeta:\n- País: Países Bajos\n- Periodo: 2025\n- Sección: p.9–10\n- Audiencia: IES,policymakers,docentes\n- Documento: Directrices (paises).pdf\n- Tags: países-bajos, overview, directrices",
      "tags": [
        "países-bajos",
        "overview",
        "directrices"
      ],
      "meta": {
        "country": "Países Bajos",
        "timeframe": "2025",
        "section": "p.9–10",
        "audience": "IES,policymakers,docentes",
        "base": "directrices_paises_QA_50_enriquecido"
      }
    },
    {
      "id": "directrices_paises_QA_50_enriquecido__010",
      "title": "¿Qué políticas concretas de Países Bajos respaldan los objetivos 1 y 2?",
      "source": "Directrices (paises).pdf",
      "text": "Q: ¿Qué políticas concretas de Países Bajos respaldan los objetivos 1 y 2?\n\nA: Países Bajos despliega instrumentos y marcos que viabilizan los objetivos 1 y 2: según el documento, Cooperación sistémica, trayectorias flexibles, credenciales portables, infraestructura digital común e interoperable, ciencia abierta y revisión de incentivos.. Se operacionalizan con estándares, datos, plataformas y financiamiento que aseguran calidad y escalabilidad.\n\nVariantes:\n- Describe medidas clave de Países Bajos y su relación con objetivos institucionales\n- ¿Qué instrumentos de Países Bajos permiten avanzar en los objetivos 1 y 2?\n- Ejemplos de implementación en Países Bajos para dichos objetivos\n\n\nMeta:\n- País: Países Bajos\n- Periodo: 2025\n- Sección: p.9–10\n- Audiencia: IES,policymakers\n- Documento: Directrices (paises).pdf\n- Tags: países-bajos, objetivo-1, objetivo-2, policy-detail",
      "tags": [
        "países-bajos",
        "objetivo-1",
        "objetivo-2",
        "policy-detail"
      ],
      "meta": {
        "country": "Países Bajos",
        "timeframe": "2025",
        "section": "p.9–10",
        "audience": "IES,policymakers",
        "base": "directrices_paises_QA_50_enriquecido"
      }
    },
    {
      "id": "directrices_paises_QA_50_enriquecido__011",
      "title": "¿Qué acciones podría adoptar UDALBA inspirándose en las directrices de Países Bajos?",
      "source": "Directrices (paises).pdf",
      "text": "Q: ¿Qué acciones podría adoptar UDALBA inspirándose en las directrices de Países Bajos?\n\nA: Acciones: diseñar pilotos con métricas claras, modularizar credenciales y rutas, fortalecer interoperabilidad y analítica, formar talento (docente/gestión) y asegurar financiamiento y soporte. Indicadores: progresión, retención, satisfacción, empleabilidad, uso de plataformas, calidad y equidad.\n\nVariantes:\n- Propón medidas aplicables en UDALBA basadas en Países Bajos\n- ¿Qué pilotos y escalamiento se pueden diseñar tomando como referencia a Países Bajos?\n- ¿Qué indicadores se usarían para seguir la implementación inspirada en Países Bajos?\n\n\nMeta:\n- País: Países Bajos\n- Periodo: 2025–2028\n- Sección: p.9–10\n- Audiencia: IES,escuelas\n- Documento: Directrices (paises).pdf\n- Tags: países-bajos, aplicación, implementación",
      "tags": [
        "países-bajos",
        "aplicación",
        "implementación"
      ],
      "meta": {
        "country": "Países Bajos",
        "timeframe": "2025–2028",
        "section": "p.9–10",
        "audience": "IES,escuelas",
        "base": "directrices_paises_QA_50_enriquecido"
      }
    },
    {
      "id": "directrices_paises_QA_50_enriquecido__012",
      "title": "¿Qué riesgos y mitigaciones son clave al adoptar elementos del modelo de Países Bajos?",
      "source": "Directrices (paises).pdf",
      "text": "Q: ¿Qué riesgos y mitigaciones son clave al adoptar elementos del modelo de Países Bajos?\n\nA: Riesgos: sesgos/privacidad de datos, inequidad en acceso digital, fragmentación de calidad, fatiga organizacional. Mitigaciones: marcos éticos y de datos, interoperabilidad y estándares, apoyos y subsidios focalizados, formación continua, comunicación y participación, pilotaje con evaluación de impacto.\n\nVariantes:\n- Identifica salvaguardas éticas y de datos al adaptar prácticas de Países Bajos\n- ¿Cómo evitar inequidades y resistencias en la implementación de directrices de Países Bajos?\n- ¿Qué gobernanza del cambio se requiere para adoptar el enfoque de Países Bajos?\n\n\nMeta:\n- País: Países Bajos\n- Periodo: 2025\n- Sección: p.9–10\n- Audiencia: IES,policymakers\n- Documento: Directrices (paises).pdf\n- Tags: países-bajos, riesgos, mitigaciones",
      "tags": [
        "países-bajos",
        "riesgos",
        "mitigaciones"
      ],
      "meta": {
        "country": "Países Bajos",
        "timeframe": "2025",
        "section": "p.9–10",
        "audience": "IES,policymakers",
        "base": "directrices_paises_QA_50_enriquecido"
      }
    },
    {
      "id": "directrices_paises_QA_50_enriquecido__013",
      "title": "¿Cómo concibe Estados Unidos la universidad del futuro y con qué objetivos estratégicos conversa?",
      "source": "Directrices (paises).pdf",
      "text": "Q: ¿Cómo concibe Estados Unidos la universidad del futuro y con qué objetivos estratégicos conversa?\n\nA: Estados Unidos prioriza: Hibridez como norma, portafolio de credenciales, IA y analítica para retención, estándares verificables de credenciales digitales, apertura científica.. Esto conversa con objetivos como 2, 8, 10, 12, 13, 14, 15, 16, articulando flexibilidad, calidad, transformación digital, IA y/o impacto territorial según corresponda.\n\nVariantes:\n- Resume la visión de Estados Unidos sobre la universidad del futuro\n- ¿Qué directrices de Estados Unidos se alinean con los objetivos institucionales?\n- ¿Qué elementos clave definen el modelo futuro en Estados Unidos?\n\n\nMeta:\n- País: Estados Unidos\n- Periodo: 2025\n- Sección: p.11–13\n- Audiencia: IES,policymakers,docentes\n- Documento: Directrices (paises).pdf\n- Tags: estados-unidos, overview, directrices",
      "tags": [
        "estados-unidos",
        "overview",
        "directrices"
      ],
      "meta": {
        "country": "Estados Unidos",
        "timeframe": "2025",
        "section": "p.11–13",
        "audience": "IES,policymakers,docentes",
        "base": "directrices_paises_QA_50_enriquecido"
      }
    },
    {
      "id": "directrices_paises_QA_50_enriquecido__014",
      "title": "¿Qué políticas concretas de Estados Unidos respaldan los objetivos 2 y 8?",
      "source": "Directrices (paises).pdf",
      "text": "Q: ¿Qué políticas concretas de Estados Unidos respaldan los objetivos 2 y 8?\n\nA: Estados Unidos despliega instrumentos y marcos que viabilizan los objetivos 2 y 8: según el documento, Hibridez como norma, portafolio de credenciales, IA y analítica para retención, estándares verificables de credenciales digitales, apertura científica.. Se operacionalizan con estándares, datos, plataformas y financiamiento que aseguran calidad y escalabilidad.\n\nVariantes:\n- Describe medidas clave de Estados Unidos y su relación con objetivos institucionales\n- ¿Qué instrumentos de Estados Unidos permiten avanzar en los objetivos 2 y 8?\n- Ejemplos de implementación en Estados Unidos para dichos objetivos\n\n\nMeta:\n- País: Estados Unidos\n- Periodo: 2025\n- Sección: p.11–13\n- Audiencia: IES,policymakers\n- Documento: Directrices (paises).pdf\n- Tags: estados-unidos, objetivo-2, objetivo-8, policy-detail",
      "tags": [
        "estados-unidos",
        "objetivo-2",
        "objetivo-8",
        "policy-detail"
      ],
      "meta": {
        "country": "Estados Unidos",
        "timeframe": "2025",
        "section": "p.11–13",
        "audience": "IES,policymakers",
        "base": "directrices_paises_QA_50_enriquecido"
      }
    },
    {
      "id": "directrices_paises_QA_50_enriquecido__015",
      "title": "¿Qué acciones podría adoptar UDALBA inspirándose en las directrices de Estados Unidos?",
      "source": "Directrices (paises).pdf",
      "text": "Q: ¿Qué acciones podría adoptar UDALBA inspirándose en las directrices de Estados Unidos?\n\nA: Acciones: diseñar pilotos con métricas claras, modularizar credenciales y rutas, fortalecer interoperabilidad y analítica, formar talento (docente/gestión) y asegurar financiamiento y soporte. Indicadores: progresión, retención, satisfacción, empleabilidad, uso de plataformas, calidad y equidad.\n\nVariantes:\n- Propón medidas aplicables en UDALBA basadas en Estados Unidos\n- ¿Qué pilotos y escalamiento se pueden diseñar tomando como referencia a Estados Unidos?\n- ¿Qué indicadores se usarían para seguir la implementación inspirada en Estados Unidos?\n\n\nMeta:\n- País: Estados Unidos\n- Periodo: 2025–2028\n- Sección: p.11–13\n- Audiencia: IES,escuelas\n- Documento: Directrices (paises).pdf\n- Tags: estados-unidos, aplicación, implementación",
      "tags": [
        "estados-unidos",
        "aplicación",
        "implementación"
      ],
      "meta": {
        "country": "Estados Unidos",
        "timeframe": "2025–2028",
        "section": "p.11–13",
        "audience": "IES,escuelas",
        "base": "directrices_paises_QA_50_enriquecido"
      }
    },
    {
      "id": "directrices_paises_QA_50_enriquecido__016",
      "title": "¿Qué riesgos y mitigaciones son clave al adoptar elementos del modelo de Estados Unidos?",
      "source": "Directrices (paises).pdf",
      "text": "Q: ¿Qué riesgos y mitigaciones son clave al adoptar elementos del modelo de Estados Unidos?\n\nA: Riesgos: sesgos/privacidad de datos, inequidad en acceso digital, fragmentación de calidad, fatiga organizacional. Mitigaciones: marcos éticos y de datos, interoperabilidad y estándares, apoyos y subsidios focalizados, formación continua, comunicación y participación, pilotaje con evaluación de impacto.\n\nVariantes:\n- Identifica salvaguardas éticas y de datos al adaptar prácticas de Estados Unidos\n- ¿Cómo evitar inequidades y resistencias en la implementación de directrices de Estados Unidos?\n- ¿Qué gobernanza del cambio se requiere para adoptar el enfoque de Estados Unidos?\n\n\nMeta:\n- País: Estados Unidos\n- Periodo: 2025\n- Sección: p.11–13\n- Audiencia: IES,policymakers\n- Documento: Directrices (paises).pdf\n- Tags: estados-unidos, riesgos, mitigaciones",
      "tags": [
        "estados-unidos",
        "riesgos",
        "mitigaciones"
      ],
      "meta": {
        "country": "Estados Unidos",
        "timeframe": "2025",
        "section": "p.11–13",
        "audience": "IES,policymakers",
        "base": "directrices_paises_QA_50_enriquecido"
      }
    },
    {
      "id": "directrices_paises_QA_50_enriquecido__017",
      "title": "¿Cómo concibe Reino Unido la universidad del futuro y con qué objetivos estratégicos conversa?",
      "source": "Directrices (paises).pdf",
      "text": "Q: ¿Cómo concibe Reino Unido la universidad del futuro y con qué objetivos estratégicos conversa?\n\nA: Reino Unido prioriza: Modularidad (LLE), regulación de calidad centrada en resultados (OfS/TEF), transformación digital integral (Jisc), IA generativa y rediseño evaluativo (QAA/Russell Group), ciencia abierta (UKRI/REF).. Esto conversa con objetivos como 2, 7, 8, 15, 16, 19, articulando flexibilidad, calidad, transformación digital, IA y/o impacto territorial según corresponda.\n\nVariantes:\n- Resume la visión de Reino Unido sobre la universidad del futuro\n- ¿Qué directrices de Reino Unido se alinean con los objetivos institucionales?\n- ¿Qué elementos clave definen el modelo futuro en Reino Unido?\n\n\nMeta:\n- País: Reino Unido\n- Periodo: 2025\n- Sección: p.13–15\n- Audiencia: IES,policymakers,docentes\n- Documento: Directrices (paises).pdf\n- Tags: reino-unido, overview, directrices",
      "tags": [
        "reino-unido",
        "overview",
        "directrices"
      ],
      "meta": {
        "country": "Reino Unido",
        "timeframe": "2025",
        "section": "p.13–15",
        "audience": "IES,policymakers,docentes",
        "base": "directrices_paises_QA_50_enriquecido"
      }
    },
    {
      "id": "directrices_paises_QA_50_enriquecido__018",
      "title": "¿Qué políticas concretas de Reino Unido respaldan los objetivos 2 y 7?",
      "source": "Directrices (paises).pdf",
      "text": "Q: ¿Qué políticas concretas de Reino Unido respaldan los objetivos 2 y 7?\n\nA: Reino Unido despliega instrumentos y marcos que viabilizan los objetivos 2 y 7: según el documento, Modularidad (LLE), regulación de calidad centrada en resultados (OfS/TEF), transformación digital integral (Jisc), IA generativa y rediseño evaluativo (QAA/Russell Group), ciencia abierta (UKRI/REF).. Se operacionalizan con estándares, datos, plataformas y financiamiento que aseguran calidad y escalabilidad.\n\nVariantes:\n- Describe medidas clave de Reino Unido y su relación con objetivos institucionales\n- ¿Qué instrumentos de Reino Unido permiten avanzar en los objetivos 2 y 7?\n- Ejemplos de implementación en Reino Unido para dichos objetivos\n\n\nMeta:\n- País: Reino Unido\n- Periodo: 2025\n- Sección: p.13–15\n- Audiencia: IES,policymakers\n- Documento: Directrices (paises).pdf\n- Tags: reino-unido, objetivo-2, objetivo-7, policy-detail",
      "tags": [
        "reino-unido",
        "objetivo-2",
        "objetivo-7",
        "policy-detail"
      ],
      "meta": {
        "country": "Reino Unido",
        "timeframe": "2025",
        "section": "p.13–15",
        "audience": "IES,policymakers",
        "base": "directrices_paises_QA_50_enriquecido"
      }
    },
    {
      "id": "directrices_paises_QA_50_enriquecido__019",
      "title": "¿Qué acciones podría adoptar UDALBA inspirándose en las directrices de Reino Unido?",
      "source": "Directrices (paises).pdf",
      "text": "Q: ¿Qué acciones podría adoptar UDALBA inspirándose en las directrices de Reino Unido?\n\nA: Acciones: diseñar pilotos con métricas claras, modularizar credenciales y rutas, fortalecer interoperabilidad y analítica, formar talento (docente/gestión) y asegurar financiamiento y soporte. Indicadores: progresión, retención, satisfacción, empleabilidad, uso de plataformas, calidad y equidad.\n\nVariantes:\n- Propón medidas aplicables en UDALBA basadas en Reino Unido\n- ¿Qué pilotos y escalamiento se pueden diseñar tomando como referencia a Reino Unido?\n- ¿Qué indicadores se usarían para seguir la implementación inspirada en Reino Unido?\n\n\nMeta:\n- País: Reino Unido\n- Periodo: 2025–2028\n- Sección: p.13–15\n- Audiencia: IES,escuelas\n- Documento: Directrices (paises).pdf\n- Tags: reino-unido, aplicación, implementación",
      "tags": [
        "reino-unido",
        "aplicación",
        "implementación"
      ],
      "meta": {
        "country": "Reino Unido",
        "timeframe": "2025–2028",
        "section": "p.13–15",
        "audience": "IES,escuelas",
        "base": "directrices_paises_QA_50_enriquecido"
      }
    },
    {
      "id": "directrices_paises_QA_50_enriquecido__020",
      "title": "¿Qué riesgos y mitigaciones son clave al adoptar elementos del modelo de Reino Unido?",
      "source": "Directrices (paises).pdf",
      "text": "Q: ¿Qué riesgos y mitigaciones son clave al adoptar elementos del modelo de Reino Unido?\n\nA: Riesgos: sesgos/privacidad de datos, inequidad en acceso digital, fragmentación de calidad, fatiga organizacional. Mitigaciones: marcos éticos y de datos, interoperabilidad y estándares, apoyos y subsidios focalizados, formación continua, comunicación y participación, pilotaje con evaluación de impacto.\n\nVariantes:\n- Identifica salvaguardas éticas y de datos al adaptar prácticas de Reino Unido\n- ¿Cómo evitar inequidades y resistencias en la implementación de directrices de Reino Unido?\n- ¿Qué gobernanza del cambio se requiere para adoptar el enfoque de Reino Unido?\n\n\nMeta:\n- País: Reino Unido\n- Periodo: 2025\n- Sección: p.13–15\n- Audiencia: IES,policymakers\n- Documento: Directrices (paises).pdf\n- Tags: reino-unido, riesgos, mitigaciones",
      "tags": [
        "reino-unido",
        "riesgos",
        "mitigaciones"
      ],
      "meta": {
        "country": "Reino Unido",
        "timeframe": "2025",
        "section": "p.13–15",
        "audience": "IES,policymakers",
        "base": "directrices_paises_QA_50_enriquecido"
      }
    },
    {
      "id": "directrices_paises_QA_50_enriquecido__021",
      "title": "¿Cómo concibe Francia la universidad del futuro y con qué objetivos estratégicos conversa?",
      "source": "Directrices (paises).pdf",
      "text": "Q: ¿Cómo concibe Francia la universidad del futuro y con qué objetivos estratégicos conversa?\n\nA: Francia prioriza: Transformación por programación pública: hibridación y plataformas nacionales (FUN), microcertificaciones con marcos comunes, inversión estratégica en I+D (France 2030/PEPR), ciencia abierta y transición ecológica, cultura de evaluación (Hcéres).. Esto conversa con objetivos como 2, 6, 8, 11, 14, 15, 19, articulando flexibilidad, calidad, transformación digital, IA y/o impacto territorial según corresponda.\n\nVariantes:\n- Resume la visión de Francia sobre la universidad del futuro\n- ¿Qué directrices de Francia se alinean con los objetivos institucionales?\n- ¿Qué elementos clave definen el modelo futuro en Francia?\n\n\nMeta:\n- País: Francia\n- Periodo: 2025\n- Sección: p.15–17\n- Audiencia: IES,policymakers,docentes\n- Documento: Directrices (paises).pdf\n- Tags: francia, overview, directrices",
      "tags": [
        "francia",
        "overview",
        "directrices"
      ],
      "meta": {
        "country": "Francia",
        "timeframe": "2025",
        "section": "p.15–17",
        "audience": "IES,policymakers,docentes",
        "base": "directrices_paises_QA_50_enriquecido"
      }
    },
    {
      "id": "directrices_paises_QA_50_enriquecido__022",
      "title": "¿Qué políticas concretas de Francia respaldan los objetivos 2 y 6?",
      "source": "Directrices (paises).pdf",
      "text": "Q: ¿Qué políticas concretas de Francia respaldan los objetivos 2 y 6?\n\nA: Francia despliega instrumentos y marcos que viabilizan los objetivos 2 y 6: según el documento, Transformación por programación pública: hibridación y plataformas nacionales (FUN), microcertificaciones con marcos comunes, inversión estratégica en I+D (France 2030/PEPR), ciencia abierta y transición ecológica, cultura de evaluación (Hcéres).. Se operacionalizan con estándares, datos, plataformas y financiamiento que aseguran calidad y escalabilidad.\n\nVariantes:\n- Describe medidas clave de Francia y su relación con objetivos institucionales\n- ¿Qué instrumentos de Francia permiten avanzar en los objetivos 2 y 6?\n- Ejemplos de implementación en Francia para dichos objetivos\n\n\nMeta:\n- País: Francia\n- Periodo: 2025\n- Sección: p.15–17\n- Audiencia: IES,policymakers\n- Documento: Directrices (paises).pdf\n- Tags: francia, objetivo-2, objetivo-6, policy-detail",
      "tags": [
        "francia",
        "objetivo-2",
        "objetivo-6",
        "policy-detail"
      ],
      "meta": {
        "country": "Francia",
        "timeframe": "2025",
        "section": "p.15–17",
        "audience": "IES,policymakers",
        "base": "directrices_paises_QA_50_enriquecido"
      }
    },
    {
      "id": "directrices_paises_QA_50_enriquecido__023",
      "title": "¿Qué acciones podría adoptar UDALBA inspirándose en las directrices de Francia?",
      "source": "Directrices (paises).pdf",
      "text": "Q: ¿Qué acciones podría adoptar UDALBA inspirándose en las directrices de Francia?\n\nA: Acciones: diseñar pilotos con métricas claras, modularizar credenciales y rutas, fortalecer interoperabilidad y analítica, formar talento (docente/gestión) y asegurar financiamiento y soporte. Indicadores: progresión, retención, satisfacción, empleabilidad, uso de plataformas, calidad y equidad.\n\nVariantes:\n- Propón medidas aplicables en UDALBA basadas en Francia\n- ¿Qué pilotos y escalamiento se pueden diseñar tomando como referencia a Francia?\n- ¿Qué indicadores se usarían para seguir la implementación inspirada en Francia?\n\n\nMeta:\n- País: Francia\n- Periodo: 2025–2028\n- Sección: p.15–17\n- Audiencia: IES,escuelas\n- Documento: Directrices (paises).pdf\n- Tags: francia, aplicación, implementación",
      "tags": [
        "francia",
        "aplicación",
        "implementación"
      ],
      "meta": {
        "country": "Francia",
        "timeframe": "2025–2028",
        "section": "p.15–17",
        "audience": "IES,escuelas",
        "base": "directrices_paises_QA_50_enriquecido"
      }
    },
    {
      "id": "directrices_paises_QA_50_enriquecido__024",
      "title": "¿Qué riesgos y mitigaciones son clave al adoptar elementos del modelo de Francia?",
      "source": "Directrices (paises).pdf",
      "text": "Q: ¿Qué riesgos y mitigaciones son clave al adoptar elementos del modelo de Francia?\n\nA: Riesgos: sesgos/privacidad de datos, inequidad en acceso digital, fragmentación de calidad, fatiga organizacional. Mitigaciones: marcos éticos y de datos, interoperabilidad y estándares, apoyos y subsidios focalizados, formación continua, comunicación y participación, pilotaje con evaluación de impacto.\n\nVariantes:\n- Identifica salvaguardas éticas y de datos al adaptar prácticas de Francia\n- ¿Cómo evitar inequidades y resistencias en la implementación de directrices de Francia?\n- ¿Qué gobernanza del cambio se requiere para adoptar el enfoque de Francia?\n\n\nMeta:\n- País: Francia\n- Periodo: 2025\n- Sección: p.15–17\n- Audiencia: IES,policymakers\n- Documento: Directrices (paises).pdf\n- Tags: francia, riesgos, mitigaciones",
      "tags": [
        "francia",
        "riesgos",
        "mitigaciones"
      ],
      "meta": {
        "country": "Francia",
        "timeframe": "2025",
        "section": "p.15–17",
        "audience": "IES,policymakers",
        "base": "directrices_paises_QA_50_enriquecido"
      }
    },
    {
      "id": "directrices_paises_QA_50_enriquecido__025",
      "title": "¿En qué se diferencian Singapur y Alemania respecto a gobernanza digital y uso de datos?",
      "source": "Directrices (paises).pdf",
      "text": "Q: ¿En qué se diferencian Singapur y Alemania respecto a gobernanza digital y uso de datos?\n\nA: Singapur pone énfasis en sus directrices específicas y habilitadores (según el documento), mientras Alemania prioriza mecanismos complementarios en el mismo eje. Ambos comparten metas de calidad y pertinencia, pero difieren en gobernanza, financiamiento y velocidad de adopción.\n\nVariantes:\n- Compara enfoques de Singapur y Alemania en gobernanza digital y uso de datos\n- ¿Qué ventajas y trade-offs muestran Singapur y Alemania en gobernanza digital y uso de datos?\n- ¿Qué lecciones aplicables a UDALBA surgen del contraste entre Singapur y Alemania?\n\n\nMeta:\n- País: Multi-país\n- Periodo: 2025\n- Sección: p.3–17\n- Audiencia: IES,policymakers,docentes\n- Documento: Directrices (paises).pdf\n- Tags: singapur, alemania, comparativa, gobernanza-digital-y-uso-de-datos",
      "tags": [
        "singapur",
        "alemania",
        "comparativa",
        "gobernanza-digital-y-uso-de-datos"
      ],
      "meta": {
        "country": "Multi-país",
        "timeframe": "2025",
        "section": "p.3–17",
        "audience": "IES,policymakers,docentes",
        "base": "directrices_paises_QA_50_enriquecido"
      }
    },
    {
      "id": "directrices_paises_QA_50_enriquecido__026",
      "title": "¿En qué se diferencian Singapur y Países Bajos respecto a credenciales apilables e interoperabilidad?",
      "source": "Directrices (paises).pdf",
      "text": "Q: ¿En qué se diferencian Singapur y Países Bajos respecto a credenciales apilables e interoperabilidad?\n\nA: Singapur pone énfasis en sus directrices específicas y habilitadores (según el documento), mientras Países Bajos prioriza mecanismos complementarios en el mismo eje. Ambos comparten metas de calidad y pertinencia, pero difieren en gobernanza, financiamiento y velocidad de adopción.\n\nVariantes:\n- Compara enfoques de Singapur y Países Bajos en credenciales apilables e interoperabilidad\n- ¿Qué ventajas y trade-offs muestran Singapur y Países Bajos en credenciales apilables e interoperabilidad?\n- ¿Qué lecciones aplicables a UDALBA surgen del contraste entre Singapur y Países Bajos?\n\n\nMeta:\n- País: Multi-país\n- Periodo: 2025\n- Sección: p.3–17\n- Audiencia: IES,policymakers,docentes\n- Documento: Directrices (paises).pdf\n- Tags: singapur, países-bajos, comparativa, credenciales-apilables-e-interoperabilidad",
      "tags": [
        "singapur",
        "países-bajos",
        "comparativa",
        "credenciales-apilables-e-interoperabilidad"
      ],
      "meta": {
        "country": "Multi-país",
        "timeframe": "2025",
        "section": "p.3–17",
        "audience": "IES,policymakers,docentes",
        "base": "directrices_paises_QA_50_enriquecido"
      }
    },
    {
      "id": "directrices_paises_QA_50_enriquecido__027",
      "title": "¿En qué se diferencian Estados Unidos y Reino Unido respecto a IA generativa y rediseño de evaluación?",
      "source": "Directrices (paises).pdf",
      "text": "Q: ¿En qué se diferencian Estados Unidos y Reino Unido respecto a IA generativa y rediseño de evaluación?\n\nA: Estados Unidos pone énfasis en sus directrices específicas y habilitadores (según el documento), mientras Reino Unido prioriza mecanismos complementarios en el mismo eje. Ambos comparten metas de calidad y pertinencia, pero difieren en gobernanza, financiamiento y velocidad de adopción.\n\nVariantes:\n- Compara enfoques de Estados Unidos y Reino Unido en IA generativa y rediseño de evaluación\n- ¿Qué ventajas y trade-offs muestran Estados Unidos y Reino Unido en IA generativa y rediseño de evaluación?\n- ¿Qué lecciones aplicables a UDALBA surgen del contraste entre Estados Unidos y Reino Unido?\n\n\nMeta:\n- País: Multi-país\n- Periodo: 2025\n- Sección: p.3–17\n- Audiencia: IES,policymakers,docentes\n- Documento: Directrices (paises).pdf\n- Tags: estados-unidos, reino-unido, comparativa, IA-generativa-y-rediseño-de-evaluación",
      "tags": [
        "estados-unidos",
        "reino-unido",
        "comparativa",
        "IA-generativa-y-rediseño-de-evaluación"
      ],
      "meta": {
        "country": "Multi-país",
        "timeframe": "2025",
        "section": "p.3–17",
        "audience": "IES,policymakers,docentes",
        "base": "directrices_paises_QA_50_enriquecido"
      }
    },
    {
      "id": "directrices_paises_QA_50_enriquecido__028",
      "title": "¿En qué se diferencian Estados Unidos y Francia respecto a plataformas nacionales vs. mercado de credenciales?",
      "source": "Directrices (paises).pdf",
      "text": "Q: ¿En qué se diferencian Estados Unidos y Francia respecto a plataformas nacionales vs. mercado de credenciales?\n\nA: Estados Unidos pone énfasis en sus directrices específicas y habilitadores (según el documento), mientras Francia prioriza mecanismos complementarios en el mismo eje. Ambos comparten metas de calidad y pertinencia, pero difieren en gobernanza, financiamiento y velocidad de adopción.\n\nVariantes:\n- Compara enfoques de Estados Unidos y Francia en plataformas nacionales vs. mercado de credenciales\n- ¿Qué ventajas y trade-offs muestran Estados Unidos y Francia en plataformas nacionales vs. mercado de credenciales?\n- ¿Qué lecciones aplicables a UDALBA surgen del contraste entre Estados Unidos y Francia?\n\n\nMeta:\n- País: Multi-país\n- Periodo: 2025\n- Sección: p.3–17\n- Audiencia: IES,policymakers,docentes\n- Documento: Directrices (paises).pdf\n- Tags: estados-unidos, francia, comparativa, plataformas-nacionales-vs.-mercado-de-credenciales",
      "tags": [
        "estados-unidos",
        "francia",
        "comparativa",
        "plataformas-nacionales-vs.-mercado-de-credenciales"
      ],
      "meta": {
        "country": "Multi-país",
        "timeframe": "2025",
        "section": "p.3–17",
        "audience": "IES,policymakers,docentes",
        "base": "directrices_paises_QA_50_enriquecido"
      }
    },
    {
      "id": "directrices_paises_QA_50_enriquecido__029",
      "title": "¿En qué se diferencian Países Bajos y Alemania respecto a cooperación sistémica e innovación docente?",
      "source": "Directrices (paises).pdf",
      "text": "Q: ¿En qué se diferencian Países Bajos y Alemania respecto a cooperación sistémica e innovación docente?\n\nA: Países Bajos pone énfasis en sus directrices específicas y habilitadores (según el documento), mientras Alemania prioriza mecanismos complementarios en el mismo eje. Ambos comparten metas de calidad y pertinencia, pero difieren en gobernanza, financiamiento y velocidad de adopción.\n\nVariantes:\n- Compara enfoques de Países Bajos y Alemania en cooperación sistémica e innovación docente\n- ¿Qué ventajas y trade-offs muestran Países Bajos y Alemania en cooperación sistémica e innovación docente?\n- ¿Qué lecciones aplicables a UDALBA surgen del contraste entre Países Bajos y Alemania?\n\n\nMeta:\n- País: Multi-país\n- Periodo: 2025\n- Sección: p.3–17\n- Audiencia: IES,policymakers,docentes\n- Documento: Directrices (paises).pdf\n- Tags: países-bajos, alemania, comparativa, cooperación-sistémica-e-innovación-docente",
      "tags": [
        "países-bajos",
        "alemania",
        "comparativa",
        "cooperación-sistémica-e-innovación-docente"
      ],
      "meta": {
        "country": "Multi-país",
        "timeframe": "2025",
        "section": "p.3–17",
        "audience": "IES,policymakers,docentes",
        "base": "directrices_paises_QA_50_enriquecido"
      }
    },
    {
      "id": "directrices_paises_QA_50_enriquecido__030",
      "title": "¿En qué se diferencian Reino Unido y Países Bajos respecto a modularidad y calidad regulada?",
      "source": "Directrices (paises).pdf",
      "text": "Q: ¿En qué se diferencian Reino Unido y Países Bajos respecto a modularidad y calidad regulada?\n\nA: Reino Unido pone énfasis en sus directrices específicas y habilitadores (según el documento), mientras Países Bajos prioriza mecanismos complementarios en el mismo eje. Ambos comparten metas de calidad y pertinencia, pero difieren en gobernanza, financiamiento y velocidad de adopción.\n\nVariantes:\n- Compara enfoques de Reino Unido y Países Bajos en modularidad y calidad regulada\n- ¿Qué ventajas y trade-offs muestran Reino Unido y Países Bajos en modularidad y calidad regulada?\n- ¿Qué lecciones aplicables a UDALBA surgen del contraste entre Reino Unido y Países Bajos?\n\n\nMeta:\n- País: Multi-país\n- Periodo: 2025\n- Sección: p.3–17\n- Audiencia: IES,policymakers,docentes\n- Documento: Directrices (paises).pdf\n- Tags: reino-unido, países-bajos, comparativa, modularidad-y-calidad-regulada",
      "tags": [
        "reino-unido",
        "países-bajos",
        "comparativa",
        "modularidad-y-calidad-regulada"
      ],
      "meta": {
        "country": "Multi-país",
        "timeframe": "2025",
        "section": "p.3–17",
        "audience": "IES,policymakers,docentes",
        "base": "directrices_paises_QA_50_enriquecido"
      }
    },
    {
      "id": "directrices_paises_QA_50_enriquecido__031",
      "title": "¿En qué se diferencian Francia y Alemania respecto a programación pública e interoperabilidad?",
      "source": "Directrices (paises).pdf",
      "text": "Q: ¿En qué se diferencian Francia y Alemania respecto a programación pública e interoperabilidad?\n\nA: Francia pone énfasis en sus directrices específicas y habilitadores (según el documento), mientras Alemania prioriza mecanismos complementarios en el mismo eje. Ambos comparten metas de calidad y pertinencia, pero difieren en gobernanza, financiamiento y velocidad de adopción.\n\nVariantes:\n- Compara enfoques de Francia y Alemania en programación pública e interoperabilidad\n- ¿Qué ventajas y trade-offs muestran Francia y Alemania en programación pública e interoperabilidad?\n- ¿Qué lecciones aplicables a UDALBA surgen del contraste entre Francia y Alemania?\n\n\nMeta:\n- País: Multi-país\n- Periodo: 2025\n- Sección: p.3–17\n- Audiencia: IES,policymakers,docentes\n- Documento: Directrices (paises).pdf\n- Tags: francia, alemania, comparativa, programación-pública-e-interoperabilidad",
      "tags": [
        "francia",
        "alemania",
        "comparativa",
        "programación-pública-e-interoperabilidad"
      ],
      "meta": {
        "country": "Multi-país",
        "timeframe": "2025",
        "section": "p.3–17",
        "audience": "IES,policymakers,docentes",
        "base": "directrices_paises_QA_50_enriquecido"
      }
    },
    {
      "id": "directrices_paises_QA_50_enriquecido__032",
      "title": "¿En qué se diferencian Singapur y Estados Unidos respecto a aprendizaje a lo largo de la vida y portafolio de credenciales?",
      "source": "Directrices (paises).pdf",
      "text": "Q: ¿En qué se diferencian Singapur y Estados Unidos respecto a aprendizaje a lo largo de la vida y portafolio de credenciales?\n\nA: Singapur pone énfasis en sus directrices específicas y habilitadores (según el documento), mientras Estados Unidos prioriza mecanismos complementarios en el mismo eje. Ambos comparten metas de calidad y pertinencia, pero difieren en gobernanza, financiamiento y velocidad de adopción.\n\nVariantes:\n- Compara enfoques de Singapur y Estados Unidos en aprendizaje a lo largo de la vida y portafolio de credenciales\n- ¿Qué ventajas y trade-offs muestran Singapur y Estados Unidos en aprendizaje a lo largo de la vida y portafolio de credenciales?\n- ¿Qué lecciones aplicables a UDALBA surgen del contraste entre Singapur y Estados Unidos?\n\n\nMeta:\n- País: Multi-país\n- Periodo: 2025\n- Sección: p.3–17\n- Audiencia: IES,policymakers,docentes\n- Documento: Directrices (paises).pdf\n- Tags: singapur, estados-unidos, comparativa, aprendizaje-a-lo-largo-de-la-vida-y-portafolio-de-credenciales",
      "tags": [
        "singapur",
        "estados-unidos",
        "comparativa",
        "aprendizaje-a-lo-largo-de-la-vida-y-portafolio-de-credenciales"
      ],
      "meta": {
        "country": "Multi-país",
        "timeframe": "2025",
        "section": "p.3–17",
        "audience": "IES,policymakers,docentes",
        "base": "directrices_paises_QA_50_enriquecido"
      }
    },
    {
      "id": "directrices_paises_QA_50_enriquecido__033",
      "title": "¿En qué se diferencian Reino Unido y Francia respecto a apertura científica y políticas de investigación?",
      "source": "Directrices (paises).pdf",
      "text": "Q: ¿En qué se diferencian Reino Unido y Francia respecto a apertura científica y políticas de investigación?\n\nA: Reino Unido pone énfasis en sus directrices específicas y habilitadores (según el documento), mientras Francia prioriza mecanismos complementarios en el mismo eje. Ambos comparten metas de calidad y pertinencia, pero difieren en gobernanza, financiamiento y velocidad de adopción.\n\nVariantes:\n- Compara enfoques de Reino Unido y Francia en apertura científica y políticas de investigación\n- ¿Qué ventajas y trade-offs muestran Reino Unido y Francia en apertura científica y políticas de investigación?\n- ¿Qué lecciones aplicables a UDALBA surgen del contraste entre Reino Unido y Francia?\n\n\nMeta:\n- País: Multi-país\n- Periodo: 2025\n- Sección: p.3–17\n- Audiencia: IES,policymakers,docentes\n- Documento: Directrices (paises).pdf\n- Tags: reino-unido, francia, comparativa, apertura-científica-y-políticas-de-investigación",
      "tags": [
        "reino-unido",
        "francia",
        "comparativa",
        "apertura-científica-y-políticas-de-investigación"
      ],
      "meta": {
        "country": "Multi-país",
        "timeframe": "2025",
        "section": "p.3–17",
        "audience": "IES,policymakers,docentes",
        "base": "directrices_paises_QA_50_enriquecido"
      }
    },
    {
      "id": "directrices_paises_QA_50_enriquecido__034",
      "title": "¿En qué se diferencian Singapur y Reino Unido respecto a subsidios y financiamiento vs. LLE?",
      "source": "Directrices (paises).pdf",
      "text": "Q: ¿En qué se diferencian Singapur y Reino Unido respecto a subsidios y financiamiento vs. LLE?\n\nA: Singapur pone énfasis en sus directrices específicas y habilitadores (según el documento), mientras Reino Unido prioriza mecanismos complementarios en el mismo eje. Ambos comparten metas de calidad y pertinencia, pero difieren en gobernanza, financiamiento y velocidad de adopción.\n\nVariantes:\n- Compara enfoques de Singapur y Reino Unido en subsidios y financiamiento vs. LLE\n- ¿Qué ventajas y trade-offs muestran Singapur y Reino Unido en subsidios y financiamiento vs. LLE?\n- ¿Qué lecciones aplicables a UDALBA surgen del contraste entre Singapur y Reino Unido?\n\n\nMeta:\n- País: Multi-país\n- Periodo: 2025\n- Sección: p.3–17\n- Audiencia: IES,policymakers,docentes\n- Documento: Directrices (paises).pdf\n- Tags: singapur, reino-unido, comparativa, subsidios-y-financiamiento-vs.-LLE",
      "tags": [
        "singapur",
        "reino-unido",
        "comparativa",
        "subsidios-y-financiamiento-vs.-LLE"
      ],
      "meta": {
        "country": "Multi-país",
        "timeframe": "2025",
        "section": "p.3–17",
        "audience": "IES,policymakers,docentes",
        "base": "directrices_paises_QA_50_enriquecido"
      }
    },
    {
      "id": "directrices_paises_QA_50_enriquecido__035",
      "title": "¿En qué se diferencian Países Bajos y Estados Unidos respecto a badges/microcredenciales y verificabilidad?",
      "source": "Directrices (paises).pdf",
      "text": "Q: ¿En qué se diferencian Países Bajos y Estados Unidos respecto a badges/microcredenciales y verificabilidad?\n\nA: Países Bajos pone énfasis en sus directrices específicas y habilitadores (según el documento), mientras Estados Unidos prioriza mecanismos complementarios en el mismo eje. Ambos comparten metas de calidad y pertinencia, pero difieren en gobernanza, financiamiento y velocidad de adopción.\n\nVariantes:\n- Compara enfoques de Países Bajos y Estados Unidos en badges/microcredenciales y verificabilidad\n- ¿Qué ventajas y trade-offs muestran Países Bajos y Estados Unidos en badges/microcredenciales y verificabilidad?\n- ¿Qué lecciones aplicables a UDALBA surgen del contraste entre Países Bajos y Estados Unidos?\n\n\nMeta:\n- País: Multi-país\n- Periodo: 2025\n- Sección: p.3–17\n- Audiencia: IES,policymakers,docentes\n- Documento: Directrices (paises).pdf\n- Tags: países-bajos, estados-unidos, comparativa, badges/microcredenciales-y-verificabilidad",
      "tags": [
        "países-bajos",
        "estados-unidos",
        "comparativa",
        "badges/microcredenciales-y-verificabilidad"
      ],
      "meta": {
        "country": "Multi-país",
        "timeframe": "2025",
        "section": "p.3–17",
        "audience": "IES,policymakers,docentes",
        "base": "directrices_paises_QA_50_enriquecido"
      }
    },
    {
      "id": "directrices_paises_QA_50_enriquecido__036",
      "title": "¿En qué se diferencian Alemania y Reino Unido respecto a regulación de calidad y estándares mínimos?",
      "source": "Directrices (paises).pdf",
      "text": "Q: ¿En qué se diferencian Alemania y Reino Unido respecto a regulación de calidad y estándares mínimos?\n\nA: Alemania pone énfasis en sus directrices específicas y habilitadores (según el documento), mientras Reino Unido prioriza mecanismos complementarios en el mismo eje. Ambos comparten metas de calidad y pertinencia, pero difieren en gobernanza, financiamiento y velocidad de adopción.\n\nVariantes:\n- Compara enfoques de Alemania y Reino Unido en regulación de calidad y estándares mínimos\n- ¿Qué ventajas y trade-offs muestran Alemania y Reino Unido en regulación de calidad y estándares mínimos?\n- ¿Qué lecciones aplicables a UDALBA surgen del contraste entre Alemania y Reino Unido?\n\n\nMeta:\n- País: Multi-país\n- Periodo: 2025\n- Sección: p.3–17\n- Audiencia: IES,policymakers,docentes\n- Documento: Directrices (paises).pdf\n- Tags: alemania, reino-unido, comparativa, regulación-de-calidad-y-estándares-mínimos",
      "tags": [
        "alemania",
        "reino-unido",
        "comparativa",
        "regulación-de-calidad-y-estándares-mínimos"
      ],
      "meta": {
        "country": "Multi-país",
        "timeframe": "2025",
        "section": "p.3–17",
        "audience": "IES,policymakers,docentes",
        "base": "directrices_paises_QA_50_enriquecido"
      }
    },
    {
      "id": "directrices_paises_QA_50_enriquecido__037",
      "title": "¿En qué se diferencian Francia y Países Bajos respecto a marcos comunes de credenciales y ciencia abierta?",
      "source": "Directrices (paises).pdf",
      "text": "Q: ¿En qué se diferencian Francia y Países Bajos respecto a marcos comunes de credenciales y ciencia abierta?\n\nA: Francia pone énfasis en sus directrices específicas y habilitadores (según el documento), mientras Países Bajos prioriza mecanismos complementarios en el mismo eje. Ambos comparten metas de calidad y pertinencia, pero difieren en gobernanza, financiamiento y velocidad de adopción.\n\nVariantes:\n- Compara enfoques de Francia y Países Bajos en marcos comunes de credenciales y ciencia abierta\n- ¿Qué ventajas y trade-offs muestran Francia y Países Bajos en marcos comunes de credenciales y ciencia abierta?\n- ¿Qué lecciones aplicables a UDALBA surgen del contraste entre Francia y Países Bajos?\n\n\nMeta:\n- País: Multi-país\n- Periodo: 2025\n- Sección: p.3–17\n- Audiencia: IES,policymakers,docentes\n- Documento: Directrices (paises).pdf\n- Tags: francia, países-bajos, comparativa, marcos-comunes-de-credenciales-y-ciencia-abierta",
      "tags": [
        "francia",
        "países-bajos",
        "comparativa",
        "marcos-comunes-de-credenciales-y-ciencia-abierta"
      ],
      "meta": {
        "country": "Multi-país",
        "timeframe": "2025",
        "section": "p.3–17",
        "audience": "IES,policymakers,docentes",
        "base": "directrices_paises_QA_50_enriquecido"
      }
    },
    {
      "id": "directrices_paises_QA_50_enriquecido__038",
      "title": "¿En qué se diferencian Estados Unidos y Alemania respecto a adopción de IA con marcos institucionales?",
      "source": "Directrices (paises).pdf",
      "text": "Q: ¿En qué se diferencian Estados Unidos y Alemania respecto a adopción de IA con marcos institucionales?\n\nA: Estados Unidos pone énfasis en sus directrices específicas y habilitadores (según el documento), mientras Alemania prioriza mecanismos complementarios en el mismo eje. Ambos comparten metas de calidad y pertinencia, pero difieren en gobernanza, financiamiento y velocidad de adopción.\n\nVariantes:\n- Compara enfoques de Estados Unidos y Alemania en adopción de IA con marcos institucionales\n- ¿Qué ventajas y trade-offs muestran Estados Unidos y Alemania en adopción de IA con marcos institucionales?\n- ¿Qué lecciones aplicables a UDALBA surgen del contraste entre Estados Unidos y Alemania?\n\n\nMeta:\n- País: Multi-país\n- Periodo: 2025\n- Sección: p.3–17\n- Audiencia: IES,policymakers,docentes\n- Documento: Directrices (paises).pdf\n- Tags: estados-unidos, alemania, comparativa, adopción-de-IA-con-marcos-institucionales",
      "tags": [
        "estados-unidos",
        "alemania",
        "comparativa",
        "adopción-de-IA-con-marcos-institucionales"
      ],
      "meta": {
        "country": "Multi-país",
        "timeframe": "2025",
        "section": "p.3–17",
        "audience": "IES,policymakers,docentes",
        "base": "directrices_paises_QA_50_enriquecido"
      }
    },
    {
      "id": "directrices_paises_QA_50_enriquecido__039",
      "title": "¿En qué se diferencian Singapur y Francia respecto a IA con guías institucionales vs. misiones nacionales?",
      "source": "Directrices (paises).pdf",
      "text": "Q: ¿En qué se diferencian Singapur y Francia respecto a IA con guías institucionales vs. misiones nacionales?\n\nA: Singapur pone énfasis en sus directrices específicas y habilitadores (según el documento), mientras Francia prioriza mecanismos complementarios en el mismo eje. Ambos comparten metas de calidad y pertinencia, pero difieren en gobernanza, financiamiento y velocidad de adopción.\n\nVariantes:\n- Compara enfoques de Singapur y Francia en IA con guías institucionales vs. misiones nacionales\n- ¿Qué ventajas y trade-offs muestran Singapur y Francia en IA con guías institucionales vs. misiones nacionales?\n- ¿Qué lecciones aplicables a UDALBA surgen del contraste entre Singapur y Francia?\n\n\nMeta:\n- País: Multi-país\n- Periodo: 2025\n- Sección: p.3–17\n- Audiencia: IES,policymakers,docentes\n- Documento: Directrices (paises).pdf\n- Tags: singapur, francia, comparativa, IA-con-guías-institucionales-vs.-misiones-nacionales",
      "tags": [
        "singapur",
        "francia",
        "comparativa",
        "IA-con-guías-institucionales-vs.-misiones-nacionales"
      ],
      "meta": {
        "country": "Multi-país",
        "timeframe": "2025",
        "section": "p.3–17",
        "audience": "IES,policymakers,docentes",
        "base": "directrices_paises_QA_50_enriquecido"
      }
    },
    {
      "id": "directrices_paises_QA_50_enriquecido__040",
      "title": "¿En qué se diferencian Reino Unido y Estados Unidos respecto a equidad y accesibilidad en hibridez?",
      "source": "Directrices (paises).pdf",
      "text": "Q: ¿En qué se diferencian Reino Unido y Estados Unidos respecto a equidad y accesibilidad en hibridez?\n\nA: Reino Unido pone énfasis en sus directrices específicas y habilitadores (según el documento), mientras Estados Unidos prioriza mecanismos complementarios en el mismo eje. Ambos comparten metas de calidad y pertinencia, pero difieren en gobernanza, financiamiento y velocidad de adopción.\n\nVariantes:\n- Compara enfoques de Reino Unido y Estados Unidos en equidad y accesibilidad en hibridez\n- ¿Qué ventajas y trade-offs muestran Reino Unido y Estados Unidos en equidad y accesibilidad en hibridez?\n- ¿Qué lecciones aplicables a UDALBA surgen del contraste entre Reino Unido y Estados Unidos?\n\n\nMeta:\n- País: Multi-país\n- Periodo: 2025\n- Sección: p.3–17\n- Audiencia: IES,policymakers,docentes\n- Documento: Directrices (paises).pdf\n- Tags: reino-unido, estados-unidos, comparativa, equidad-y-accesibilidad-en-hibridez",
      "tags": [
        "reino-unido",
        "estados-unidos",
        "comparativa",
        "equidad-y-accesibilidad-en-hibridez"
      ],
      "meta": {
        "country": "Multi-país",
        "timeframe": "2025",
        "section": "p.3–17",
        "audience": "IES,policymakers,docentes",
        "base": "directrices_paises_QA_50_enriquecido"
      }
    },
    {
      "id": "directrices_paises_QA_50_enriquecido__041",
      "title": "¿En qué se diferencian Alemania y Estados Unidos respecto a interoperabilidad y estándares de credenciales?",
      "source": "Directrices (paises).pdf",
      "text": "Q: ¿En qué se diferencian Alemania y Estados Unidos respecto a interoperabilidad y estándares de credenciales?\n\nA: Alemania pone énfasis en sus directrices específicas y habilitadores (según el documento), mientras Estados Unidos prioriza mecanismos complementarios en el mismo eje. Ambos comparten metas de calidad y pertinencia, pero difieren en gobernanza, financiamiento y velocidad de adopción.\n\nVariantes:\n- Compara enfoques de Alemania y Estados Unidos en interoperabilidad y estándares de credenciales\n- ¿Qué ventajas y trade-offs muestran Alemania y Estados Unidos en interoperabilidad y estándares de credenciales?\n- ¿Qué lecciones aplicables a UDALBA surgen del contraste entre Alemania y Estados Unidos?\n\n\nMeta:\n- País: Multi-país\n- Periodo: 2025\n- Sección: p.3–17\n- Audiencia: IES,policymakers,docentes\n- Documento: Directrices (paises).pdf\n- Tags: alemania, estados-unidos, comparativa, interoperabilidad-y-estándares-de-credenciales",
      "tags": [
        "alemania",
        "estados-unidos",
        "comparativa",
        "interoperabilidad-y-estándares-de-credenciales"
      ],
      "meta": {
        "country": "Multi-país",
        "timeframe": "2025",
        "section": "p.3–17",
        "audience": "IES,policymakers,docentes",
        "base": "directrices_paises_QA_50_enriquecido"
      }
    },
    {
      "id": "directrices_paises_QA_50_enriquecido__042",
      "title": "¿En qué se diferencian Países Bajos y Singapur respecto a coordinación de sistema y dashboards de habilidades?",
      "source": "Directrices (paises).pdf",
      "text": "Q: ¿En qué se diferencian Países Bajos y Singapur respecto a coordinación de sistema y dashboards de habilidades?\n\nA: Países Bajos pone énfasis en sus directrices específicas y habilitadores (según el documento), mientras Singapur prioriza mecanismos complementarios en el mismo eje. Ambos comparten metas de calidad y pertinencia, pero difieren en gobernanza, financiamiento y velocidad de adopción.\n\nVariantes:\n- Compara enfoques de Países Bajos y Singapur en coordinación de sistema y dashboards de habilidades\n- ¿Qué ventajas y trade-offs muestran Países Bajos y Singapur en coordinación de sistema y dashboards de habilidades?\n- ¿Qué lecciones aplicables a UDALBA surgen del contraste entre Países Bajos y Singapur?\n\n\nMeta:\n- País: Multi-país\n- Periodo: 2025\n- Sección: p.3–17\n- Audiencia: IES,policymakers,docentes\n- Documento: Directrices (paises).pdf\n- Tags: países-bajos, singapur, comparativa, coordinación-de-sistema-y-dashboards-de-habilidades",
      "tags": [
        "países-bajos",
        "singapur",
        "comparativa",
        "coordinación-de-sistema-y-dashboards-de-habilidades"
      ],
      "meta": {
        "country": "Multi-país",
        "timeframe": "2025",
        "section": "p.3–17",
        "audience": "IES,policymakers,docentes",
        "base": "directrices_paises_QA_50_enriquecido"
      }
    },
    {
      "id": "directrices_paises_QA_50_enriquecido__043",
      "title": "¿En qué se diferencian Francia y Estados Unidos respecto a transición ecológica y apertura científica?",
      "source": "Directrices (paises).pdf",
      "text": "Q: ¿En qué se diferencian Francia y Estados Unidos respecto a transición ecológica y apertura científica?\n\nA: Francia pone énfasis en sus directrices específicas y habilitadores (según el documento), mientras Estados Unidos prioriza mecanismos complementarios en el mismo eje. Ambos comparten metas de calidad y pertinencia, pero difieren en gobernanza, financiamiento y velocidad de adopción.\n\nVariantes:\n- Compara enfoques de Francia y Estados Unidos en transición ecológica y apertura científica\n- ¿Qué ventajas y trade-offs muestran Francia y Estados Unidos en transición ecológica y apertura científica?\n- ¿Qué lecciones aplicables a UDALBA surgen del contraste entre Francia y Estados Unidos?\n\n\nMeta:\n- País: Multi-país\n- Periodo: 2025\n- Sección: p.3–17\n- Audiencia: IES,policymakers,docentes\n- Documento: Directrices (paises).pdf\n- Tags: francia, estados-unidos, comparativa, transición-ecológica-y-apertura-científica",
      "tags": [
        "francia",
        "estados-unidos",
        "comparativa",
        "transición-ecológica-y-apertura-científica"
      ],
      "meta": {
        "country": "Multi-país",
        "timeframe": "2025",
        "section": "p.3–17",
        "audience": "IES,policymakers,docentes",
        "base": "directrices_paises_QA_50_enriquecido"
      }
    },
    {
      "id": "directrices_paises_QA_50_enriquecido__044",
      "title": "¿En qué se diferencian Reino Unido y Alemania respecto a formación docente e innovación escalable?",
      "source": "Directrices (paises).pdf",
      "text": "Q: ¿En qué se diferencian Reino Unido y Alemania respecto a formación docente e innovación escalable?\n\nA: Reino Unido pone énfasis en sus directrices específicas y habilitadores (según el documento), mientras Alemania prioriza mecanismos complementarios en el mismo eje. Ambos comparten metas de calidad y pertinencia, pero difieren en gobernanza, financiamiento y velocidad de adopción.\n\nVariantes:\n- Compara enfoques de Reino Unido y Alemania en formación docente e innovación escalable\n- ¿Qué ventajas y trade-offs muestran Reino Unido y Alemania en formación docente e innovación escalable?\n- ¿Qué lecciones aplicables a UDALBA surgen del contraste entre Reino Unido y Alemania?\n\n\nMeta:\n- País: Multi-país\n- Periodo: 2025\n- Sección: p.3–17\n- Audiencia: IES,policymakers,docentes\n- Documento: Directrices (paises).pdf\n- Tags: reino-unido, alemania, comparativa, formación-docente-e-innovación-escalable",
      "tags": [
        "reino-unido",
        "alemania",
        "comparativa",
        "formación-docente-e-innovación-escalable"
      ],
      "meta": {
        "country": "Multi-país",
        "timeframe": "2025",
        "section": "p.3–17",
        "audience": "IES,policymakers,docentes",
        "base": "directrices_paises_QA_50_enriquecido"
      }
    },
    {
      "id": "directrices_paises_QA_50_enriquecido__045",
      "title": "¿En qué se diferencian Singapur y Reino Unido respecto a política de IA en docencia (NUS) vs. QAA/OfS?",
      "source": "Directrices (paises).pdf",
      "text": "Q: ¿En qué se diferencian Singapur y Reino Unido respecto a política de IA en docencia (NUS) vs. QAA/OfS?\n\nA: Singapur pone énfasis en sus directrices específicas y habilitadores (según el documento), mientras Reino Unido prioriza mecanismos complementarios en el mismo eje. Ambos comparten metas de calidad y pertinencia, pero difieren en gobernanza, financiamiento y velocidad de adopción.\n\nVariantes:\n- Compara enfoques de Singapur y Reino Unido en política de IA en docencia (NUS) vs. QAA/OfS\n- ¿Qué ventajas y trade-offs muestran Singapur y Reino Unido en política de IA en docencia (NUS) vs. QAA/OfS?\n- ¿Qué lecciones aplicables a UDALBA surgen del contraste entre Singapur y Reino Unido?\n\n\nMeta:\n- País: Multi-país\n- Periodo: 2025\n- Sección: p.3–17\n- Audiencia: IES,policymakers,docentes\n- Documento: Directrices (paises).pdf\n- Tags: singapur, reino-unido, comparativa, política-de-IA-en-docencia-(NUS)-vs.-QAA/OfS",
      "tags": [
        "singapur",
        "reino-unido",
        "comparativa",
        "política-de-IA-en-docencia-(NUS)-vs.-QAA/OfS"
      ],
      "meta": {
        "country": "Multi-país",
        "timeframe": "2025",
        "section": "p.3–17",
        "audience": "IES,policymakers,docentes",
        "base": "directrices_paises_QA_50_enriquecido"
      }
    },
    {
      "id": "directrices_paises_QA_50_enriquecido__046",
      "title": "¿En qué se diferencian Países Bajos y Francia respecto a infraestructura digital común y plataformas nacionales?",
      "source": "Directrices (paises).pdf",
      "text": "Q: ¿En qué se diferencian Países Bajos y Francia respecto a infraestructura digital común y plataformas nacionales?\n\nA: Países Bajos pone énfasis en sus directrices específicas y habilitadores (según el documento), mientras Francia prioriza mecanismos complementarios en el mismo eje. Ambos comparten metas de calidad y pertinencia, pero difieren en gobernanza, financiamiento y velocidad de adopción.\n\nVariantes:\n- Compara enfoques de Países Bajos y Francia en infraestructura digital común y plataformas nacionales\n- ¿Qué ventajas y trade-offs muestran Países Bajos y Francia en infraestructura digital común y plataformas nacionales?\n- ¿Qué lecciones aplicables a UDALBA surgen del contraste entre Países Bajos y Francia?\n\n\nMeta:\n- País: Multi-país\n- Periodo: 2025\n- Sección: p.3–17\n- Audiencia: IES,policymakers,docentes\n- Documento: Directrices (paises).pdf\n- Tags: países-bajos, francia, comparativa, infraestructura-digital-común-y-plataformas-nacionales",
      "tags": [
        "países-bajos",
        "francia",
        "comparativa",
        "infraestructura-digital-común-y-plataformas-nacionales"
      ],
      "meta": {
        "country": "Multi-país",
        "timeframe": "2025",
        "section": "p.3–17",
        "audience": "IES,policymakers,docentes",
        "base": "directrices_paises_QA_50_enriquecido"
      }
    },
    {
      "id": "directrices_paises_QA_50_enriquecido__047",
      "title": "¿En qué se diferencian Estados Unidos y Países Bajos respecto a rol de community colleges vs. cooperación interuniversitaria?",
      "source": "Directrices (paises).pdf",
      "text": "Q: ¿En qué se diferencian Estados Unidos y Países Bajos respecto a rol de community colleges vs. cooperación interuniversitaria?\n\nA: Estados Unidos pone énfasis en sus directrices específicas y habilitadores (según el documento), mientras Países Bajos prioriza mecanismos complementarios en el mismo eje. Ambos comparten metas de calidad y pertinencia, pero difieren en gobernanza, financiamiento y velocidad de adopción.\n\nVariantes:\n- Compara enfoques de Estados Unidos y Países Bajos en rol de community colleges vs. cooperación interuniversitaria\n- ¿Qué ventajas y trade-offs muestran Estados Unidos y Países Bajos en rol de community colleges vs. cooperación interuniversitaria?\n- ¿Qué lecciones aplicables a UDALBA surgen del contraste entre Estados Unidos y Países Bajos?\n\n\nMeta:\n- País: Multi-país\n- Periodo: 2025\n- Sección: p.3–17\n- Audiencia: IES,policymakers,docentes\n- Documento: Directrices (paises).pdf\n- Tags: estados-unidos, países-bajos, comparativa, rol-de-community-colleges-vs.-cooperación-interuniversitaria",
      "tags": [
        "estados-unidos",
        "países-bajos",
        "comparativa",
        "rol-de-community-colleges-vs.-cooperación-interuniversitaria"
      ],
      "meta": {
        "country": "Multi-país",
        "timeframe": "2025",
        "section": "p.3–17",
        "audience": "IES,policymakers,docentes",
        "base": "directrices_paises_QA_50_enriquecido"
      }
    },
    {
      "id": "directrices_paises_QA_50_enriquecido__048",
      "title": "¿En qué se diferencian Alemania y Francia respecto a exigencia de excelencia investigativa vs. misiones PEPR?",
      "source": "Directrices (paises).pdf",
      "text": "Q: ¿En qué se diferencian Alemania y Francia respecto a exigencia de excelencia investigativa vs. misiones PEPR?\n\nA: Alemania pone énfasis en sus directrices específicas y habilitadores (según el documento), mientras Francia prioriza mecanismos complementarios en el mismo eje. Ambos comparten metas de calidad y pertinencia, pero difieren en gobernanza, financiamiento y velocidad de adopción.\n\nVariantes:\n- Compara enfoques de Alemania y Francia en exigencia de excelencia investigativa vs. misiones PEPR\n- ¿Qué ventajas y trade-offs muestran Alemania y Francia en exigencia de excelencia investigativa vs. misiones PEPR?\n- ¿Qué lecciones aplicables a UDALBA surgen del contraste entre Alemania y Francia?\n\n\nMeta:\n- País: Multi-país\n- Periodo: 2025\n- Sección: p.3–17\n- Audiencia: IES,policymakers,docentes\n- Documento: Directrices (paises).pdf\n- Tags: alemania, francia, comparativa, exigencia-de-excelencia-investigativa-vs.-misiones-PEPR",
      "tags": [
        "alemania",
        "francia",
        "comparativa",
        "exigencia-de-excelencia-investigativa-vs.-misiones-PEPR"
      ],
      "meta": {
        "country": "Multi-país",
        "timeframe": "2025",
        "section": "p.3–17",
        "audience": "IES,policymakers,docentes",
        "base": "directrices_paises_QA_50_enriquecido"
      }
    },
    {
      "id": "directrices_paises_QA_50_enriquecido__049",
      "title": "¿En qué se diferencian Reino Unido y Singapur respecto a modularidad financiada (LLE) vs. subsidios SkillsFuture?",
      "source": "Directrices (paises).pdf",
      "text": "Q: ¿En qué se diferencian Reino Unido y Singapur respecto a modularidad financiada (LLE) vs. subsidios SkillsFuture?\n\nA: Reino Unido pone énfasis en sus directrices específicas y habilitadores (según el documento), mientras Singapur prioriza mecanismos complementarios en el mismo eje. Ambos comparten metas de calidad y pertinencia, pero difieren en gobernanza, financiamiento y velocidad de adopción.\n\nVariantes:\n- Compara enfoques de Reino Unido y Singapur en modularidad financiada (LLE) vs. subsidios SkillsFuture\n- ¿Qué ventajas y trade-offs muestran Reino Unido y Singapur en modularidad financiada (LLE) vs. subsidios SkillsFuture?\n- ¿Qué lecciones aplicables a UDALBA surgen del contraste entre Reino Unido y Singapur?\n\n\nMeta:\n- País: Multi-país\n- Periodo: 2025\n- Sección: p.3–17\n- Audiencia: IES,policymakers,docentes\n- Documento: Directrices (paises).pdf\n- Tags: reino-unido, singapur, comparativa, modularidad-financiada-(LLE)-vs.-subsidios-SkillsFuture",
      "tags": [
        "reino-unido",
        "singapur",
        "comparativa",
        "modularidad-financiada-(LLE)-vs.-subsidios-SkillsFuture"
      ],
      "meta": {
        "country": "Multi-país",
        "timeframe": "2025",
        "section": "p.3–17",
        "audience": "IES,policymakers,docentes",
        "base": "directrices_paises_QA_50_enriquecido"
      }
    },
    {
      "id": "directrices_paises_QA_50_enriquecido__050",
      "title": "¿En qué se diferencian Estados Unidos y Singapur respecto a retención/analítica vs. cohortes de por vida?",
      "source": "Directrices (paises).pdf",
      "text": "Q: ¿En qué se diferencian Estados Unidos y Singapur respecto a retención/analítica vs. cohortes de por vida?\n\nA: Estados Unidos pone énfasis en sus directrices específicas y habilitadores (según el documento), mientras Singapur prioriza mecanismos complementarios en el mismo eje. Ambos comparten metas de calidad y pertinencia, pero difieren en gobernanza, financiamiento y velocidad de adopción.\n\nVariantes:\n- Compara enfoques de Estados Unidos y Singapur en retención/analítica vs. cohortes de por vida\n- ¿Qué ventajas y trade-offs muestran Estados Unidos y Singapur en retención/analítica vs. cohortes de por vida?\n- ¿Qué lecciones aplicables a UDALBA surgen del contraste entre Estados Unidos y Singapur?\n\n\nMeta:\n- País: Multi-país\n- Periodo: 2025\n- Sección: p.3–17\n- Audiencia: IES,policymakers,docentes\n- Documento: Directrices (paises).pdf\n- Tags: estados-unidos, singapur, comparativa, retención/analítica-vs.-cohortes-de-por-vida",
      "tags": [
        "estados-unidos",
        "singapur",
        "comparativa",
        "retención/analítica-vs.-cohortes-de-por-vida"
      ],
      "meta": {
        "country": "Multi-país",
        "timeframe": "2025",
        "section": "p.3–17",
        "audience": "IES,policymakers,docentes",
        "base": "directrices_paises_QA_50_enriquecido"
      }
    }
  ]
}